Workbook

Sheet MENU-OLD
A1: PHP DEVELOPER WISE ARN TGT VS ACV
A2: SL NO. | B2: DEVLOPER NAME | C2: DEVELOPER HISTORY | D2: TEAM LEAD | E2: LANGUAGE | F2: WORK LOCATION | G2: CONTACT | H2: TGT LAST DATE | I2: ACT LAST DATE | J2: PROB END DT | K2: T SAVE | L2: TOTAL | M2: =COUNTA(E3:E51) -> 36
A3: 1 | B3: Amit Mishra | C3: AMIT MISHRA'!A1 | D3: SANDEEP | E3: PHP | F3: OFFICE | G3: 90780 75643 | H3: =MAX('AMIT MISHRA'!$J$3:$J$1009) -> 45104 | I3: =MAX('AMIT MISHRA'!$L$3:$L$1009) -> 45096 | J3: =MAX('AMIT MISHRA'!$N$3:$N$1009) -> 45103 | K3: =+'AMIT MISHRA'!Q1 -> -79 | L3: PHP | M3: =COUNTIF($E$3:$E$52,L3) -> 22
A4: 2 | B4: Banita kumari swain | C4: BANITA KU SWAIN'!A1 | D4: SANDEEP | E4: PHP | F4: WFH | G4: 90780 84117 | H4: =MAX('BANITA KU SWAIN'!$K$3:$K$965) -> 45412 | I4: =MAX('BANITA KU SWAIN'!$M$3:$M$965) -> 45404 | J4: =MAX('BANITA KU SWAIN'!$O$3:$O$965) -> 45374 | K4: =+'BANITA KU SWAIN'!R1 -> -174 | L4: PYTHON | M4: =COUNTIF($E$3:$E$36,L4) -> 2
A5: 3 | B5: Gayatri Gochhayat | C5: GAYATRI GOCHHAYAT'!A1 | D5: SANDEEP | E5: PHP | F5: OFFICE | G5: 90780 84119 | H5: =MAX('GAYATRI GOCHHAYAT'!$K$3:$K$944) -> 45444 | I5: =MAX('GAYATRI GOCHHAYAT'!$M$3:$M$944) -> 45441 | J5: =MAX('GAYATRI GOCHHAYAT'!$O$3:$O$944) -> 45427 | K5: =+'GAYATRI GOCHHAYAT'!R1 -> -111 | L5: DESIGN | M5: =COUNTIF($E$3:$E$30,L5) -> 2
A6: 4 | B6: Jyotirani Panda | C6: JYOTIRANI PANDA'!A1 | D6: JYOTIRANI | E6: PHP | F6: OFFICE | G6: 74400 12310 | H6: =MAX('JYOTIRANI PANDA'!$K$3:$K$1114) -> 45448 | I6: =MAX('JYOTIRANI PANDA'!$M$3:$M$1114) -> 45442 | J6: =MAX('JYOTIRANI PANDA'!$O$3:$O$1114) -> 45436 | K6: =+'JYOTIRANI PANDA'!R1 -> -90 | L6: ANDROID | M6: =COUNTIF($E$3:$E$30,L6) -> 1
A7: 5 | B7: Krushna Ch Sahoo | C7: KRUSHNA CH SAHOO'!A1 | D7: KRUSHNA | E7: PHP | F7: OFFICE | G7: 90780 79614 | H7: =MAX('KRUSHNA CH SAHOO'!$J$3:$J$1031) -> 45037 | I7: =MAX('KRUSHNA CH SAHOO'!$L$3:$L$1031) -> 45077 | J7: =MAX('KRUSHNA CH SAHOO'!$N$3:$N$1031) -> 45058 | K7: =+'KRUSHNA CH SAHOO'!Q1 -> -49 | L7: Coordination | M7: =COUNTIF($E$3:$E$45,L7) -> 2
A8: 6 | B8: Puja Verma | C8: PUJA VERMA'!A1 | D8: JYOTIRANI | E8: PHP | F8: WFH | G8: 89269 73952 | H8: =MAX('PUJA VERMA'!$L$3:$L$1072) -> 45443 | I8: =MAX('PUJA VERMA'!$N$3:$N$1072) -> 45440 | J8: =MAX('PUJA VERMA'!$P$3:$P$1072) -> 45421 | K8: =+'PUJA VERMA'!S1 -> -189 | L8: Testing | M8: =COUNTIF($E$3:$E$48,L8) -> 0
A9: 7 | B9: Sandeep Jena | C9: SANDEEP JENA'!A1 | D9: SANDEEP | E9: PHP | F9: OFFICE | G9: 93376 42361 | H9: =MAX('SANDEEP JENA'!$J$3:$J$1001) -> 45105 | I9: =MAX('SANDEEP JENA'!$L$3:$L$1001) -> 45134 | J9: =MAX('SANDEEP JENA'!$N$3:$N$1001) -> 45108 | K9: =+'SANDEEP JENA'!Q1 -> -64 | L9: DOT NET | M9: =COUNTIF($E$3:$E$48,L9) -> 1
A10: 8 | B10: Snigdha S. Tripathy | C10: SNIGDHA S TRIPATHY'!A1 | D10: UMESH M | E10: PHP | F10: OFFICE | H10: =MAX('SNIGDHA S TRIPATHY'!$L$3:$L$1099) -> 45446 | I10: =MAX('SNIGDHA S TRIPATHY'!$N$3:$N$1099) -> 45442 | J10: =MAX('SNIGDHA S TRIPATHY'!$P$3:$P$1099) -> 45575 | K10: =+'SNIGDHA S TRIPATHY'!S1 -> 94
A11: 9 | B11: Souvik Paik | C11: SOUVIK PAIK'!A1 | D11: KRUSHNA | E11: PHP | F11: OFFICE | G11: 77354 13179 | H11: =MAX('SOUVIK PAIK'!$K$3:$K$1080) -> 45444 | I11: =MAX('SOUVIK PAIK'!$M$3:$M$1080) -> 45442 | J11: =MAX('SOUVIK PAIK'!$O$3:$O$1080) -> 45433 | K11: =+'SOUVIK PAIK'!R1 -> -42
A12: 10 | B12: Sradha Suman | C12: SRADHA S BEHERA'!A1 | D12: UMESH M | E12: PHP | F12: OFFICE | G12: 90780 74812 | H12: =MAX('SRADHA S BEHERA'!$K$163:$K$1155) -> 0 | I12: =MAX('SRADHA S BEHERA'!$M$5:$M$1155) -> 45435 | J12: =MAX('SRADHA S BEHERA'!$O$163:$O$1155) -> 0 | K12: =+'SRADHA S BEHERA'!R1 -> #VALUE!
A13: 11 | B13: Subham Behera | C13: SUBHAM BEHERA'!A1 | D13: KRUSHNA | E13: PHP | F13: OFFICE | G13: 63729 10485 | H13: =MAX('SUBHAM BEHERA -MIS'!$J$2:$J$1099) -> 45443 | I13: =MAX('SUBHAM BEHERA -MIS'!$L$2:$L$1099) -> 45436 | J13: =MAX('SUBHAM BEHERA -MIS'!$N$2:$N$1099) -> 45414 | K13: =+'SUBHAM BEHERA -MIS'!Q1 -> -92
A14: 12 | B14: Subhankar Tripathy | C14: SUBHANKAR TRIPATHY'!A1 | D14: SRADHA | E14: PHP | F14: WFH | H14: =MAX('SUBHANKAR TRIPATHY'!$J$2:$J$1004) -> 45166 | I14: =MAX('SUBHANKAR TRIPATHY'!$L$2:$L$1008) -> 45196 | J14: =MAX('SUBHANKAR TRIPATHY'!$N$2:$N$1008) -> 45166 | K14: =+'SUBHANKAR TRIPATHY'!Q1 -> -77
A15: 13 | B15: Sitesh moharana | C15: SITESH MOHARANA'!A1 | D15: SUBHAM | E15: PHP | F15: OFFICE | G15: 90780 79609 | H15: =MAX(SITESH!$K$2:$K$1094) -> 45570 | I15: =MAX(SITESH!$M$3:$M$1095) -> 45439 | J15: =MAX(SITESH!$O$3:$O$1095) -> 45413 | K15: =+SITESH!R1 -> -107
A16: 14 | B16: Satyabrata jati | C16: SATYABRATA JATI'!A1 | D16: SUBHAM | E16: PHP | F16: OFFICE | G16: 98533 83400 | H16: =MAX('SATYABRATA JATI-MIS'!$I$3:$I$1014) -> 45085 | I16: =MAX('SATYABRATA JATI-MIS'!$K$3:$K$1014) -> 45087 | J16: =MAX('SATYABRATA JATI-MIS'!$M$3:$M$1014) -> 45087 | K16: =+'SATYABRATA JATI-MIS'!P1 -> -12
A17: 15 | B17: Truptirani Behera | C17: TRUPTIRANI BEHERA'!A1 | D17: JYOTIRANI | E17: PHP | F17: OFFICE | G17: 90780 84118 | H17: =MAX('TRUPTIRANI BEHERA'!$I$3:$I$1010) -> 45126 | I17: =MAX('TRUPTIRANI BEHERA'!$L$3:$L$1010) -> 45156 | J17: =MAX('TRUPTIRANI BEHERA'!$N$3:$N$1010) -> 45092 | K17: ='TRUPTIRANI BEHERA'!Q1 -> -137
A18: 16 | B18: Umesh Majhi | C18: UMESH MAJHI'!A1 | D18: UMESH M | E18: PHP | F18: OFFICE | G18: https://t.me/umeshmjhi | H18: =MAX('UMESH MAJHI'!$K$7:$K$1082) -> 47268 | I18: =MAX('UMESH MAJHI'!$M$3:$M$1082) -> 45570 | J18: =MAX('UMESH MAJHI'!$O$7:$O$1082) -> 45540 | K18: =+'UMESH MAJHI'!R1 -> -39
A19: 17 | B19: Jyostnamayee Nayak | C19: JYOSTNAMAYEE NAYAK'!A1 | D19: GAYATRI | E19: PHP | F19: WFH | G19: 75048 89447 | H19: =MAX('JYOSTNAMAYEE NAYAK'!$J$3:$J$1019) -> 45435 | I19: =MAX('JYOSTNAMAYEE NAYAK'!$L$3:$L$1019) -> 45433 | J19: =MAX('JYOSTNAMAYEE NAYAK'!$N$3:$N$1019) -> 0 | K19: =+'JYOSTNAMAYEE NAYAK'!Q1 -> -201
A20: 18 | B20: Deenabandhu Dakua | C20: DEENABANDHU DAKUA'!A1 | D20: KRUSHNA | E20: DESIGN | F20: OFFICE | G20: 92373 03661 | H20: =MAX('DEENABANDHU DAKUA'!$K$2:$K$1131) -> 45444 | I20: =MAX('DEENABANDHU DAKUA'!$M$2:$M$1131) -> 45442 | J20: =MAX('DEENABANDHU DAKUA'!$O$2:$O$1131) -> 45421 | K20: =+'DEENABANDHU DAKUA'!R1 -> -96
A21: 19 | B21: Shakti Darshan Behera | D21: SANJIT | E21: DESIGN | F21: OFFICE
A22: 20 | B22: Miki Pradhan | E22: PHP | F22: OFFICE
A23: 21 | B23: Chetan Pradhan | E23: PHP | F23: OFFICE
A24: 22 | B24: Sreedhar Panigrahi | E24: PHP | F24: OFFICE
A25: 23 | B25: Chinmayee Majhi | E25: PHP | F25: OFFICE
A26: 24 | B26: Rakesh Kumar Dash | E26: PHP | F26: OFFICE
A27: 25 | B27: Sunila Kumar Dash | D27: UMESH M | E27: ANDROID | F27: OFFICE | G27: 90780 82272
A28: 27 | B28: Santosh Nayak | D28: SANJIT | E28: DOT NET | F28: OFFICE
A29: 27 | B29: Sibaprasad Behera | D29: AMIT M | E29: PYTHON | F29: OFFICE | G29: https://t.me/Sibaprasad65
A30: 28 | B30: Sunil Kumar Pattanaik | D30: AMIT M | E30: PYTHON | F30: WFH
A31: 30 | B31: Bibhudatta Triripathy | D31: AMIT M | E31: LEFT | F31: PYTHON
A32: 29 | B32: Chinmayee Panda | D32: AMIT M | E32: LEFT | F32: PYTHON
A33: 26 | B33: Prangyashree Das | D33: UMESH M | E33: LEFT | F33: ANDROID | G33: 92373 03662
A34: 31 | B34: Kalyani Priyadarshini | C34: KALYANI PRIYADARSHINI'!A1 | D34: UMESH M | E34: LEFT | F34: PHP | G34: 90780 75636 | H34: =MAX('KALYANI PRIYADARSHINI'!$J$3:$J$997) -> #REF! | I34: =MAX('KALYANI PRIYADARSHINI'!$L$3:$L$997) -> 44981 | J34: =MAX('KALYANI PRIYADARSHINI'!$N$3:$N$997) -> #REF! | K34: =+'KALYANI PRIYADARSHINI'!Q1 -> -45
A35: 32 | B35: Smita Mishra | C35: SMITA MISHRA'!A1 | D35: UMESH M | E35: LEFT | F35: PHP | H35: =MAX('SMITA MISHRA'!$H$3:$H$1002) -> 44865 | I35: =MAX('SMITA MISHRA'!$J$3:$J$1002) -> 0 | K35: =+'SMITA MISHRA'!M1 -> 0
A37: 33 | B37: Sushanta Mohapatra | E37: Coordination | F37: Office
A38: 34 | B38: Jitendra Kumar Jena | E38: FULL STACK | F38: Office
A39: 35 | B39: Rakesh Biswal | F39: LEFT
A40: 36 | B40: Soumya Mohapatra | E40: Coordination | F40: Office

Sheet DEVELOPER  INFO
A1: PHP DEVELOPER WISE DEVELOPMENT HISTORY
A2: SL NO. | B2: DEVLOPER NAME | C2: DEVELOPER HISTORY | D2: CATEGORY | E2: TEAM LEAD | F2: CURRENT TEAM | G2: LANGUAGE | H2: WORK LOCATION | I2: CONTACT | J2: WORK STAGE | K2: CURRENT WORK DETAIL | L2: TGT START DATE | M2: TG END DATE | N2: ACT START DATE | O2: T SAVE
A3: 1 | B3: RAHUL ROUT | E3: Jyotirani | G3: ANDROID | H3: OFFICE | I3: 83430 33946 | K3: Material Internal Request | L3: 45439 | M3: 45444 | N3: 45439
A4: 2 | B4: Gayatri Gochhayat | C4: GAYATRI GOCHHAYAT'!A1 | D4: ERP | E4: Gayatri | F4: MIS | G4: PHP | H4: OFFICE | I4: 90780 84119 | K4: counting for new pending approval | L4: 45440 | M4: 45444 | N4: 45439 | O4: ='GAYATRI GOCHHAYAT'!R1 -> -111
A5: 3 | B5: Sreedhar Panigrahi | C5: SREEDHAR | D5: ERP | E5: Gayatri | F5: MIS | G5: PHP | H5: OFFICE | K5: Pending count function creation with old sql query optimization of (Tender, Purchase, Expense) For new pending approval | L5: 45443 | M5: 45448 | N5: 45443 | O5: =SREEDHAR!R1 -> -63
A6: 4 | B6: Sailesh Dakua | D6: ERP | E6: Gayatri | F6: M RULES | G6: PHP | H6: OFFICE | K6: Output gst report of collection modules El listing, and analyse of the work. | L6: 45428 | M6: 45434 | N6: 45428 | O6: ='SAILESH DAKUA'!R1 -> -255
A7: 5 | B7: Rakesh Kumar Dash | C7: RAKESH KUMAR | D7: ERP | E7: Gayatri | F7: M RULES | G7: PHP | H7: OFFICE | K7: Solving issues of manage creditor and testing in dev | L7: 45443 | M7: 45446 | N7: 45443 | O7: =RAKESH!S3 -> -108
A8: 6 | B8: Jyostnamayee Nayak | C8: JYOSTNAMAYEE NAYAK'!A1 | D8: ERP | E8: Gayatri | F8: M RULES | G8: PHP | H8: WFH | I8: 75048 89447 | K8: Modification in getremark ,getapprovalremark,totalpendingcount function in approvalmatrix function page | L8: 45433 | M8: 45435 | N8: 45433 | O8: ='JYOSTNAMAYEE NAYAK'!Q1 -> -201
A9: 7 | B9: Sitesh moharana | C9: SITESH MOHARANA'!A1 | D9: ERP | E9: Jyotirani | F9: M RULES | G9: PHP | H9: OFFICE | I9: 90780 79609 | K9: Fraction of unit entry and calculation at time of PI to EI convertion. | L9: 45434 | M9: 45443 | N9: 45434 | O9: =SITESH!R1 -> -107
A10: 8 | B10: Snigdha S. Tripathy | C10: SNIGDHA S TRIPATHY'!A1 | D10: ERP | E10: Jyotirani | F10: M RULES | G10: PHP | H10: OFFICE | K10: All 5 module dpr to show attendance status of all employee in dpr section | L10: 45443 | M10: 45445 | N10: 45443 | O10: ='SNIGDHA S TRIPATHY'!S1 -> 94
A11: 9 | B11: Puja Verma | C11: PUJA VERMA'!A1 | D11: ERP | E11: Jyotirani | F11: M RULES | G11: PHP | H11: OFFICE | I11: 89269 73952 | K11: Order Receipt second phase functionality Implement | L11: 45440 | M11: 45443 | N11: 45440 | O11: ='PUJA VERMA'!S1 -> -189
A12: 10 | B12: Souvik Paik | C12: SOUVIK PAIK'!A1 | D12: API | E12: Jyotirani | F12: MIS & CMC | G12: PHP | H12: OFFICE | I12: 77354 13179 | K12: working on blogs section of iyro solar website | L12: 45443 | M12: 45444 | N12: 45443 | O12: ='SOUVIK PAIK'!R1 -> -42
A13: 11 | B13: Jyotirani Panda | C13: JYOTIRANI PANDA'!A1 | D13: ERP | E13: Jyotirani | F13: MIS & CMC | G13: PHP | H13: OFFICE | I13: 74400 12310 | K13: Close job order cancel part and vender assign part implementation. | L13: 45444 | M13: 45446 | N13: 45444 | O13: ='JYOTIRANI PANDA'!R1 -> -90
A14: 12 | B14: Chetan Pradhan | C14: CHETAN PRADHAN | D14: ERP | E14: Sradha Suman | F14: M RULES | G14: PHP | H14: OFFICE | K14: 2nd Stage implementation in expense module of payment request . | L14: 45442 | M14: 45447 | N14: 45442 | O14: =CHETAN!R1 -> -236
A15: 13 | B15: Jagannath Prasad Kar | D15: ERP | E15: Sradha Suman | G15: PHP | H15: OFFICE | K15: DEV COMPLETE | O15: =JAGANNATH!O1 -> -11
A16: 14 | B16: Sradha Suman | C16: SRADHA S BEHERA'!A1 | D16: ERP | E16: Sradha Suman | F16: MIS & CMC | G16: PHP | H16: OFFICE | I16: 90780 74812 | K16: Approval access change in multiple section in live server(manual attendance, Leave apply , Leave cancel, OD) | L16: 45441 | M16: 45442 | N16: 45442 | O16: ='SRADHA S BEHERA'!P3 -> 437
A17: 15 | B17: Subham Behera | C17: SUBHAM BEHERA'!A1 | D17: Manufecturing | E17: Sradha Suman | G17: PHP | H17: OFFICE | I17: 63729 10485 | K17: Store stock report of manufacturing project. | L17: 45440 | M17: 45443 | N17: 45441 | O17: ='SUBHAM BEHERA -MIS'!Q1 -> -92
A18: 16 | B18: Deenabandhu Dakua | C18: DEENABANDHU DAKUA'!A1 | D18: ERP | E18: Umesh Majhi | G18: DESIGN | H18: OFFICE | I18: 92373 03661 | K18: Designing of Factory Creation List page in manufacturing ERP. | L18: 45443 | M18: 45444 | N18: 45443 | O18: ='DEENABANDHU DAKUA'!R1 -> -96
A19: 17 | B19: Shakti Darshan Behera | C19: SHAKTI DESIGN | D19: ERP | E19: Sradha Suman | G19: DESIGN | H19: OFFICE | I19: 8908363107 | K19: DEV COMPLETE | O19: =SHAKTI!Q1 -> -187
A20: 18 | B20: Umesh Majhi | C20: UMESH MAJHI'!A1 | D20: ERP | E20: Umesh Majhi | F20: MIS & CMC | G20: PHP | H20: OFFICE | I20: https://t.me/umeshmjhi | K20: Implement parallel approval in PO Term in dev server | L20: 45443 | M20: 45444 | N20: 45443 | O20: ='UMESH MAJHI'!R1 -> -39
A21: 19 | B21: Dipti Ranjan Barik | C21: DEEPTI | D21: ERP | E21: Umesh Majhi | G21: PHP | H21: OFFICE | K21: Solving issue of Supplier Enquiry Page | L21: 45442 | M21: 45443 | N21: 45442 | O21: =DEEPTI!R2 -> -374
A22: 20 | B22: Chinmayee Majhi | C22: CHINMAYEE | D22: ERP | E22: Sanjaya Kumar Rout | F22: M RULES | G22: PHP | H22: OFFICE | K22: Backend change request work for ERP complain module | L22: 45439 | M22: 45444 | N22: 45440 | O22: ='CHINMAYEE M'!S2 -> -114
A23: 21 | B23: Satya Swarup | C23: SATYASWARUP | D23: ERP | E23: Sanjaya Kumar Rout | F23: M RULES | G23: PHP | H23: OFFICE | K23: Working on pending PO amounts and store PO amount as per discussion | L23: 45428 | M23: 45434 | N23: 45429 | O23: =SATYASWARUP!R2 -> -155
A24: 22 | B24: Bikash Pradhan | D24: ERP | E24: Sanjaya Kumar Rout | G24: PHP | H24: OFFICE | K24: Loan advance Dynamical approval and 2nd stage design | L24: 45444 | M24: 45447 | N24: 45444 | O24: =BIKASH!R2 -> -132
A25: 23 | B25: Sanjaya Kumar Rout | C25: SANJAY KU ROUT' | D25: ERP | E25: Sanjaya Kumar Rout | F25: MIS & CMC | G25: PHP | H25: OFFICE | K25: Function part modification in Deduction part with implement in Local System. | L25: 45434 | M25: 45435 | N25: 45434 | O25: ='SANJAY KU ROUT'!R2 -> -150
A26: 24 | B26: Jitendra Kumar Jena | G26: PHP | H26: OFFICE | I26: 9337642362
A27: 25 | B27: Santosh Nayak | D27: Moneymela | E27: Prabodh Dash | G27: DOT NET | H27: OFFICE | I27: 8882357266 | K27: Issue Resolve On Lender Management | L27: 45442 | M27: 45443 | N27: 45442 | O27: ='SANTOSH NAYAK'!R1 -> -72
A28: 26 | B28: Ratnajit Singh | D28: Moneymela | E28: Prabodh Dash | G28: DOT NET | H28: OFFICE | K28: Issue fixing In Employee Registration time Aadhar number field. Also in upload document field age proof name and in the drop down PAN Card | L28: 45444 | M28: 45444 | N28: 45444 | O28: ='RATNAJEET SINGH'!R1 -> -39
A29: 27 | B29: Sabita | E29: Prabodh Dash | G29: Coordination | H29: OFFICE | K29: MoneyMela Testing & ERP KT Acceptance
A30: 28 | B30: Sushanta Mohapatra | E30: Sushant Mohaptra | G30: Coordination | H30: OFFICE | I30: 74400 12108 | K30: Multi task
A31: 29 | B31: Soumya Mohapatra | E31: Sushant Mohaptra | G31: Coordination | H31: OFFICE | I31: 9078074801 | K31: Multi task
A32: 30 | B32: Janmejaya Giri | E32: Sushant Mohaptra | G32: Coordination | H32: OFFICE | K32: Multi task
A33: 31 | B33: Soumitra Kumar Sahoo | E33: Sushant Mohaptra | G33: Coordination | H33: OFFICE | K33: MoneyMela Testing & ERP KT Acceptance
A36: 1 | B36: Bunty Das | G36: RESIGNED | H36: Coordination
A37: 2 | B37: Pabitra Kumar Sethi | G37: RESIGNED | H37: Outsourcing | I37: 6372910479
A38: 3 | B38: Rakesh Biswal | G38: RESIGNED | H38: QA TESTING
A39: 4 | B39: Sunila Kumar Dash | G39: RESIGNED | H39: ANDROID | I39: 90780 82272 | J39: 1ST STAGE
A40: 5 | B40: Prangyashree Das | G40: RESIGNED | H40: ANDROID | I40: 92373 03662
A41: 6 | B41: Sunil Kumar Pattanaik | G41: RESIGNED | H41: PYTHON | I41: 8260839694
A42: 7 | B42: Bibhudatta Triripathy | G42: RESIGNED | H42: PYTHON
A43: 8 | B43: Chinmayee Panda | G43: RESIGNED | H43: PYTHON
A44: 9 | B44: Sibaprasad Behera | G44: RESIGNED | H44: PYTHON | I44: https://t.me/Sibaprasad65 | J44: 1ST STAGE
A45: 10 | B45: Kalyani Priyadarshini | C45: KALYANI PRIYADARSHINI'!A1 | G45: RESIGNED | H45: PHP | I45: 90780 75636
A46: 11 | B46: Smita Mishra | C46: SMITA MISHRA'!A1 | G46: RESIGNED | H46: PHP
A47: 12 | B47: Krushna Ch Sahoo | C47: KRUSHNA CH SAHOO'!A1 | G47: RESIGNED | H47: PHP | I47: 90780 79614 | J47: 1ST STAGE
A48: 13 | B48: Satyabrata jati | C48: SATYABRATA JATI'!A1 | G48: RESIGNED | H48: PHP | I48: 98533 83400 | J48: 2ND STAGE
A49: 14 | B49: Amit Mishra | C49: AMIT MISHRA'!A1 | G49: RESIGNED | H49: PHP | I49: 90780 75643 | J49: 2ND STAGE
A50: 15 | B50: Sandeep Jena | C50: SANDEEP JENA'!A1 | G50: RESIGNED | H50: PHP | I50: 93376 42361
A51: 16 | B51: Truptirani Behera | C51: TRUPTIRANI BEHERA'!A1 | F51: TTBP | G51: RESIGNED | H51: PHP | I51: 90780 84118
A52: 17 | B52: Subhankar Tripathy | C52: SUBHANKAR TRIPATHY'!A1 | F52: 2ND STAGE | G52: RESIGNED | H52: WFH
A53: 18 | B53: Banita kumari swain | C53: BANITA KU SWAIN'!A1 | G53: RESIGNED | H53: PHP/WFH | J53: 2ND STAGE
A54: 19 | B54: SOUMYA RANJAN | G54: RESIGNED | H54: PHP | J54: 2ND STAGE
B55: Miki Pradhan | C55: MIKI PRADHAN
B65: MODULE
B67: ASSET | C67: RENT
B68: COLLECTION | C68: RESCO | K68: DEVELOPER
B69: EXPENSE | C69: SOP | F69: GAYATRI | K69: MIKI PRADHAN | L69: SOUVIK PAIK
B70: FINANCE | C70: TELE CALLER | F70: UMESH MAJHI | K70: PUJA VERMA | L70: SRADHA SUMAN
B71: GENERAL | C71: TENDER | F71: JYOSTNAMAYEE | K71: RAKESH | L71: UMESH MAJHI
B72: HI-TOMI | C72: CRM | F72: BIKASH | K72: SAILESH | L72: SREEDHAR
B73: HR | C73: OTHER | F73: BANITA | K73: SAKTI | L73: SUBHAM
B74: LETTER | C74: IYRO SOLAR SALES | F74: CHETAN | K74: SANJAY KU ROUT
B75: MAINTENANCE | C75: IYRO ERP SALES | F75: CHINMAYEE | K75: SATYA SWARUP
B76: MASTER | F76: DEENABANDHU | K76: SITESH
B77: NEW | F77: JAGANNATH | K77: SNIGDHA
B78: PROJECT | F78: JYOTIRANI | K78: SOUMYA RANJAN
B79: PURCHASE
B82: STATUS | D82: WORK TYPE
B84: HOLD | D84: 1ST STAGE | E84: BACKEND CHANGE
B85: COMPLETE | D85: 2ND STAGE | E85: FORM
B86: DEV COMPLETE | D86: API | E86: live update
B87: INCOMPLETE | D87: IMPROVEMENT | E87: TABLE MURGING
B88: INPROGRESS | D88: ISSUE FIX | E88: THIRD
B89: LIVE | D89: LIVE | E89: R & D
B90: LIVE PENDING | D90: LIVE ISSUE | E90: MODIFICATION
B91: PARTLY | D91: LIVE WORK | E91: OTHER
B92: RETURN TO DEV | D92: MAINTENANCE | E92: TESTING ISSUE
B93: TESTING | D93: MIS
B94: TESTING HOLD | D94: OPERATIONAL ISSUES
B95: TO-DO

Sheet SANTOSH NAYAK
P1: =SUM(P3:P1055) -> 51 | Q1: =SUM(Q3:Q1055) -> 123 | R1: =SUM(R3:R1055) -> -72
A2: SL.NO. | B2: MODULE | C2: SUB MODULE | D2: ACTIVITIES | E2: WORK TYPE | F2: STATUS | G2: APPROVAL | H2: RESTRICTION | I2: NOTIFICATION | J2: TGT ST DATE | K2: TGT END DATE | L2: ACT ST DATE | M2: ACT END DATE | N2: PROB ST DT | O2: PROB END DT | P2: TGT DUR | Q2: ACT DUR | R2: T SAVING | S2: DELAY REASON STATUS
A3: 1 | B3: MONEYMELA | D3: Issue resolve in Borrower details is not showing in the view details. | F3: COMPLETE | J3: 45372 | K3: 45372 | L3: 45372 | M3: 45373 | N3: =L3 -> 45372 | O3: =N3+P3-1 -> 45372 | P3: =IF(IF(J4="",0,IF(K4="",0,K4-J4))="",0,K4-J4+1) -> 1 | Q3: =IF(L4="",0,IF(M4="",TODAY()-L4,M4-L4+1)) -> 2 | R3: =IF(Q3=0,0,P3-Q3) -> -1
A4: 2 | B4: MONEYMELA | D4: Issue fix of transation id ,Payment mode and deposit bank is not showing in the pending fund report | E4: ISSUE FIX | F4: COMPLETE | J4: 45373 | K4: 45373 | L4: 45373 | M4: 45374 | N4: =IF(L4="",IF(M3="",O3+1,M3+1),L4) -> 45373 | O4: =IF(N4="","",N4+P4-1) -> 45373 | P4: =IF(IF(J5="",0,IF(K5="",0,K5-J5))="",0,K5-J5+1) -> 1 | Q4: =IF(L5="",0,IF(M5="",TODAY()-L5,M5-L5+1)) -> 3 | R4: =IF(Q4=0,0,P4-Q4) -> -2
A5: 3 | B5: MONEYMELA | D5: After profile update when we go to the employee portal for approval in the lender profile some details are not fetched. (EX.Gender and company type) | E5: ISSUE FIX | F5: COMPLETE | J5: 45374 | K5: 45374 | L5: 45374 | M5: 45376 | N5: =IF(L5="",IF(M4="",O4+1,M4+1),L5) -> 45374 | O5: =IF(N5="","",N5+P5-1) -> 45374 | P5: =IF(IF(J5="",0,IF(K5="",0,K5-J5))="",0,K5-J5+1) -> 1 | Q5: =IF(L5="",0,IF(M5="",TODAY()-L5,M5-L5+1)) -> 3 | R5: =IF(Q5=0,0,P5-Q5) -> -2
A6: 4 | B6: MONEYMELA | D6: When we uploaded the document and save without entry some data, its not take submit, but the uploaded document is removed that time. | E6: ISSUE FIX | F6: COMPLETE | J6: 45378 | K6: 45378 | L6: 45378 | M6: 45379 | N6: =IF(L6="",IF(M5="",O5+1,M5+1),L6) -> 45378 | O6: =IF(N6="","",N6+P6-1) -> 45378 | P6: =IF(IF(J6="",0,IF(K6="",0,K6-J6))="",0,K6-J6+1) -> 1 | Q6: =IF(L6="",0,IF(M6="",TODAY()-L6,M6-L6+1)) -> 2 | R6: =IF(Q6=0,0,P6-Q6) -> -1
A7: 5 | B7: MONEYMELA | D7: There should be an admin in moneymela application .to provide access rights to different employees. | E7: IMPROVEMENT | F7: COMPLETE | J7: 45379 | K7: 45380 | L7: 45379 | M7: 45381 | N7: =IF(L7="",IF(M6="",O6+1,M6+1),L7) -> 45379 | O7: =IF(N7="","",N7+P7-1) -> 45380 | P7: =IF(IF(J7="",0,IF(K7="",0,K7-J7))="",0,K7-J7+1) -> 2 | Q7: =IF(L7="",0,IF(M7="",TODAY()-L7,M7-L7+1)) -> 3 | R7: =IF(Q7=0,0,P7-Q7) -> -1
A8: 6 | B8: MONEYMELA | D8: Create a new Page LoanFacility Document | E8: IMPROVEMENT | F8: COMPLETE | J8: 45381 | K8: 45381 | L8: 45381 | M8: 45381 | N8: =IF(L8="",IF(M7="",O7+1,M7+1),L8) -> 45381 | O8: =IF(N8="","",N8+P8-1) -> 45381 | P8: =IF(IF(J8="",0,IF(K8="",0,K8-J8))="",0,K8-J8+1) -> 1 | Q8: =IF(L8="",0,IF(M8="",TODAY()-L8,M8-L8+1)) -> 1 | R8: =IF(Q8=0,0,P8-Q8) -> 0
A9: 7 | B9: MONEYMELA | C9: SANCTION LETTER | D9: Working With Sanction Letter,Create a page for Sanction Letter | E9: IMPROVEMENT | F9: COMPLETE | J9: 45383 | K9: 45386 | L9: 45383 | M9: 45387 | N9: =IF(L9="",IF(M8="",O8+1,M8+1),L9) -> 45383 | O9: =IF(N9="","",N9+P9-1) -> 45386 | P9: =IF(IF(J9="",0,IF(K9="",0,K9-J9))="",0,K9-J9+1) -> 4 | Q9: =IF(L9="",0,IF(M9="",TODAY()-L9,M9-L9+1)) -> 5 | R9: =IF(Q9=0,0,P9-Q9) -> -1
A10: 8 | B10: MONEYMELA | C10: AGREEMENT LETTER | D10: Create New webpage Aggrement Letter | E10: IMPROVEMENT | F10: COMPLETE | J10: 45387 | K10: 45388 | L10: 45387 | M10: 45391 | N10: =IF(L10="",IF(M9="",O9+1,M9+1),L10) -> 45387 | O10: =IF(N10="","",N10+P10-1) -> 45388 | P10: =IF(IF(J10="",0,IF(K10="",0,K10-J10))="",0,K10-J10+1) -> 2 | Q10: =IF(L10="",0,IF(M10="",TODAY()-L10,M10-L10+1)) -> 5 | R10: =IF(Q10=0,0,P10-Q10) -> -3
A11: 9 | B11: MONEYMELA | C11: BANK MANDATE | D11: Create Master For Bank Mandate | E11: IMPROVEMENT | F11: COMPLETE | J11: 45391 | K11: 45391 | L11: 45391 | M11: 45392 | N11: =IF(L11="",IF(M10="",O10+1,M10+1),L11) -> 45391 | O11: =IF(N11="","",N11+P11-1) -> 45391 | P11: =IF(IF(J11="",0,IF(K11="",0,K11-J11))="",0,K11-J11+1) -> 1 | Q11: =IF(L11="",0,IF(M11="",TODAY()-L11,M11-L11+1)) -> 2 | R11: =IF(Q11=0,0,P11-Q11) -> -1
A12: 10 | B12: MONEYMELA | C12: MANAGE BANK | D12: Bank Details Shows and Update in Borrower Profile | E12: IMPROVEMENT | F12: COMPLETE | J12: 45392 | K12: 45393 | L12: 45392 | M12: 45394 | N12: =IF(L12="",IF(M11="",O11+1,M11+1),L12) -> 45392 | O12: =IF(N12="","",N12+P12-1) -> 45393 | P12: =IF(IF(J12="",0,IF(K12="",0,K12-J12))="",0,K12-J12+1) -> 2 | Q12: =IF(L12="",0,IF(M12="",TODAY()-L12,M12-L12+1)) -> 3 | R12: =IF(Q12=0,0,P12-Q12) -> -1
A13: 11 | B13: MONEYMELA | C13: MANAGE BANK | D13: Create Bank Mandate Approval Page | E13: IMPROVEMENT | F13: COMPLETE | J13: 45394 | K13: 45395 | L13: 45394 | M13: 45395 | N13: =IF(L13="",IF(M12="",O12+1,M12+1),L13) -> 45394 | O13: =IF(N13="","",N13+P13-1) -> 45395 | P13: =IF(IF(J13="",0,IF(K13="",0,K13-J13))="",0,K13-J13+1) -> 2 | Q13: =IF(L13="",0,IF(M13="",TODAY()-L13,M13-L13+1)) -> 2 | R13: =IF(Q13=0,0,P13-Q13) -> 0
A14: 12 | B14: MONEYMELA | C14: MANAGE BANK | D14: Bank Mandate Approval details update in Borrower page and reflect it approval management | E14: IMPROVEMENT | F14: COMPLETE | J14: 45395 | K14: 45398 | L14: 45395 | M14: 45399 | N14: =IF(L14="",IF(M13="",O13+1,M13+1),L14) -> 45395 | O14: =IF(N14="","",N14+P14-1) -> 45398 | P14: =IF(IF(J14="",0,IF(K14="",0,K14-J14))="",0,K14-J14+1) -> 4 | Q14: =IF(L14="",0,IF(M14="",TODAY()-L14,M14-L14+1)) -> 5 | R14: =IF(Q14=0,0,P14-Q14) -> -1
A15: 13 | B15: MONEYMELA | C15: MANAGE BANK | D15: Bank Mandate amount from Member will reflect when he/she paid EMI | E15: IMPROVEMENT | F15: COMPLETE | J15: 45399 | K15: 45400 | L15: 45399 | M15: 45404 | N15: =IF(L15="",IF(M14="",O14+1,M14+1),L15) -> 45399 | O15: =IF(N15="","",N15+P15-1) -> 45400 | P15: =IF(IF(J15="",0,IF(K15="",0,K15-J15))="",0,K15-J15+1) -> 2 | Q15: =IF(L15="",0,IF(M15="",TODAY()-L15,M15-L15+1)) -> 6 | R15: =IF(Q15=0,0,P15-Q15) -> -4
A16: 14 | B16: MONEYMELA | C16: MANAGE BANK | D16: Bank Mandate for Employee Portal | E16: IMPROVEMENT | F16: COMPLETE | J16: 45404 | K16: 45404 | L16: 45404 | M16: 45404 | N16: =IF(L16="",IF(M15="",O15+1,M15+1),L16) -> 45404 | O16: =IF(N16="","",N16+P16-1) -> 45404 | P16: =IF(IF(J16="",0,IF(K16="",0,K16-J16))="",0,K16-J16+1) -> 1 | Q16: =IF(L16="",0,IF(M16="",TODAY()-L16,M16-L16+1)) -> 1 | R16: =IF(Q16=0,0,P16-Q16) -> 0
A17: 15 | B17: MONEYMELA | D17: RND with Adhar API | E17: IMPROVEMENT | F17: COMPLETE | J17: 45405 | K17: 45405 | L17: 45405 | M17: 45406 | N17: =IF(L17="",IF(M16="",O16+1,M16+1),L17) -> 45405 | O17: =IF(N17="","",N17+P17-1) -> 45405 | P17: =IF(IF(J17="",0,IF(K17="",0,K17-J17))="",0,K17-J17+1) -> 1 | Q17: =IF(L17="",0,IF(M17="",TODAY()-L17,M17-L17+1)) -> 2 | R17: =IF(Q17=0,0,P17-Q17) -> -1
A18: 16 | B18: MONEYMELA | D18: Authenticate OTP from adhar and get all details RND | E18: IMPROVEMENT | F18: COMPLETE | J18: 45406 | K18: 45406 | L18: 45406 | M18: 45408 | N18: =IF(L18="",IF(M17="",O17+1,M17+1),L18) -> 45406 | O18: =IF(N18="","",N18+P18-1) -> 45406 | P18: =IF(IF(J18="",0,IF(K18="",0,K18-J18))="",0,K18-J18+1) -> 1 | Q18: =IF(L18="",0,IF(M18="",TODAY()-L18,M18-L18+1)) -> 3 | R18: =IF(Q18=0,0,P18-Q18) -> -2
A19: 17 | B19: MONEYMELA | D19: Create table structure and modified code for transaction | E19: IMPROVEMENT | F19: COMPLETE | J19: 45408 | K19: 45409 | L19: 45408 | M19: 45409 | N19: =IF(L19="",IF(M18="",O18+1,M18+1),L19) -> 45408 | O19: =IF(N19="","",N19+P19-1) -> 45409 | P19: =IF(IF(J19="",0,IF(K19="",0,K19-J19))="",0,K19-J19+1) -> 2 | Q19: =IF(L19="",0,IF(M19="",TODAY()-L19,M19-L19+1)) -> 2 | R19: =IF(Q19=0,0,P19-Q19) -> 0
A20: 18 | B20: MONEYMELA | D20: Get Details From PAN NO AND IFSC CODE RND | F20: COMPLETE | J20: 45411 | K20: 45411 | L20: 45411 | M20: 45412 | N20: =IF(L20="",IF(M19="",O19+1,M19+1),L20) -> 45411 | O20: =IF(N20="","",N20+P20-1) -> 45411 | P20: =IF(IF(J20="",0,IF(K20="",0,K20-J20))="",0,K20-J20+1) -> 1 | Q20: =IF(L20="",0,IF(M20="",TODAY()-L20,M20-L20+1)) -> 2 | R20: =IF(Q20=0,0,P20-Q20) -> -1
A21: 19 | B21: MONEYMELA | D21: working in lender data to be inserted for ledger | F21: COMPLETE | J21: 45412 | K21: 45412 | L21: 45412 | M21: 45413 | N21: =IF(L21="",IF(M20="",O20+1,M20+1),L21) -> 45412 | O21: =IF(N21="","",N21+P21-1) -> 45412 | P21: =IF(IF(J21="",0,IF(K21="",0,K21-J21))="",0,K21-J21+1) -> 1 | Q21: =IF(L21="",0,IF(M21="",TODAY()-L21,M21-L21+1)) -> 2 | R21: =IF(Q21=0,0,P21-Q21) -> -1
A22: 20 | B22: MONEYMELA | D22: Approval payment page has some calculation showing wrong . | E22: ISSUE FIX | F22: COMPLETE | J22: 45413 | K22: 45414 | L22: 45413 | N22: =IF(L22="",IF(M21="",O21+1,M21+1),L22) -> 45413 | O22: =IF(N22="","",N22+P22-1) -> 45414 | P22: =IF(IF(J22="",0,IF(K22="",0,K22-J22))="",0,K22-J22+1) -> 2 | Q22: =IF(L22="",0,IF(M22="",TODAY()-L22,M22-L22+1)) -> 35 | R22: =IF(Q22=0,0,P22-Q22) -> -33
A23: 21 | B23: MONEYMELA | D23: In Withdraw page data is store another table and call it at Ledger | E23: IMPROVEMENT | F23: COMPLETE | G23: 45416 | H23: 45416 | I23: 45416 | J23: 45416 | K23: 45416 | L23: 45416 | M23: 45418 | N23: =IF(L23="",IF(M22="",O22+1,M22+1),L23) -> 45416 | O23: =IF(N23="","",N23+P23-1) -> 45416 | P23: =IF(IF(J23="",0,IF(K23="",0,K23-J23))="",0,K23-J23+1) -> 1 | Q23: =IF(L23="",0,IF(M23="",TODAY()-L23,M23-L23+1)) -> 3 | R23: =IF(Q23=0,0,P23-Q23) -> -2
A24: 22 | B24: MONEYMELA | D24: Create a new page for Ledger Report | E24: IMPROVEMENT | F24: COMPLETE | G24: 45418 | H24: 45419 | I24: 45418 | J24: 45418 | K24: 45419 | L24: 45418 | M24: 45419 | N24: =IF(L24="",IF(M23="",O23+1,M23+1),L24) -> 45418 | O24: =IF(N24="","",N24+P24-1) -> 45419 | P24: =IF(IF(J24="",0,IF(K24="",0,K24-J24))="",0,K24-J24+1) -> 2 | Q24: =IF(L24="",0,IF(M24="",TODAY()-L24,M24-L24+1)) -> 2 | R24: =IF(Q24=0,0,P24-Q24) -> 0
A25: 23 | B25: MONEYMELA | D25: Add Loan Page for adding new field and show it data grid. | E25: IMPROVEMENT | F25: COMPLETE | G25: 45420 | H25: 45420 | I25: 45420 | J25: 45420 | K25: 45420 | L25: 45420 | M25: 45421 | N25: =IF(L25="",IF(M24="",O24+1,M24+1),L25) -> 45420 | O25: =IF(N25="","",N25+P25-1) -> 45420 | P25: =IF(IF(J25="",0,IF(K25="",0,K25-J25))="",0,K25-J25+1) -> 1 | Q25: =IF(L25="",0,IF(M25="",TODAY()-L25,M25-L25+1)) -> 2 | R25: =IF(Q25=0,0,P25-Q25) -> -1
A26: 24 | B26: MONEYMELA | D26: Loan Approval Page Shows all Data . | E26: IMPROVEMENT | F26: COMPLETE | J26: 45421 | K26: 45421 | L26: 45421 | M26: 45422 | N26: =IF(L26="",IF(M25="",O25+1,M25+1),L26) -> 45421 | O26: =IF(N26="","",N26+P26-1) -> 45421 | P26: =IF(IF(J26="",0,IF(K26="",0,K26-J26))="",0,K26-J26+1) -> 1 | Q26: =IF(L26="",0,IF(M26="",TODAY()-L26,M26-L26+1)) -> 2 | R26: =IF(Q26=0,0,P26-Q26) -> -1
A27: 25 | B27: MONEYMELA | D27: Correct Data is not coming in Lender Transaction Report | E27: ISSUE FIX | F27: COMPLETE | J27: 45422 | K27: 45422 | L27: 45422 | M27: 45426 | N27: =IF(L27="",IF(M26="",O26+1,M26+1),L27) -> 45422 | O27: =IF(N27="","",N27+P27-1) -> 45422 | P27: =IF(IF(J27="",0,IF(K27="",0,K27-J27))="",0,K27-J27+1) -> 1 | Q27: =IF(L27="",0,IF(M27="",TODAY()-L27,M27-L27+1)) -> 5 | R27: =IF(Q27=0,0,P27-Q27) -> -4
A28: 26 | B28: MONEYMELA | D28: Issue Resolve From Lender Portal | E28: ISSUE FIX | F28: COMPLETE | J28: 45426 | K28: 45426 | L28: 45426 | M28: 45427 | N28: =IF(L28="",IF(M27="",O27+1,M27+1),L28) -> 45426 | O28: =IF(N28="","",N28+P28-1) -> 45426 | P28: =IF(IF(J28="",0,IF(K28="",0,K28-J28))="",0,K28-J28+1) -> 1 | Q28: =IF(L28="",0,IF(M28="",TODAY()-L28,M28-L28+1)) -> 2 | R28: =IF(Q28=0,0,P28-Q28) -> -1
A29: 27 | B29: MONEYMELA | D29: Dynamically CA certificate format to be uploaded. | E29: IMPROVEMENT | F29: COMPLETE | J29: 45427 | K29: 45427 | L29: 45427 | M29: 45428 | N29: =IF(L29="",IF(M28="",O28+1,M28+1),L29) -> 45427 | O29: =IF(N29="","",N29+P29-1) -> 45427 | P29: =IF(IF(J29="",0,IF(K29="",0,K29-J29))="",0,K29-J29+1) -> 1 | Q29: =IF(L29="",0,IF(M29="",TODAY()-L29,M29-L29+1)) -> 2 | R29: =IF(Q29=0,0,P29-Q29) -> -1
A30: 28 | B30: MONEYMELA | D30: Work in investment report section The total principal amt, Principal Received, Loan Status,risk category and remarks details showing wrong. | E30: ISSUE FIX | F30: COMPLETE | J30: 45428 | K30: 45428 | L30: 45428 | M30: 45429 | N30: =IF(L30="",IF(M29="",O29+1,M29+1),L30) -> 45428 | O30: =IF(N30="","",N30+P30-1) -> 45428 | P30: =IF(IF(J30="",0,IF(K30="",0,K30-J30))="",0,K30-J30+1) -> 1 | Q30: =IF(L30="",0,IF(M30="",TODAY()-L30,M30-L30+1)) -> 2 | R30: =IF(Q30=0,0,P30-Q30) -> -1
A31: 29 | B31: MONEYMELA | D31: ISSUE RESOLVE | E31: ISSUE FIX | F31: COMPLETE | J31: 45429 | K31: 45433 | L31: 45429 | M31: 45434 | N31: =IF(L31="",IF(M30="",O30+1,M30+1),L31) -> 45429 | O31: =IF(N31="","",N31+P31-1) -> 45433 | P31: =IF(IF(J31="",0,IF(K31="",0,K31-J31))="",0,K31-J31+1) -> 5 | Q31: =IF(L31="",0,IF(M31="",TODAY()-L31,M31-L31+1)) -> 6 | R31: =IF(Q31=0,0,P31-Q31) -> -1
A32: 30 | B32: MONEYMELA | D32: API Meeting for PAN AND ADHAAR at signzy and RND for integration | E32: OTHER | F32: COMPLETE | J32: 45434 | K32: 45435 | L32: 45434 | M32: 45436 | N32: =IF(L32="",IF(M31="",O31+1,M31+1),L32) -> 45434 | O32: =IF(N32="","",N32+P32-1) -> 45435 | P32: =IF(IF(J32="",0,IF(K32="",0,K32-J32))="",0,K32-J32+1) -> 2 | Q32: =IF(L32="",0,IF(M32="",TODAY()-L32,M32-L32+1)) -> 3 | R32: =IF(Q32=0,0,P32-Q32) -> -1
A33: 31 | B33: MONEYMELA | D33: Video KYC API Meeting From surepass and RND | E33: OTHER | F33: COMPLETE | J33: 45436 | K33: 45437 | L33: 45436 | M33: 45440 | N33: =IF(L33="",IF(M32="",O32+1,M32+1),L33) -> 45436 | O33: =IF(N33="","",N33+P33-1) -> 45437 | P33: =IF(IF(J33="",0,IF(K33="",0,K33-J33))="",0,K33-J33+1) -> 2 | Q33: =IF(L33="",0,IF(M33="",TODAY()-L33,M33-L33+1)) -> 5 | R33: =IF(Q33=0,0,P33-Q33) -> -3
A34: 32 | B34: MONEYMELA | D34: Employee Management Profile Page New Development | E34: IMPROVEMENT | F34: COMPLETE | J34: 45440 | K34: 45441 | L34: 45440 | M34: 45442
A35: 33 | B35: MONEYMELA | D35: Issue Resolve On Lender Management | E35: ISSUE FIX | F35: INPROGRESS | J35: 45442 | K35: 45443 | L35: 45442

Sheet RATNAJEET SINGH
P1: =SUM(P3:P1058) -> 57 | Q1: =SUM(Q3:Q1058) -> 96 | R1: =SUM(R3:R1058) -> -39
A2: SL.NO. | B2: MODULE | C2: SUB MODULE | D2: ACTIVITIES | E2: WORK TYPE | F2: STATUS | G2: APPROVAL | H2: RESTRICTION | I2: NOTIFICATION | J2: TGT ST DATE | K2: TGT END DATE | L2: ACT ST DATE | M2: ACT END DATE | N2: PROB ST DT | O2: PROB END DT | P2: TGT DUR | Q2: ACT DUR | R2: T SAVING | S2: DELAY REASON STATUS
A3: =ROW() - 3 -> 0 | B3: MONEYMELA | D3: Changing the new Databse and table name on new MoneyMelaP2P Application | E3: MODIFICATION | F3: COMPLETE | J3: 45358 | K3: 45358 | L3: 45358 | M3: 45364 | N3: =L3 -> 45358 | O3: =N3+P3-1 -> 45358 | P3: =IF(IF(J3="",0,IF(K3="",0,K3-J3))="",0,K3-J3+1) -> 1 | Q3: =IF(L3="",0,IF(M3="",TODAY()-L3,M3-L3+1)) -> 7 | R3: =IF(Q3=0,0,P3-Q3) -> -6
A4: =ROW() - 3 -> 1 | B4: MONEYMELA | D4: Photo refresh on Lender_UpdateProfile | E4: MODIFICATION | F4: COMPLETE | J4: 45374 | K4: 45376 | L4: 45374 | M4: 45376 | N4: =IF(L4="",IF(M3="",O3+1,M3+1),L4) -> 45374 | O4: =IF(N4="","",N4+P4-1) -> 45376 | P4: =IF(IF(J4="",0,IF(K4="",0,K4-J4))="",0,K4-J4+1) -> 3 | Q4: =IF(L4="",0,IF(M4="",TODAY()-L4,M4-L4+1)) -> 3 | R4: =IF(Q4=0,0,P4-Q4) -> 0
A5: =ROW() - 3 -> 2 | B5: MONEYMELA | D5: Photo remove when page refresh on UpdateProfile2 Page i.e for Borrower Profile Update | E5: MODIFICATION | F5: COMPLETE | J5: 45376 | K5: 45376 | L5: 45376 | M5: 45379 | N5: =IF(L5="",IF(M4="",O4+1,M4+1),L5) -> 45376 | O5: =IF(N5="","",N5+P5-1) -> 45376 | P5: =IF(IF(J5="",0,IF(K5="",0,K5-J5))="",0,K5-J5+1) -> 1 | Q5: =IF(L5="",0,IF(M5="",TODAY()-L5,M5-L5+1)) -> 4 | R5: =IF(Q5=0,0,P5-Q5) -> -3
A6: =ROW() - 3 -> 3 | B6: MONEYMELA | D6: Borrower and Lender Profile Page for replacing the Download button to Icon and change the place of icon | E6: MODIFICATION | F6: COMPLETE | J6: 45378 | K6: 45378 | L6: 45378 | M6: 45380 | N6: =IF(L6="",IF(M5="",O5+1,M5+1),L6) -> 45378 | O6: =IF(N6="","",N6+P6-1) -> 45378 | P6: =IF(IF(J6="",0,IF(K6="",0,K6-J6))="",0,K6-J6+1) -> 1 | Q6: =IF(L6="",0,IF(M6="",TODAY()-L6,M6-L6+1)) -> 3 | R6: =IF(Q6=0,0,P6-Q6) -> -2
A7: =ROW() - 3 -> 4 | B7: MONEYMELA | D7: Employee Management on Admin login on page Admin_EmployeeRegistration | E7: IMPROVEMENT | F7: COMPLETE | J7: 45380 | K7: 45381 | L7: 45381 | M7: 45383 | N7: =IF(L7="",IF(M6="",O6+1,M6+1),L7) -> 45381 | O7: =IF(N7="","",N7+P7-1) -> 45382 | P7: =IF(IF(J7="",0,IF(K7="",0,K7-J7))="",0,K7-J7+1) -> 2 | Q7: =IF(L7="",0,IF(M7="",TODAY()-L7,M7-L7+1)) -> 3 | R7: =IF(Q7=0,0,P7-Q7) -> -1
A8: =ROW() - 3 -> 5 | B8: MONEYMELA | D8: Approval Management Search & Edit | E8: IMPROVEMENT | F8: COMPLETE | J8: 45383 | K8: 45383 | L8: 45383 | M8: 45384 | N8: =IF(L8="",IF(M7="",O7+1,M7+1),L8) -> 45383 | O8: =IF(N8="","",N8+P8-1) -> 45383 | P8: =IF(IF(J8="",0,IF(K8="",0,K8-J8))="",0,K8-J8+1) -> 1 | Q8: =IF(L8="",0,IF(M8="",TODAY()-L8,M8-L8+1)) -> 2 | R8: =IF(Q8=0,0,P8-Q8) -> -1
A9: =ROW() - 3 -> 6 | B9: MONEYMELA | D9: Server Database MODIFICATION | E9: MODIFICATION | F9: COMPLETE | J9: 45384 | K9: 45385 | L9: 45384 | M9: 45386 | N9: =IF(L9="",IF(M8="",O8+1,M8+1),L9) -> 45384 | O9: =IF(N9="","",N9+P9-1) -> 45385 | P9: =IF(IF(J9="",0,IF(K9="",0,K9-J9))="",0,K9-J9+1) -> 2 | Q9: =IF(L9="",0,IF(M9="",TODAY()-L9,M9-L9+1)) -> 3 | R9: =IF(Q9=0,0,P9-Q9) -> -1
A10: =ROW() - 3 -> 7 | B10: MONEYMELA | D10: Database for Admin menu modification | E10: MODIFICATION | F10: COMPLETE | J10: 45386 | K10: 45386 | L10: 45386 | M10: 45386 | N10: =IF(L10="",IF(M9="",O9+1,M9+1),L10) -> 45386 | O10: =IF(N10="","",N10+P10-1) -> 45386 | P10: =IF(IF(J10="",0,IF(K10="",0,K10-J10))="",0,K10-J10+1) -> 1 | Q10: =IF(L10="",0,IF(M10="",TODAY()-L10,M10-L10+1)) -> 1 | R10: =IF(Q10=0,0,P10-Q10) -> 0
A11: =ROW() - 3 -> 8 | B11: MONEYMELA | D11: Employee Profile details after Employee login | E11: IMPROVEMENT | F11: COMPLETE | J11: 45387 | K11: 45388 | L11: 45387 | M11: 45390 | N11: =IF(L11="",IF(M10="",O10+1,M10+1),L11) -> 45387 | O11: =IF(N11="","",N11+P11-1) -> 45388 | P11: =IF(IF(J11="",0,IF(K11="",0,K11-J11))="",0,K11-J11+1) -> 2 | Q11: =IF(L11="",0,IF(M11="",TODAY()-L11,M11-L11+1)) -> 4 | R11: =IF(Q11=0,0,P11-Q11) -> -2
A12: =ROW() - 3 -> 9 | B12: MONEYMELA | D12: Admin EmployeeRegistration Page Validation | E12: IMPROVEMENT | F12: COMPLETE | J12: 45388 | K12: 45390 | L12: 45390 | M12: 45390 | N12: =IF(L12="",IF(M11="",O11+1,M11+1),L12) -> 45390 | O12: =IF(N12="","",N12+P12-1) -> 45392 | P12: =IF(IF(J12="",0,IF(K12="",0,K12-J12))="",0,K12-J12+1) -> 3 | Q12: =IF(L12="",0,IF(M12="",TODAY()-L12,M12-L12+1)) -> 1 | R12: =IF(Q12=0,0,P12-Q12) -> 2
A13: =ROW() - 3 -> 10 | B13: MONEYMELA | D13: Creat new login Page for Admin Login Page SA Login | E13: IMPROVEMENT | F13: COMPLETE | J13: 45390 | K13: 45391 | L13: 45390 | M13: 45391 | N13: =IF(L13="",IF(M12="",O12+1,M12+1),L13) -> 45390 | O13: =IF(N13="","",N13+P13-1) -> 45391 | P13: =IF(IF(J13="",0,IF(K13="",0,K13-J13))="",0,K13-J13+1) -> 2 | Q13: =IF(L13="",0,IF(M13="",TODAY()-L13,M13-L13+1)) -> 2 | R13: =IF(Q13=0,0,P13-Q13) -> 0
A14: =ROW() - 3 -> 11 | B14: MONEYMELA | D14: Creati only for Employee Login portal page i.e Moneymela_Login | E14: IMPROVEMENT | F14: COMPLETE | J14: 45391 | K14: 45392 | L14: 45391 | M14: 45393 | N14: =IF(L14="",IF(M13="",O13+1,M13+1),L14) -> 45391 | O14: =IF(N14="","",N14+P14-1) -> 45392 | P14: =IF(IF(J14="",0,IF(K14="",0,K14-J14))="",0,K14-J14+1) -> 2 | Q14: =IF(L14="",0,IF(M14="",TODAY()-L14,M14-L14+1)) -> 3 | R14: =IF(Q14=0,0,P14-Q14) -> -1
A15: 13 | B15: MONEYMELA | D15: Validation when he click Update on Profile Page for Borrower portal after approve from Admin . | E15: MODIFICATION | F15: COMPLETE | J15: 45393 | K15: 45393 | L15: 45393 | M15: 45394 | N15: =IF(L15="",IF(M14="",O14+1,M14+1),L15) -> 45393 | O15: =IF(N15="","",N15+P15-1) -> 45393 | P15: =IF(IF(J15="",0,IF(K15="",0,K15-J15))="",0,K15-J15+1) -> 1 | Q15: =IF(L15="",0,IF(M15="",TODAY()-L15,M15-L15+1)) -> 2 | R15: =IF(Q15=0,0,P15-Q15) -> -1
A16: 14 | B16: MONEYMELA | D16: Lender_UpdateProfile validation | E16: IMPROVEMENT | F16: COMPLETE | J16: 45394 | K16: 45394 | L16: 45394 | M16: 45395 | N16: =IF(L16="",IF(M15="",O15+1,M15+1),L16) -> 45394 | O16: =IF(N16="","",N16+P16-1) -> 45394 | P16: =IF(IF(J16="",0,IF(K16="",0,K16-J16))="",0,K16-J16+1) -> 1 | Q16: =IF(L16="",0,IF(M16="",TODAY()-L16,M16-L16+1)) -> 2 | R16: =IF(Q16=0,0,P16-Q16) -> -1
A17: 15 | B17: MONEYMELA | D17: Working on Lender_Profile page Validation | F17: COMPLETE | J17: 45397 | K17: 45397 | L17: 45398 | M17: 45398 | N17: =IF(L17="",IF(M16="",O16+1,M16+1),L17) -> 45398 | O17: =IF(N17="","",N17+P17-1) -> 45398 | P17: =IF(IF(J17="",0,IF(K17="",0,K17-J17))="",0,K17-J17+1) -> 1 | Q17: =IF(L17="",0,IF(M17="",TODAY()-L17,M17-L17+1)) -> 1 | R17: =IF(Q17=0,0,P17-Q17) -> 0
A18: 16 | B18: MONEYMELA | D18: Issue fixing on UpdateProfile2 on Borrower Profile | E18: ISSUE FIX | F18: COMPLETE | J18: 45398 | K18: 45398 | L18: 45398 | M18: 45399 | N18: =IF(L18="",IF(M17="",O17+1,M17+1),L18) -> 45398 | O18: =IF(N18="","",N18+P18-1) -> 45398 | P18: =IF(IF(J18="",0,IF(K18="",0,K18-J18))="",0,K18-J18+1) -> 1 | Q18: =IF(L18="",0,IF(M18="",TODAY()-L18,M18-L18+1)) -> 2 | R18: =IF(Q18=0,0,P18-Q18) -> -1
A19: 17 | B19: MONEYMELA | D19: Issue fixing on Admin Portal Loan Management | E19: ISSUE FIX | F19: COMPLETE | J19: 45399 | K19: 45400 | L19: 45399 | M19: 45401 | N19: =IF(L19="",IF(M18="",O18+1,M18+1),L19) -> 45399 | O19: =IF(N19="","",N19+P19-1) -> 45400 | P19: =IF(IF(J19="",0,IF(K19="",0,K19-J19))="",0,K19-J19+1) -> 2 | Q19: =IF(L19="",0,IF(M19="",TODAY()-L19,M19-L19+1)) -> 3 | R19: =IF(Q19=0,0,P19-Q19) -> -1
A20: 18 | B20: MONEYMELA | D20: User right for Bank Mandate | E20: IMPROVEMENT | F20: COMPLETE | J20: 45401 | K20: 45401 | L20: 45401 | M20: 45404 | N20: =IF(L20="",IF(M19="",O19+1,M19+1),L20) -> 45401 | O20: =IF(N20="","",N20+P20-1) -> 45401 | P20: =IF(IF(J20="",0,IF(K20="",0,K20-J20))="",0,K20-J20+1) -> 1 | Q20: =IF(L20="",0,IF(M20="",TODAY()-L20,M20-L20+1)) -> 4 | R20: =IF(Q20=0,0,P20-Q20) -> -3
A21: 19 | B21: MONEYMELA | D21: Bank Mandate for Lender Portal | E21: IMPROVEMENT | F21: COMPLETE | J21: 45402 | K21: 45405 | L21: 45402 | M21: 45406 | N21: =IF(L21="",IF(M20="",O20+1,M20+1),L21) -> 45402 | O21: =IF(N21="","",N21+P21-1) -> 45405 | P21: =IF(IF(J21="",0,IF(K21="",0,K21-J21))="",0,K21-J21+1) -> 4 | Q21: =IF(L21="",0,IF(M21="",TODAY()-L21,M21-L21+1)) -> 5 | R21: =IF(Q21=0,0,P21-Q21) -> -1
A22: 20 | B22: MONEYMELA | D22: Issue resolve on Admin_Loan_Registration page on Employee Portal | E22: ISSUE FIX | F22: COMPLETE | J22: 45406 | K22: 45406 | L22: 45406 | M22: 45407 | N22: =IF(L22="",IF(M21="",O21+1,M21+1),L22) -> 45406 | O22: =IF(N22="","",N22+P22-1) -> 45406 | P22: =IF(IF(J22="",0,IF(K22="",0,K22-J22))="",0,K22-J22+1) -> 1 | Q22: =IF(L22="",0,IF(M22="",TODAY()-L22,M22-L22+1)) -> 2 | R22: =IF(Q22=0,0,P22-Q22) -> -1
A23: 21 | B23: MONEYMELA | D23: Issue fixing on Make Payment on Lender portal | E23: ISSUE FIX | F23: COMPLETE | J23: 45407 | K23: 45407 | L23: 45408 | M23: 45408 | N23: =IF(L23="",IF(M22="",O22+1,M22+1),L23) -> 45408 | O23: =IF(N23="","",N23+P23-1) -> 45408 | P23: =IF(IF(J23="",0,IF(K23="",0,K23-J23))="",0,K23-J23+1) -> 1 | Q23: =IF(L23="",0,IF(M23="",TODAY()-L23,M23-L23+1)) -> 1 | R23: =IF(Q23=0,0,P23-Q23) -> 0
A24: 22 | B24: MONEYMELA | D24: Working for photo issue Bank Statement PAN card issue on Admin/Approval Management/ Loan approval | E24: ISSUE FIX | F24: COMPLETE | J24: 45408 | K24: 45408 | L24: 45408 | M24: 45408 | N24: =IF(L24="",IF(M23="",O23+1,M23+1),L24) -> 45408 | O24: =IF(N24="","",N24+P24-1) -> 45408 | P24: =IF(IF(J24="",0,IF(K24="",0,K24-J24))="",0,K24-J24+1) -> 1 | Q24: =IF(L24="",0,IF(M24="",TODAY()-L24,M24-L24+1)) -> 1 | R24: =IF(Q24=0,0,P24-Q24) -> 0
A25: 23 | B25: MONEYMELA | D25: Issue resolving on Pending Form report on Support Management Admin Portal | E25: ISSUE FIX | F25: COMPLETE | J25: 45408 | K25: 45408 | L25: 45408 | M25: 45409 | N25: =IF(L25="",IF(M24="",O24+1,M24+1),L25) -> 45408 | O25: =IF(N25="","",N25+P25-1) -> 45408 | P25: =IF(IF(J25="",0,IF(K25="",0,K25-J25))="",0,K25-J25+1) -> 1 | Q25: =IF(L25="",0,IF(M25="",TODAY()-L25,M25-L25+1)) -> 2 | R25: =IF(Q25=0,0,P25-Q25) -> -1
A26: 24 | B26: MONEYMELA | D26: Find out the path for uploaded photo for entire solution | E26: IMPROVEMENT | F26: COMPLETE | J26: 45411 | K26: 45411 | L26: 45411 | M26: 45412 | N26: =IF(L26="",IF(M25="",O25+1,M25+1),L26) -> 45411 | O26: =IF(N26="","",N26+P26-1) -> 45411 | P26: =IF(IF(J26="",0,IF(K26="",0,K26-J26))="",0,K26-J26+1) -> 1 | Q26: =IF(L26="",0,IF(M26="",TODAY()-L26,M26-L26+1)) -> 2 | R26: =IF(Q26=0,0,P26-Q26) -> -1
A27: 25 | B27: MONEYMELA | D27: Issue fixing resolve from Website | E27: IMPROVEMENT | F27: COMPLETE | J27: 45413 | K27: 45414 | L27: 45413 | M27: 45416 | N27: =IF(L27="",IF(M26="",O26+1,M26+1),L27) -> 45413 | O27: =IF(N27="","",N27+P27-1) -> 45414 | P27: =IF(IF(J27="",0,IF(K27="",0,K27-J27))="",0,K27-J27+1) -> 2 | Q27: =IF(L27="",0,IF(M27="",TODAY()-L27,M27-L27+1)) -> 4 | R27: =IF(Q27=0,0,P27-Q27) -> -2
A28: 26 | B28: MONEYMELA | D28: Update_Profile2 page on Borrower portal for modifying to save the image | E28: IMPROVEMENT | F28: COMPLETE | J28: 45420 | K28: 45421 | L28: 45420 | M28: 45422 | N28: =IF(L28="",IF(M27="",O27+1,M27+1),L28) -> 45420 | O28: =IF(N28="","",N28+P28-1) -> 45421 | P28: =IF(IF(J28="",0,IF(K28="",0,K28-J28))="",0,K28-J28+1) -> 2 | Q28: =IF(L28="",0,IF(M28="",TODAY()-L28,M28-L28+1)) -> 3 | R28: =IF(Q28=0,0,P28-Q28) -> -1
A29: 27 | B29: MONEYMELA | D29: Issue fixing website (As per Arpita) | E29: ISSUE FIX | F29: COMPLETE | J29: 45422 | K29: 45422 | L29: 45422 | M29: 45426 | N29: =IF(L29="",IF(M28="",O28+1,M28+1),L29) -> 45422 | O29: =IF(N29="","",N29+P29-1) -> 45422 | P29: =IF(IF(J29="",0,IF(K29="",0,K29-J29))="",0,K29-J29+1) -> 1 | Q29: =IF(L29="",0,IF(M29="",TODAY()-L29,M29-L29+1)) -> 5 | R29: =IF(Q29=0,0,P29-Q29) -> -4
... A36: 34 | B36: MONEYMELA | D36: Issue fixing on Borrower portal & Working on Modifying Bank Account Details adding some field as per required in Borrower Portal | E36: ISSUE FIX | F36: COMPLETE | J36: 45435 | K36: 45439 | L36: 45435 | M36: 45440 | N36: =IF(L36="",IF(M35="",O35+1,M35+1),L36) -> 45435 | O36: =IF(N36="","",N36+P36-1) -> 45439 | P36: =IF(IF(J36="",0,IF(K36="",0,K36-J36))="",0,K36-J36+1) -> 5 | Q36: =IF(L36="",0,IF(M36="",TODAY()-L36,M36-L36+1)) -> 6 | R36: =IF(Q36=0,0,P36-Q36) -> -1
A37: 35 | B37: MONEYMELA | D37: Working on MemberRegisteration and InvestorRegisteration search & Edit on Admin portal | E37: IMPROVEMENT | F37: COMPLETE | J37: 45440 | K37: 45440 | L37: 45440 | M37: 45442
A38: 36 | B38: MONEYMELA | D38: Issue fixing in Admin_EmployeeRegistration page | E38: ISSUE FIX | F38: COMPLETE | J38: 45441 | K38: 45441 | L38: 45442 | M38: 45442
A39: 37 | B39: MONEYMELA | D39: Modifying in Member Registeration for dropdown value at Admin portal | F39: COMPLETE | J39: 45442 | K39: 45442 | L39: 45443 | M39: 45443
A40: 38 | B40: MONEYMELA | D40: Lender, Borrower portal for modifying the dropdown details and checking validation | E40: IMPROVEMENT | F40: COMPLETE | J40: 45443 | K40: 45443 | L40: 45443 | M40: 45443
A41: 39 | B41: MONEYMELA | D41: Issue fixing In Employee Registration time Aadhar number field. Also in upload document field age proof name and in the drop down PAN Card | E41: ISSUE FIX | F41: INPROGRESS | J41: 45444 | K41: 45444 | L41: 45444

Sheet CHETAN
P1: =SUM(P3:P1009) -> 264 | Q1: =SUM(Q3:Q1009) -> 500 | R1: =SUM(R3:R1009) -> -236
A2: SL.NO. | B2: MODULE | C2: SUB MODULE | D2: ACTIVITIES | E2: WORK TYPE | F2: STATUS | G2: APPROVAL | H2: RESTRICTION | I2: NOTIFICATION | J2: TGT ST DATE | K2: TGT END DATE | L2: ACT ST DATE | M2: ACT END DATE | N2: PROB ST DT | O2: PROB END DT | P2: TGT DUR | Q2: ACT DUR | R2: T SAVING | S2: DELAY REASON STATUS
A3: =ROW() - ROW($A$30) + 28 -> 1 | B3: MASTER DATA | C3: LOCAL SUPPLIER(GENERAL) | D3: Manage Local Supplier Listing Page As Per 2Nd Phase Wth Dynamic Approval | E3: 2ND STAGE IMPLEMENTATION | F3: LIVE | J3: 45072 | K3: 45075 | L3: 45072 | M3: 45136 | N3: =L3 -> 45072 | O3: =N3+P3-1 -> 45075 | P3: =IF(IF(J3="",0,IF(K3="",0,K3-J3))="",0,K3-J3+1) -> 4 | Q3: =IF(L3="",0,IF(M3="",TODAY()-L3,M3-L3+1)) -> 65 | R3: =IF(Q3=0,0,P3-Q3) -> -61
A4: =ROW() - ROW($A$30) + 28 -> 2 | B4: NEW | C4: Format Control Module | D4: Format Control Module | E4: FORM | F4: TESTING | J4: 45100 | K4: 45135 | L4: 45100 | M4: 45135 | N4: =IF(L4="",IF(M3="",O3+1,M3+1),L4) -> 45100 | O4: =+N4+P4-1 -> 45135 | P4: =IF(IF(J4="",0,IF(K4="",0,K4-J4))="",0,K4-J4+1) -> 36 | Q4: =IF(L4="",0,IF(M4="",TODAY()-L4,M4-L4+1)) -> 36 | R4: =IF(Q4=0,0,P4-Q4) -> 0 | S4: IT'S IN LIVE SERVER AND ASSIGNED MANAGMENT FOR TESTING
A5: =ROW() - ROW($A$30) + 28 -> 3 | B5: MASTER DATA | C5: LOCAL SUPPLIER(GENERAL) | D5: Error and Issue fix in mange local supplier,Validation in add local supplier,mange local supplier process guide documentation | E5: ISSUE | F5: LIVE | J5: 45135 | K5: 45163 | L5: 45135 | M5: 45168 | N5: =IF(L5="",IF(M4="",O4+1,M4+1),L5) -> 45135 | O5: =+N5+P5-1 -> 45163 | P5: =IF(IF(J5="",0,IF(K5="",0,K5-J5))="",0,K5-J5+1) -> 29 | Q5: =IF(L5="",0,IF(M5="",TODAY()-L5,M5-L5+1)) -> 34 | R5: =IF(Q5=0,0,P5-Q5) -> -5
A6: =ROW() - ROW($A$30) + 28 -> 4 | B6: MASTER DATA | C6: MAMAGE LOCATION(PROJECT) | D6: State, District, Block, Gramapanchayat | E6: 2ND STAGE IMPLEMENTATION | F6: LIVE | J6: 45167 | K6: 45187 | L6: 45168 | M6: 45215 | N6: =IF(L6="",IF(M5="",O5+1,M5+1),L6) -> 45168 | O6: =+N6+P6-1 -> 45188 | P6: =IF(IF(J6="",0,IF(K6="",0,K6-J6))="",0,K6-J6+1) -> 21 | Q6: =IF(L6="",0,IF(M6="",TODAY()-L6,M6-L6+1)) -> 48 | R6: =IF(Q6=0,0,P6-Q6) -> -27
A7: =ROW() - ROW($A$30) + 28 -> 5 | B7: MASTER DATA | C7: CATEGORY AND SUB CATEGORY(PROJECT) | D7: Manage Category and sub category new design and dynamic approval. | E7: 2ND STAGE IMPLEMENTATION | F7: LIVE | J7: 45194 | K7: 45202 | L7: 45195 | M7: 45205 | N7: =IF(L7="",IF(M6="",O6+1,M6+1),L7) -> 45195 | O7: =+N7+P7-1 -> 45203 | P7: =IF(IF(J7="",0,IF(K7="",0,K7-J7))="",0,K7-J7+1) -> 9 | Q7: =IF(L7="",0,IF(M7="",TODAY()-L7,M7-L7+1)) -> 11 | R7: =IF(Q7=0,0,P7-Q7) -> -2
A8: =ROW() - ROW($A$30) + 28 -> 6 | B8: MASTER DATA | C8: MANAGE GROUP AND SUB GROUP | D8: Manage group and sub group new design and dynamic approval. | E8: 2ND STAGE IMPLEMENTATION | F8: LIVE | J8: 45202 | K8: 45209 | L8: 45205 | M8: 45209 | N8: =IF(L8="",IF(M7="",O7+1,M7+1),L8) -> 45205 | O8: =+N8+P8-1 -> 45212 | P8: =IF(IF(J8="",0,IF(K8="",0,K8-J8))="",0,K8-J8+1) -> 8 | Q8: =IF(L8="",0,IF(M8="",TODAY()-L8,M8-L8+1)) -> 5 | R8: =IF(Q8=0,0,P8-Q8) -> 3
A9: =ROW() - ROW($A$30) + 28 -> 7 | B9: MASTER DATA | C9: MANAGE MATERIAL | D9: Manage Material in Manage Project part | E9: 2ND STAGE IMPLEMENTATION | F9: LIVE | J9: 45209 | K9: 45212 | L9: 45209 | M9: 45215 | N9: =IF(L9="",IF(M8="",O8+1,M8+1),L9) -> 45209 | O9: =+N9+P9-1 -> 45212 | P9: =IF(IF(J9="",0,IF(K9="",0,K9-J9))="",0,K9-J9+1) -> 4 | Q9: =IF(L9="",0,IF(M9="",TODAY()-L9,M9-L9+1)) -> 7 | R9: =IF(Q9=0,0,P9-Q9) -> -3
A10: =ROW() - ROW($A$30) + 28 -> 8 | B10: FINANCE | C10: MAMAGE LOCATION(PROJECT) | D10: Download Excel functionality in Manage Head of Grouping in Finance module.Filtration and PhP Pagination and Sorting in Manage location | F10: LIVE | J10: 45215 | K10: 45229 | L10: 45215 | M10: 45232 | N10: =IF(L10="",IF(M9="",O9+1,M9+1),L10) -> 45215 | O10: =+N10+P10-1 -> 45229 | P10: =IF(IF(J10="",0,IF(K10="",0,K10-J10))="",0,K10-J10+1) -> 15 | Q10: =IF(L10="",0,IF(M10="",TODAY()-L10,M10-L10+1)) -> 18 | R10: =IF(Q10=0,0,P10-Q10) -> -3
A11: =ROW() - ROW($A$30) + 28 -> 9 | B11: MASTER DATA | C11: FINANCE | D11: Manage Bank Account dynamic approval ,filtration and php pagination and dynamic approval | E11: 2ND STAGE IMPLEMENTATION | F11: INCOMPLETE | J11: 45230 | K11: 45238 | L11: 45227 | M11: 45238 | N11: =IF(L11="",IF(M10="",O10+1,M10+1),L11) -> 45227 | O11: =+N11+P11-1 -> 45235 | P11: =IF(IF(J11="",0,IF(K11="",0,K11-J11))="",0,K11-J11+1) -> 9 | Q11: =IF(L11="",0,IF(M11="",TODAY()-L11,M11-L11+1)) -> 12 | R11: =IF(Q11=0,0,P11-Q11) -> -3 | S11: TEAM LEAD WILL CHECK THE REPORT AND SHE WILL ASSIGN IT FOR TESTING
A12: =ROW() - ROW($A$30) + 28 -> 10 | B12: MASTER DATA | C12: CATEGORY AND SUB CATEGORY,GROUP SUB GROUP | D12: Php pagination and filtration in mange category, mange sub category and issue solve.Pagination and filtration in mange group, mange sub sub_group and mange material. | E12: ISSUE | F12: LIVE | J12: 45238 | K12: 45240 | L12: 45238 | M12: 45250 | N12: =IF(L12="",IF(M11="",O11+1,M11+1),L12) -> 45238 | O12: =+N12+P12-1 -> 45240 | P12: =IF(IF(J12="",0,IF(K12="",0,K12-J12))="",0,K12-J12+1) -> 3 | Q12: =IF(L12="",0,IF(M12="",TODAY()-L12,M12-L12+1)) -> 13 | R12: =IF(Q12=0,0,P12-Q12) -> -10 | S12: TEAM LEAD WILL CHECK THE REPORT AND SHE WILL ASSIGN IT FOR TESTING
A13: =ROW() - ROW($A$30) + 28 -> 11 | B13: EXPENSE | C13: ALL PAYMENT REQUEST | D13: Page speed functionality in expense module (expense report -> all payment request) | E13: PAGE SPEED FUNCTIONALITY | F13: LIVE | J13: 45250 | K13: 45255 | L13: 45250 | M13: 45259 | N13: =IF(L13="",IF(M12="",O12+1,M12+1),L13) -> 45250 | O13: =+N13+P13-1 -> 45255 | P13: =IF(IF(J13="",0,IF(K13="",0,K13-J13))="",0,K13-J13+1) -> 6 | Q13: =IF(L13="",0,IF(M13="",TODAY()-L13,M13-L13+1)) -> 10 | R13: =IF(Q13=0,0,P13-Q13) -> -4 | S13: IT'S DELAY DUE TO DEV SERVER ISSUE
A14: =ROW() - ROW($A$30) + 28 -> 12 | B14: EXPENSE | C14: REPORT | D14: New design, speed customization in journal report | E14: PAGE SPEED FUNCTIONALITY | F14: LIVE | J14: 45259 | K14: 45262 | L14: 45266 | M14: 45266 | N14: =IF(L14="",IF(M13="",O13+1,M13+1),L14) -> 45266 | O14: =+N14+P14-1 -> 45269 | P14: =IF(IF(J14="",0,IF(K14="",0,K14-J14))="",0,K14-J14+1) -> 4 | Q14: =IF(L14="",0,IF(M14="",TODAY()-L14,M14-L14+1)) -> 1 | R14: =IF(Q14=0,0,P14-Q14) -> 3 | S14: TEAM LEAD WILL CHECK THE REPORT AND SHE WILL ASSIGN IT FOR TESTING
A15: =ROW() - ROW($A$30) + 28 -> 13 | B15: SALES | D15: Review of documentation of Sales CRM,Database , login and registration set up of sales CRM in local | E15: OTHER | F15: COMPLETE | J15: 45266 | K15: 45272 | L15: 45266 | M15: 45272 | N15: =IF(L15="",IF(M14="",O14+1,M14+1),L15) -> 45266 | O15: =+N15+P15-1 -> 45272 | P15: =IF(IF(J15="",0,IF(K15="",0,K15-J15))="",0,K15-J15+1) -> 7 | Q15: =IF(L15="",0,IF(M15="",TODAY()-L15,M15-L15+1)) -> 7 | R15: =IF(Q15=0,0,P15-Q15) -> 0 | S15: TEAM LEAD WILL CHECK THE REPORT AND SHE WILL ASSIGN IT FOR TESTING
A16: =ROW() - ROW($A$30) + 28 -> 14 | B16: SALES | C16: COUNTRY | D16: Adding country of location part in sale crm | E16: IMPROVEMENT | F16: COMPLETE | J16: 45272 | K16: 45273 | L16: 45272 | M16: 45274 | N16: =IF(L16="",IF(M15="",O15+1,M15+1),L16) -> 45272 | O16: =+N16+P16-1 -> 45273 | P16: =IF(IF(J16="",0,IF(K16="",0,K16-J16))="",0,K16-J16+1) -> 2 | Q16: =IF(L16="",0,IF(M16="",TODAY()-L16,M16-L16+1)) -> 3 | R16: =IF(Q16=0,0,P16-Q16) -> -1
A17: =ROW() - ROW($A$30) + 28 -> 15 | B17: SALES | C17: DISTRICT | D17: Adding district of location part in sale crm | E17: IMPROVEMENT | F17: COMPLETE | G17: 45274 | J17: 45274 | K17: 45275 | L17: 45274 | M17: 45276 | N17: =IF(L17="",IF(M16="",O16+1,M16+1),L17) -> 45274 | O17: =+N17+P17-1 -> 45275 | P17: =IF(IF(J17="",0,IF(K17="",0,K17-J17))="",0,K17-J17+1) -> 2 | Q17: =IF(L17="",0,IF(M17="",TODAY()-L17,M17-L17+1)) -> 3 | R17: =IF(Q17=0,0,P17-Q17) -> -1
A18: =ROW() - ROW($A$30) + 28 -> 16 | B18: SALES | D18: Remodification of Database of Sales CRM and Form Design. | E18: MODIFICATION | F18: COMPLETE | J18: 45285 | K18: 45286 | L18: 45287 | M18: 45287 | N18: =IF(L18="",IF(M17="",O17+1,M17+1),L18) -> 45287 | O18: =+N18+P18-1 -> 45288 | P18: =IF(IF(J18="",0,IF(K18="",0,K18-J18))="",0,K18-J18+1) -> 2 | Q18: =IF(L18="",0,IF(M18="",TODAY()-L18,M18-L18+1)) -> 1 | R18: =IF(Q18=0,0,P18-Q18) -> 1
A19: =ROW() - ROW($A$30) + 28 -> 17 | B19: SALES | C19: MANAGE BANK | D19: create bank master and bank account details form in sales crm | E19: IMPROVEMENT | F19: COMPLETE | J19: 45286 | K19: 45287 | L19: 45287 | M19: 45288 | N19: =IF(L19="",IF(M18="",O18+1,M18+1),L19) -> 45287 | O19: =+N19+P19-1 -> 45288 | P19: =IF(IF(J19="",0,IF(K19="",0,K19-J19))="",0,K19-J19+1) -> 2 | Q19: =IF(L19="",0,IF(M19="",TODAY()-L19,M19-L19+1)) -> 2 | R19: =IF(Q19=0,0,P19-Q19) -> 0
A20: =ROW() - ROW($A$30) + 28 -> 18 | B20: SALES | C20: TERM/PAYMENT TERM | D20: Term Master and Payment Term creation in sales crm | E20: IMPROVEMENT | F20: COMPLETE | J20: 45288 | K20: 45289 | L20: 45288 | M20: 45288 | N20: =IF(L20="",IF(M19="",O19+1,M19+1),L20) -> 45288 | O20: =+N20+P20-1 -> 45289 | P20: =IF(IF(J20="",0,IF(K20="",0,K20-J20))="",0,K20-J20+1) -> 2 | Q20: =IF(L20="",0,IF(M20="",TODAY()-L20,M20-L20+1)) -> 1 | R20: =IF(Q20=0,0,P20-Q20) -> 1
A21: =ROW() - ROW($A$30) + 28 -> 19 | B21: SALES | C21: TAX | D21: Tax master creation in sales crm | E21: IMPROVEMENT | F21: COMPLETE | J21: 45288 | K21: 45289 | L21: 45288 | M21: 45289 | N21: =IF(L21="",IF(M20="",O20+1,M20+1),L21) -> 45288 | O21: =+N21+P21-1 -> 45289 | P21: =IF(IF(J21="",0,IF(K21="",0,K21-J21))="",0,K21-J21+1) -> 2 | Q21: =IF(L21="",0,IF(M21="",TODAY()-L21,M21-L21+1)) -> 2 | R21: =IF(Q21=0,0,P21-Q21) -> 0
A22: =ROW() - ROW($A$30) + 28 -> 20 | B22: SALES | C22: LEAD STAGE /LEAD STATUS | D22: Lead Stage and Lead status master creation in sales CRM | E22: IMPROVEMENT | F22: COMPLETE | J22: 45289 | K22: 45290 | L22: 45289 | M22: 45294 | N22: =IF(L22="",IF(M21="",O21+1,M21+1),L22) -> 45289 | O22: =+N22+P22-1 -> 45290 | P22: =IF(IF(J22="",0,IF(K22="",0,K22-J22))="",0,K22-J22+1) -> 2 | Q22: =IF(L22="",0,IF(M22="",TODAY()-L22,M22-L22+1)) -> 6 | R22: =IF(Q22=0,0,P22-Q22) -> -4
A23: =ROW() - ROW($A$30) + 28 -> 21 | B23: SALES | C23: PRODUCT AND SERVICE | D23: Product/Service master creation in sales crm | E23: IMPROVEMENT | F23: COMPLETE | J23: 45292 | K23: 45293 | L23: 45294 | M23: 45294 | N23: =IF(L23="",IF(M22="",O22+1,M22+1),L23) -> 45294 | O23: =+N23+P23-1 -> 45295 | P23: =IF(IF(J23="",0,IF(K23="",0,K23-J23))="",0,K23-J23+1) -> 2 | Q23: =IF(L23="",0,IF(M23="",TODAY()-L23,M23-L23+1)) -> 1 | R23: =IF(Q23=0,0,P23-Q23) -> 1
A24: =ROW() - ROW($A$30) + 28 -> 22 | B24: SALES | D24: modification work of branch master and employee master in sales CRM | E24: MODIFICATION | F24: COMPLETE | J24: 45294 | K24: 45295 | L24: 45294 | M24: 45300 | N24: =IF(L24="",IF(M23="",O23+1,M23+1),L24) -> 45294 | O24: =+N24+P24-1 -> 45295 | P24: =IF(IF(J24="",0,IF(K24="",0,K24-J24))="",0,K24-J24+1) -> 2 | Q24: =IF(L24="",0,IF(M24="",TODAY()-L24,M24-L24+1)) -> 7 | R24: =IF(Q24=0,0,P24-Q24) -> -5
A25: =ROW() - ROW($A$30) + 28 -> 23 | B25: SALES | C25: ENQUIRY BUCKET | D25: Enquiry Bucket Master Sales CRM | E25: IMPROVEMENT | F25: COMPLETE | J25: 45299 | K25: 45303 | L25: 45300 | M25: 45315 | N25: =IF(L25="",IF(M24="",O24+1,M24+1),L25) -> 45300 | O25: =+N25+P25-1 -> 45304 | P25: =IF(IF(J25="",0,IF(K25="",0,K25-J25))="",0,K25-J25+1) -> 5 | Q25: =IF(L25="",0,IF(M25="",TODAY()-L25,M25-L25+1)) -> 16 | R25: =IF(Q25=0,0,P25-Q25) -> -11
A26: =ROW() - ROW($A$30) + 28 -> 24 | B26: SALES | D26: Sales CRM listing page's Enquiry bucket includes the implementation of the Pending To Assign tab, while the view page is undergoing follow-up functionality implementation. | E26: OTHER | F26: COMPLETE | J26: 45309 | K26: 45314 | L26: 45315 | M26: 45321 | N26: =IF(L26="",IF(M25="",O25+1,M25+1),L26) -> 45315 | O26: =+N26+P26-1 -> 45320 | P26: =IF(IF(J26="",0,IF(K26="",0,K26-J26))="",0,K26-J26+1) -> 6 | Q26: =IF(L26="",0,IF(M26="",TODAY()-L26,M26-L26+1)) -> 7 | R26: =IF(Q26=0,0,P26-Q26) -> -1
A27: =ROW() - ROW($A$30) + 28 -> 25 | B27: SALES | D27: Rectification the issue in enquiry bucket and follow up | E27: TESTING ISSUE | F27: COMPLETE | J27: 45315 | K27: 45318 | L27: 45321 | M27: 45323 | N27: =IF(L27="",IF(M26="",O26+1,M26+1),L27) -> 45321 | O27: =+N27+P27-1 -> 45324 | P27: =IF(IF(J27="",0,IF(K27="",0,K27-J27))="",0,K27-J27+1) -> 4 | Q27: =IF(L27="",0,IF(M27="",TODAY()-L27,M27-L27+1)) -> 3 | R27: =IF(Q27=0,0,P27-Q27) -> 1
A28: =ROW() - ROW($A$30) + 28 -> 26 | B28: SALES | C28: MY TODAYS FOLLOW UP | D28: My Todays Follow up in sales crm | E28: IMPROVEMENT | F28: COMPLETE | J28: 45322 | K28: 45324 | L28: 45323 | M28: 45329 | N28: =IF(L28="",IF(M27="",O27+1,M27+1),L28) -> 45323 | O28: =+N28+P28-1 -> 45325 | P28: =IF(IF(J28="",0,IF(K28="",0,K28-J28))="",0,K28-J28+1) -> 3 | Q28: =IF(L28="",0,IF(M28="",TODAY()-L28,M28-L28+1)) -> 7 | R28: =IF(Q28=0,0,P28-Q28) -> -4
A29: =ROW() - ROW($A$30) + 28 -> 27 | B29: SALES | C29: UPCOMING FOLLOW UP | D29: Upcoming Follow up in sale CRM | E29: IMPROVEMENT | F29: COMPLETE | J29: 45328 | K29: 45329 | L29: 45329 | M29: 45329 | N29: =IF(L29="",IF(M28="",O28+1,M28+1),L29) -> 45329 | O29: =+N29+P29-1 -> 45330 | P29: =IF(IF(J29="",0,IF(K29="",0,K29-J29))="",0,K29-J29+1) -> 2 | Q29: =IF(L29="",0,IF(M29="",TODAY()-L29,M29-L29+1)) -> 1 | R29: =IF(Q29=0,0,P29-Q29) -> 1
A30: =ROW() - ROW($A$30) + 28 -> 28 | B30: SALES | D30: Testing in Location Masters of sales CRM | E30: TESTING ISSUE | F30: COMPLETE | J30: 45329 | K30: 45329 | L30: 45329 | M30: 45330 | N30: =IF(L30="",IF(M29="",O29+1,M29+1),L30) -> 45329 | O30: =+N30+P30-1 -> 45329 | P30: =IF(IF(J30="",0,IF(K30="",0,K30-J30))="",0,K30-J30+1) -> 1 | Q30: =IF(L30="",0,IF(M30="",TODAY()-L30,M30-L30+1)) -> 2 | R30: =IF(Q30=0,0,P30-Q30) -> -1
A31: =ROW() - ROW($A$30) + 28 -> 29 | B31: SALES | C31: COMPANY | D31: Testing Company Master in Sales CRM | E31: TESTING ISSUE | F31: COMPLETE | J31: 45330 | K31: 45330 | L31: 45330 | M31: 45332 | N31: =IF(L31="",IF(M30="",O30+1,M30+1),L31) -> 45330 | O31: =+N31+P31-1 -> 45330 | P31: =IF(IF(J31="",0,IF(K31="",0,K31-J31))="",0,K31-J31+1) -> 1 | Q31: =IF(L31="",0,IF(M31="",TODAY()-L31,M31-L31+1)) -> 3 | R31: =IF(Q31=0,0,P31-Q31) -> -2
A32: =ROW() - ROW($A$30) + 28 -> 30 | B32: SALES | C32: MANAGE BANK | D32: Testing of Bank master(sales CRM) | E32: TESTING ISSUE | F32: COMPLETE | J32: 45330 | K32: 45330 | L32: 45332 | M32: 45332 | N32: =IF(L32="",IF(M31="",O31+1,M31+1),L32) -> 45332 | O32: =+N32+P32-1 -> 45332 | P32: =IF(IF(J32="",0,IF(K32="",0,K32-J32))="",0,K32-J32+1) -> 1 | Q32: =IF(L32="",0,IF(M32="",TODAY()-L32,M32-L32+1)) -> 1 | R32: =IF(Q32=0,0,P32-Q32) -> 0
A33: =ROW() - ROW($A$30) + 28 -> 31 | B33: SALES | D33: Testing of Bank account(sales CRM),Testing of tax master(sales CRM),Testing of term master(sales CRM),Testing of payment term master(sales CRM). | E33: TESTING ISSUE | F33: COMPLETE | J33: 45331 | K33: 45331 | L33: 45332 | M33: 45332 | N33: =IF(L33="",IF(M32="",O32+1,M32+1),L33) -> 45332 | O33: =+N33+P33-1 -> 45332 | P33: =IF(IF(J33="",0,IF(K33="",0,K33-J33))="",0,K33-J33+1) -> 1 | Q33: =IF(L33="",0,IF(M33="",TODAY()-L33,M33-L33+1)) -> 1 | R33: =IF(Q33=0,0,P33-Q33) -> 0
A34: =ROW() - ROW($A$30) + 28 -> 32 | B34: SALES | C34: LOCATION | D34: Issue fix of location master in sales CRM | E34: TESTING ISSUE | F34: COMPLETE | J34: 45334 | K34: 45334 | L34: 45334 | M34: 45338 | N34: =IF(L34="",IF(M33="",O33+1,M33+1),L34) -> 45334 | O34: =+N34+P34-1 -> 45334 | P34: =IF(IF(J34="",0,IF(K34="",0,K34-J34))="",0,K34-J34+1) -> 1 | Q34: =IF(L34="",0,IF(M34="",TODAY()-L34,M34-L34+1)) -> 5 | R34: =IF(Q34=0,0,P34-Q34) -> -4
A35: =ROW() - ROW($A$30) + 28 -> 33 | B35: SALES | D35: modification in location master village part and area master . | E35: MODIFICATION | F35: COMPLETE | J35: 45337 | K35: 45337 | L35: 45338 | M35: 45338 | N35: =IF(L35="",IF(M34="",O34+1,M34+1),L35) -> 45338 | O35: =+N35+P35-1 -> 45338 | P35: =IF(IF(J35="",0,IF(K35="",0,K35-J35))="",0,K35-J35+1) -> 1 | Q35: =IF(L35="",0,IF(M35="",TODAY()-L35,M35-L35+1)) -> 1 | R35: =IF(Q35=0,0,P35-Q35) -> 0
A36: =ROW() - ROW($A$30) + 28 -> 34 | B36: SALES | D36: All menu set up for reports and analysis the flow . | E36: OTHER | F36: COMPLETE | J36: 45338 | K36: 45339 | L36: 45338 | M36: 45341 | N36: =IF(L36="",IF(M35="",O35+1,M35+1),L36) -> 45338 | O36: =+N36+P36-1 -> 45339 | P36: =IF(IF(J36="",0,IF(K36="",0,K36-J36))="",0,K36-J36+1) -> 2 | Q36: =IF(L36="",0,IF(M36="",TODAY()-L36,M36-L36+1)) -> 4 | R36: =IF(Q36=0,0,P36-Q36) -> -2
A37: =ROW() - ROW($A$30) + 28 -> 35 | B37: SALES | C37: STAGE WISE REPORT | D37: stagewise report of enquiry in sale CRM | E37: IMPROVEMENT | F37: COMPLETE | J37: 45342 | K37: 45344 | L37: 45341 | M37: 45348 | N37: =IF(L37="",IF(M36="",O36+1,M36+1),L37) -> 45341 | O37: =+N37+P37-1 -> 45343 | P37: =IF(IF(J37="",0,IF(K37="",0,K37-J37))="",0,K37-J37+1) -> 3 | Q37: =IF(L37="",0,IF(M37="",TODAY()-L37,M37-L37+1)) -> 8 | R37: =IF(Q37=0,0,P37-Q37) -> -5
A38: =ROW() - ROW($A$30) + 28 -> 36 | B38: SALES | C38: STATUS WISE REPORT | D38: Statuswise report of enquiry in sale CRM | E38: IMPROVEMENT | F38: COMPLETE | J38: 45345 | K38: 45345 | L38: 45348 | M38: 45348 | N38: =IF(L38="",IF(M37="",O37+1,M37+1),L38) -> 45348 | O38: =+N38+P38-1 -> 45348 | P38: =IF(IF(J38="",0,IF(K38="",0,K38-J38))="",0,K38-J38+1) -> 1 | Q38: =IF(L38="",0,IF(M38="",TODAY()-L38,M38-L38+1)) -> 1 | R38: =IF(Q38=0,0,P38-Q38) -> 0
A39: =ROW() - ROW($A$30) + 28 -> 37 | B39: SALES | C39: PRODUCT WISE REPORT,CUSTOMERWISE AND EMPLOYEE WISE | D39: productwise report of enquiry in sale CRM,customerwise and employeewise reports of enquiry in sale crm | E39: IMPROVEMENT | F39: COMPLETE | J39: 45348 | K39: 45348 | L39: 45348 | M39: 45348 | N39: =IF(L39="",IF(M38="",O38+1,M38+1),L39) -> 45348 | O39: =+N39+P39-1 -> 45348 | P39: =IF(IF(J39="",0,IF(K39="",0,K39-J39))="",0,K39-J39+1) -> 1 | Q39: =IF(L39="",0,IF(M39="",TODAY()-L39,M39-L39+1)) -> 1 | R39: =IF(Q39=0,0,P39-Q39) -> 0
A40: =ROW() - ROW($A$30) + 28 -> 38 | B40: SALES | D40: Modification all reports (stagewise,statuswise,productwise,customerwise,employeewise) of enquiry | E40: MODIFICATION | F40: COMPLETE | J40: 45348 | K40: 45350 | L40: 45348 | M40: 45355 | N40: =IF(L40="",IF(M39="",O39+1,M39+1),L40) -> 45348 | O40: =+N40+P40-1 -> 45350 | P40: =IF(IF(J40="",0,IF(K40="",0,K40-J40))="",0,K40-J40+1) -> 3 | Q40: =IF(L40="",0,IF(M40="",TODAY()-L40,M40-L40+1)) -> 8 | R40: =IF(Q40=0,0,P40-Q40) -> -5
A41: =ROW() - ROW($A$30) + 28 -> 39 | B41: SALES | C41: PLWISE REPORT OF ENQUIRY | D41: PIwise reports of enquiry in sale crm | E41: OTHER | F41: COMPLETE | J41: 45351 | K41: 45353 | L41: 45355 | M41: 45355 | N41: =IF(L41="",IF(M40="",O40+1,M40+1),L41) -> 45355 | O41: =+N41+P41-1 -> 45357 | P41: =IF(IF(J41="",0,IF(K41="",0,K41-J41))="",0,K41-J41+1) -> 3 | Q41: =IF(L41="",0,IF(M41="",TODAY()-L41,M41-L41+1)) -> 1 | R41: =IF(Q41=0,0,P41-Q41) -> 2
A42: =ROW() - ROW($A$30) + 28 -> 40 | B42: SALES | D42: Issue fixing PIwise report | E42: TESTING ISSUE | F42: COMPLETE | J42: 45355 | K42: 45357 | L42: 45355 | M42: 45357 | N42: =IF(L42="",IF(M41="",O41+1,M41+1),L42) -> 45355 | O42: =+N42+P42-1 -> 45357 | P42: =IF(IF(J42="",0,IF(K42="",0,K42-J42))="",0,K42-J42+1) -> 3 | Q42: =IF(L42="",0,IF(M42="",TODAY()-L42,M42-L42+1)) -> 3 | R42: =IF(Q42=0,0,P42-Q42) -> 0
A43: =ROW() - ROW($A$30) + 28 -> 41 | B43: SALES | D43: laravel setup in local | E43: OTHER | F43: COMPLETE | J43: 45356 | K43: 45356 | L43: 45357 | M43: 45357 | N43: =IF(L43="",IF(M42="",O42+1,M42+1),L43) -> 45357 | O43: =+N43+P43-1 -> 45357 | P43: =IF(IF(J43="",0,IF(K43="",0,K43-J43))="",0,K43-J43+1) -> 1 | Q43: =IF(L43="",0,IF(M43="",TODAY()-L43,M43-L43+1)) -> 1 | R43: =IF(Q43=0,0,P43-Q43) -> 0
A44: =ROW() - ROW($A$30) + 28 -> 42 | B44: SALES | D44: Not interested leads and Lost enquiry in sale crm | E44: IMPROVEMENT | F44: COMPLETE | J44: 45357 | K44: 45358 | L44: 45357 | M44: 45362 | N44: =IF(L44="",IF(M43="",O43+1,M43+1),L44) -> 45357 | O44: =+N44+P44-1 -> 45358 | P44: =IF(IF(J44="",0,IF(K44="",0,K44-J44))="",0,K44-J44+1) -> 2 | Q44: =IF(L44="",0,IF(M44="",TODAY()-L44,M44-L44+1)) -> 6 | R44: =IF(Q44=0,0,P44-Q44) -> -4
A45: =ROW() - ROW($A$30) + 28 -> 43 | B45: SALES | C45: HR | D45: In local Hr module set up and analysis . | E45: OTHER | F45: COMPLETE | J45: 45362 | K45: 45363 | L45: 45362 | M45: 45364 | N45: =IF(L45="",IF(M44="",O44+1,M44+1),L45) -> 45362 | O45: =+N45+P45-1 -> 45363 | P45: =IF(IF(J45="",0,IF(K45="",0,K45-J45))="",0,K45-J45+1) -> 2 | Q45: =IF(L45="",0,IF(M45="",TODAY()-L45,M45-L45+1)) -> 3 | R45: =IF(Q45=0,0,P45-Q45) -> -1
A46: =ROW() - ROW($A$30) + 28 -> 44 | B46: SALES | C46: HR | D46: Segregation of HR module for sales CRM,with PTI and arrar. | E46: OTHER | F46: COMPLETE | J46: 45363 | K46: 45367 | L46: 45364 | M46: 45379 | N46: =IF(L46="",IF(M45="",O45+1,M45+1),L46) -> 45364 | O46: =+N46+P46-1 -> 45368 | P46: =IF(IF(J46="",0,IF(K46="",0,K46-J46))="",0,K46-J46+1) -> 5 | Q46: =IF(L46="",0,IF(M46="",TODAY()-L46,M46-L46+1)) -> 16 | R46: =IF(Q46=0,0,P46-Q46) -> -11
A47: =ROW() - ROW($A$30) + 28 -> 45 | B47: SALES | C47: HR | D47: Test the HR module. | E47: OTHER | F47: COMPLETE | J47: 45379 | K47: 45384 | L47: 45379 | M47: 45387 | N47: =IF(L47="",IF(M46="",O46+1,M46+1),L47) -> 45379 | O47: =+N47+P47-1 -> 45384 | P47: =IF(IF(J47="",0,IF(K47="",0,K47-J47))="",0,K47-J47+1) -> 6 | Q47: =IF(L47="",0,IF(M47="",TODAY()-L47,M47-L47+1)) -> 9 | R47: =IF(Q47=0,0,P47-Q47) -> -3
A48: =ROW() - ROW($A$30) + 28 -> 46 | B48: SALES | C48: HR | D48: create commission master in sale crm | E48: OTHER | F48: COMPLETE | J48: 45388 | K48: 45390 | L48: 45388 | N48: =IF(L48="",IF(M47="",O47+1,M47+1),L48) -> 45388 | O48: =+N48+P48-1 -> 45390 | P48: =IF(IF(J48="",0,IF(K48="",0,K48-J48))="",0,K48-J48+1) -> 3 | Q48: =IF(L48="",0,IF(M48="",TODAY()-L48,M48-L48+1)) -> 60 | R48: =IF(Q48=0,0,P48-Q48) -> -57
A49: =ROW() - ROW($A$30) + 28 -> 47 | B49: SALES | D49: Flow check of sale CRM Enquiry bucket onwards than implementation assign and reassign functionality after enquiry bucket | E49: OTHER | F49: COMPLETE | J49: 45390 | K49: 45391 | L49: 45390 | M49: 45394 | N49: =IF(L49="",IF(M48="",O48+1,M48+1),L49) -> 45390 | O49: =+N49+P49-1 -> 45391 | P49: =IF(IF(J49="",0,IF(K49="",0,K49-J49))="",0,K49-J49+1) -> 2 | Q49: =IF(L49="",0,IF(M49="",TODAY()-L49,M49-L49+1)) -> 5 | R49: =IF(Q49=0,0,P49-Q49) -> -3
A50: =ROW() - ROW($A$30) + 28 -> 48 | B50: SALES | D50: Real Estate CRM set up in local and Analysis the flow | E50: OTHER | F50: COMPLETE | J50: 45393 | K50: 45394 | L50: 45397 | M50: 45397 | N50: =IF(L50="",IF(M49="",O49+1,M49+1),L50) -> 45397 | O50: =+N50+P50-1 -> 45398 | P50: =IF(IF(J50="",0,IF(K50="",0,K50-J50))="",0,K50-J50+1) -> 2 | Q50: =IF(L50="",0,IF(M50="",TODAY()-L50,M50-L50+1)) -> 1 | R50: =IF(Q50=0,0,P50-Q50) -> 1
A51: =ROW() - ROW($A$30) + 28 -> 49 | B51: SALES | D51: View Page implement in department of real estate crm | E51: OTHER | F51: COMPLETE | J51: 45397 | K51: 45398 | L51: 45397 | M51: 45398 | N51: =IF(L51="",IF(M50="",O50+1,M50+1),L51) -> 45397 | O51: =+N51+P51-1 -> 45398 | P51: =IF(IF(J51="",0,IF(K51="",0,K51-J51))="",0,K51-J51+1) -> 2 | Q51: =IF(L51="",0,IF(M51="",TODAY()-L51,M51-L51+1)) -> 2 | R51: =IF(Q51=0,0,P51-Q51) -> 0
A52: =ROW() - ROW($A$30) + 28 -> 50 | B52: SALES | D52: In designation part of real estate crm implement edit,delete and view . | E52: OTHER | F52: COMPLETE | J52: 45397 | K52: 45398 | L52: 45397 | M52: 45401 | N52: =IF(L52="",IF(M51="",O51+1,M51+1),L52) -> 45397 | O52: =+N52+P52-1 -> 45398 | P52: =IF(IF(J52="",0,IF(K52="",0,K52-J52))="",0,K52-J52+1) -> 2 | Q52: =IF(L52="",0,IF(M52="",TODAY()-L52,M52-L52+1)) -> 5 | R52: =IF(Q52=0,0,P52-Q52) -> -3
A53: =ROW() - ROW($A$30) + 28 -> 51 | B53: SALES | D53: Deparment and Designation form validation in real estate CRM | E53: OTHER | F53: COMPLETE | J53: 45401 | K53: 45402 | L53: 45401 | M53: 45406 | N53: =IF(L53="",IF(M52="",O52+1,M52+1),L53) -> 45401 | O53: =+N53+P53-1 -> 45402 | P53: =IF(IF(J53="",0,IF(K53="",0,K53-J53))="",0,K53-J53+1) -> 2 | Q53: =IF(L53="",0,IF(M53="",TODAY()-L53,M53-L53+1)) -> 6 | R53: =IF(Q53=0,0,P53-Q53) -> -4
A54: =ROW() - ROW($A$30) + 28 -> 52 | B54: SALES | D54: In Grade part of real estate crm implement edit,delete ,view and form validation . | E54: OTHER | F54: COMPLETE | J54: 45408 | K54: 45411 | L54: 45408 | M54: 45408 | N54: =IF(L54="",IF(M53="",O53+1,M53+1),L54) -> 45408 | O54: =+N54+P54-1 -> 45411 | P54: =IF(IF(J54="",0,IF(K54="",0,K54-J54))="",0,K54-J54+1) -> 4 | Q54: =IF(L54="",0,IF(M54="",TODAY()-L54,M54-L54+1)) -> 1 | R54: =IF(Q54=0,0,P54-Q54) -> 3
A55: =ROW() - ROW($A$30) + 28 -> 53 | B55: FINANCE | C55: HEAD | D55: Manage head new pagination ,dynamic approval and pending approval. | E55: 2ND STAGE | F55: TESTING | J55: 45412 | K55: 45419 | L55: 45412 | M55: 45426 | N55: =IF(L55="",IF(M54="",O54+1,M54+1),L55) -> 45412 | O55: =+N55+P55-1 -> 45419 | P55: =IF(IF(J55="",0,IF(K55="",0,K55-J55))="",0,K55-J55+1) -> 8 | Q55: =IF(L55="",0,IF(M55="",TODAY()-L55,M55-L55+1)) -> 15 | R55: =IF(Q55=0,0,P55-Q55) -> -7
A56: =ROW() - ROW($A$30) + 28 -> 54 | B56: FINANCE | C56: GROUP | D56: Implemantation of pending approval , pagination and dunamic approval in manage group. | E56: 2ND STAGE | F56: TESTING | J56: 45419 | K56: 45422 | L56: 45426 | M56: 45427 | N56: =IF(L56="",IF(M55="",O55+1,M55+1),L56) -> 45426 | O56: =+N56+P56-1 -> 45429 | P56: =IF(IF(J56="",0,IF(K56="",0,K56-J56))="",0,K56-J56+1) -> 4 | Q56: =IF(L56="",0,IF(M56="",TODAY()-L56,M56-L56+1)) -> 2 | R56: =IF(Q56=0,0,P56-Q56) -> 2
A57: =ROW() - ROW($A$30) + 28 -> 55 | B57: FINANCE | C57: SUB GROUP | D57: Pagination,dynamic approval,and pending approval in sub group | E57: 2ND STAGE | F57: TESTING | J57: 45426 | K57: 45429 | L57: 45429 | M57: 45430 | N57: =IF(L57="",IF(M56="",O56+1,M56+1),L57) -> 45429 | O57: =+N57+P57-1 -> 45432 | P57: =IF(IF(J57="",0,IF(K57="",0,K57-J57))="",0,K57-J57+1) -> 4 | Q57: =IF(L57="",0,IF(M57="",TODAY()-L57,M57-L57+1)) -> 2 | R57: =IF(Q57=0,0,P57-Q57) -> 2
A58: =ROW() - ROW($A$30) + 28 -> 56 | B58: FINANCE | C58: TYPE | D58: Pagination,dynamic approval,and pending approval in manage type and Manage sub type with testing | E58: 2ND STAGE | F58: TESTING | J58: 45429 | K58: 45432 | L58: 45430 | M58: 45439
A59: =ROW() - ROW($A$30) + 28 -> 57 | B59: FINANCE | C59: SUB TYPE | D59: Pagination,dynamic approval,and pending approval in sub sub type | E59: 2ND STAGE | F59: TESTING | J59: 45434 | K59: 45436 | L59: 45439 | M59: 45439
A60: 58 | B60: FINANCE | D60: All module of groupping(Head,group,subgroup,type,sub type) testing in dev and paralle functionality implement on that. | E60: 2ND STAGE | F60: COMPLETE | J60: 45440 | K60: 45442 | L60: 45441 | M60: 45442
A61: 59 | B61: EXPENSE | C61: PAYMENT REQUEST | D61: 2nd Stage implementation in expense module of payment request . | E61: 2ND STAGE | F61: INPROGRESS | J61: 45442 | K61: 45447 | L61: 45442

Sheet GAYATRI GOCHHAYAT
P1: =SUM(P3:P943) -> 410 | Q1: =SUM(Q3:Q943) -> 512 | R1: =SUM(R3:R943) -> -111
A2: SL. | B2: MODULE | C2: SUB MODULE | D2: ACTIVITIES | E2: WORK TYPE | F2: STATUS | G2: APPROVAL | H2: RESTRICTION | I2: NOTIFICATION | J2: TGT ST DATE | K2: TGT END DATE | L2: ACT ST DATE | M2: ACT END DATE | N2: PROB ST DT | O2: PROB END DT | P2: TGT DUR | Q2: ACT DUR | R2: T SAVING | S2: DELAY REASON /REMARK
A3: =ROW() - ROW($A$58) + 56 -> 1 | B3: FINANCE | D3: Add Bank Account | F3: NA | G3: LIVE | H3: LIVE | I3: LIVE | J3: 44820 | K3: 44826 | L3: 44820 | M3: 44827 | N3: =L3 -> 44820 | O3: =N3+P3-1 -> 44826 | P3: =IF(IF(J3="",0,IF(K3="",0,K3-J3))="",0,K3-J3+1) -> 7 | Q3: =IF(L3="",0,IF(M3="",TODAY()-L3,M3-L3+1)) -> 8 | R3: =IF(Q3=0,0,P3-Q3) -> -1
A4: =ROW() - ROW($A$58) + 56 -> 2 | B4: FINANCE | D4: Fd Processing | F4: NA | G4: LIVE | H4: LIVE | I4: LIVE | J4: 44827 | K4: 44827 | L4: 44830 | M4: 44831 | N4: =IF(L4="",IF(M3="",O3+1,M3+1),L4) -> 44830 | O4: =IF(N4="","",N4+P4-1) -> 44830 | P4: =IF(IF(J4="",0,IF(K4="",0,K4-J4))="",0,K4-J4+1) -> 1 | Q4: =IF(L4="",0,IF(M4="",TODAY()-L4,M4-L4+1)) -> 2 | R4: =IF(Q4=0,0,P4-Q4) -> -1 | S4: HITOMI ISUUE SLOVE
A5: =ROW() - ROW($A$58) + 56 -> 3 | B5: FINANCE | D5: Dd Processing | F5: NA | G5: LIVE | H5: LIVE | I5: LIVE | J5: 44833 | K5: 44833 | L5: 44832 | M5: 44833 | N5: =L5 -> 44832 | O5: =N5+P5-1 -> 44832 | P5: =IF(IF(J5="",0,IF(K5="",0,K5-J5))="",0,K5-J5+1) -> 1 | Q5: =IF(L5="",0,IF(M5="",TODAY()-L5,M5-L5+1)) -> 2 | R5: =IF(Q5=0,0,P5-Q5) -> -1 | S5: DEADLINE NOTIFICATION WORK BY BANITA MAM
A6: =ROW() - ROW($A$58) + 56 -> 4 | B6: FINANCE | D6: Bg Processing | F6: NA | G6: LIVE | H6: LIVE | I6: LIVE | J6: 44837 | K6: 44837 | L6: 44840 | M6: 44846 | N6: =IF(L6="",IF(M5="",O5+1,M5+1),L6) -> 44840 | O6: =IF(N6="","",N6+P6-1) -> 44840 | P6: =IF(IF(J6="",0,IF(K6="",0,K6-J6))="",0,K6-J6+1) -> 1 | Q6: =IF(L6="",0,IF(M6="",TODAY()-L6,M6-L6+1)) -> 7 | R6: =IF(Q6=0,0,P6-Q6) -> -6 | S6: DEADLINE NOTIFICATION WORK BY BANITA MAM
A7: =ROW() - ROW($A$58) + 56 -> 5 | B7: FINANCE | D7: Emd Processing | F7: NA | G7: LIVE | H7: LIVE | I7: LIVE | J7: 44840 | K7: 44840 | L7: 44834 | M7: 44834 | N7: =L7 -> 44834 | O7: =N7+P7-1 -> 44834 | P7: =IF(IF(J7="",0,IF(K7="",0,K7-J7))="",0,K7-J7+1) -> 1 | Q7: =IF(L7="",0,IF(M7="",TODAY()-L7,M7-L7+1)) -> 1 | R7: =IF(Q7=0,0,P7-Q7) -> 0 | S7: DEADLINE NOTIFICATION WORK BY BANITA MAM
A8: =ROW() - ROW($A$58) + 56 -> 6 | B8: FINANCE | D8: Cpbg Processing | F8: NA | G8: LIVE | H8: LIVE | I8: LIVE | J8: 44841 | K8: 44841 | L8: 44847 | M8: 44847 | N8: =IF(L8="",IF(M7="",O7+1,M7+1),L8) -> 44847 | O8: =IF(N8="","",N8+P8-1) -> 44847 | P8: =IF(IF(J8="",0,IF(K8="",0,K8-J8))="",0,K8-J8+1) -> 1 | Q8: =IF(L8="",0,IF(M8="",TODAY()-L8,M8-L8+1)) -> 1 | R8: =IF(Q8=0,0,P8-Q8) -> 0
A9: =ROW() - ROW($A$58) + 56 -> 7 | B9: FINANCE | D9: Spbg Processing | F9: NA | G9: LIVE | H9: LIVE | I9: LIVE | J9: 44844 | K9: 44844 | L9: 44848 | M9: 44848 | N9: =L9 -> 44848 | O9: =N9+P9-1 -> 44848 | P9: =IF(IF(J9="",0,IF(K9="",0,K9-J9))="",0,K9-J9+1) -> 1 | Q9: =IF(L9="",0,IF(M9="",TODAY()-L9,M9-L9+1)) -> 1 | R9: =IF(Q9=0,0,P9-Q9) -> 0
A10: =ROW() - ROW($A$58) + 56 -> 8 | B10: FINANCE | D10: Aps Processing | F10: NA | G10: LIVE | H10: LIVE | I10: LIVE | J10: 44845 | K10: 44845 | L10: 44849 | M10: 44849 | N10: =IF(L10="",IF(M9="",O9+1,M9+1),L10) -> 44849 | O10: =IF(N10="","",N10+P10-1) -> 44849 | P10: =IF(IF(J10="",0,IF(K10="",0,K10-J10))="",0,K10-J10+1) -> 1 | Q10: =IF(L10="",0,IF(M10="",TODAY()-L10,M10-L10+1)) -> 1 | R10: =IF(Q10=0,0,P10-Q10) -> 0
A11: =ROW() - ROW($A$58) + 56 -> 9 | B11: FINANCE | D11: Supplier Payment Request | F11: NA | G11: LIVE | H11: LIVE | I11: LIVE | J11: 44846 | K11: 44847 | L11: 44851 | M11: 44854 | N11: =L11 -> 44851 | O11: =N11+P11-1 -> 44852 | P11: =IF(IF(J11="",0,IF(K11="",0,K11-J11))="",0,K11-J11+1) -> 2 | Q11: =IF(L11="",0,IF(M11="",TODAY()-L11,M11-L11+1)) -> 4 | R11: =IF(Q11=0,0,P11-Q11) -> -2
A12: =ROW() - ROW($A$58) + 56 -> 10 | B12: FINANCE | D12: Remove Restriction In Job Order Rate Contract And Show Available Total Amount Instead Of Quantity. | F12: LIVE | G12: NA | H12: NA | I12: NA | J12: 44865 | K12: 44866 | L12: 44865 | M12: 44866 | N12: =IF(L12="",IF(M11="",O11+1,M11+1),L12) -> 44865 | O12: =IF(N12="","",N12+P12-1) -> 44866 | P12: =IF(IF(J12="",0,IF(K12="",0,K12-J12))="",0,K12-J12+1) -> 2
A13: =ROW() - ROW($A$58) + 56 -> 11 | B13: FINANCE | D13: Vendor Payment Request | F13: NA | G13: LIVE | H13: LIVE | I13: LIVE | J13: 44867 | K13: 44867 | L13: 44867 | M13: 44870 | N13: =L13 -> 44867 | O13: =N13+P13-1 -> 44867 | P13: =IF(IF(J13="",0,IF(K13="",0,K13-J13))="",0,K13-J13+1) -> 1 | Q13: =IF(L13="",0,IF(M13="",TODAY()-L13,M13-L13+1)) -> 4 | R13: =IF(Q13=0,0,P13-Q13) -> -3
A14: =ROW() - ROW($A$58) + 56 -> 12 | B14: FINANCE | D14: Transporter Payment Request | F14: NA | G14: LIVE | H14: LIVE | I14: LIVE | J14: 44868 | K14: 44868 | L14: 44872 | M14: 44873 | N14: =IF(L14="",IF(M13="",O13+1,M13+1),L14) -> 44872 | O14: =IF(N14="","",N14+P14-1) -> 44872 | P14: =IF(IF(J14="",0,IF(K14="",0,K14-J14))="",0,K14-J14+1) -> 1 | Q14: =IF(L14="",0,IF(M14="",TODAY()-L14,M14-L14+1)) -> 2 | R14: =IF(Q14=0,0,P14-Q14) -> -1
A15: =ROW() - ROW($A$58) + 56 -> 13 | B15: FINANCE | D15: Collection Payment Request | F15: NA | G15: LIVE | H15: LIVE | I15: LIVE | J15: 44869 | K15: 44869 | L15: 44874 | M15: 44876 | N15: =L15 -> 44874 | O15: =N15+P15-1 -> 44874 | P15: =IF(IF(J15="",0,IF(K15="",0,K15-J15))="",0,K15-J15+1) -> 1 | Q15: =IF(L15="",0,IF(M15="",TODAY()-L15,M15-L15+1)) -> 3 | R15: =IF(Q15=0,0,P15-Q15) -> -2
A16: =ROW() - ROW($A$58) + 56 -> 14 | B16: FINANCE | D16: Bug Fixing In All Security Type. | F16: COMPLETE | G16: NA | H16: NA | I16: NA | J16: 44870 | K16: 44870 | L16: 44879 | M16: 44880 | N16: =IF(L16="",IF(M15="",O15+1,M15+1),L16) -> 44879 | O16: =IF(N16="","",N16+P16-1) -> 44879 | P16: =IF(IF(J16="",0,IF(K16="",0,K16-J16))="",0,K16-J16+1) -> 1 | Q16: =IF(L16="",0,IF(M16="",TODAY()-L16,M16-L16+1)) -> 2 | R16: =IF(Q16=0,0,P16-Q16) -> -1
A17: =ROW() - ROW($A$58) + 56 -> 15 | B17: FINANCE | D17: Withdraw Payment Request | F17: NA | G17: LIVE | H17: LIVE | I17: LIVE | J17: 44872 | K17: 44872 | L17: 44879 | M17: 44880 | N17: =L17 -> 44879 | O17: =N17+P17-1 -> 44879 | P17: =IF(IF(J17="",0,IF(K17="",0,K17-J17))="",0,K17-J17+1) -> 1 | Q17: =IF(L17="",0,IF(M17="",TODAY()-L17,M17-L17+1)) -> 2 | R17: =IF(Q17=0,0,P17-Q17) -> -1
A18: =ROW() - ROW($A$58) + 56 -> 16 | B18: FINANCE | D18: Gst Payment Request | F18: NA | G18: LIVE | H18: LIVE | I18: LIVE | J18: 44873 | K18: 44873 | L18: 44879 | M18: 44880 | N18: =IF(L18="",IF(M17="",O17+1,M17+1),L18) -> 44879 | O18: =IF(N18="","",N18+P18-1) -> 44879 | P18: =IF(IF(J18="",0,IF(K18="",0,K18-J18))="",0,K18-J18+1) -> 1 | Q18: =IF(L18="",0,IF(M18="",TODAY()-L18,M18-L18+1)) -> 2 | R18: =IF(Q18=0,0,P18-Q18) -> -1
A19: =ROW() - ROW($A$58) + 56 -> 17 | B19: FINANCE | D19: Others Payment Request | F19: NA | G19: LIVE | H19: LIVE | I19: LIVE | J19: 44874 | K19: 44874 | L19: 44879 | M19: 44880 | N19: =L19 -> 44879 | O19: =N19+P19-1 -> 44879 | P19: =IF(IF(J19="",0,IF(K19="",0,K19-J19))="",0,K19-J19+1) -> 1 | Q19: =IF(L19="",0,IF(M19="",TODAY()-L19,M19-L19+1)) -> 2 | R19: =IF(Q19=0,0,P19-Q19) -> -1
A20: =ROW() - ROW($A$58) + 56 -> 18 | B20: FINANCE | D20: Rent Payment Request | F20: NA | G20: LIVE | H20: LIVE | I20: LIVE | J20: 44875 | K20: 44875 | L20: 44882 | M20: 44884 | N20: =IF(L20="",IF(M19="",O19+1,M19+1),L20) -> 44882 | O20: =IF(N20="","",N20+P20-1) -> 44882 | P20: =IF(IF(J20="",0,IF(K20="",0,K20-J20))="",0,K20-J20+1) -> 1 | Q20: =IF(L20="",0,IF(M20="",TODAY()-L20,M20-L20+1)) -> 3 | R20: =IF(Q20=0,0,P20-Q20) -> -2
A21: =ROW() - ROW($A$58) + 56 -> 19 | B21: RENT | D21: Rent Approval | F21: NA | G21: LIVE | H21: LIVE | I21: LIVE | J21: 44876 | K21: 44877 | L21: 44882 | M21: 44884 | N21: =L21 -> 44882 | O21: =N21+P21-1 -> 44883 | P21: =IF(IF(J21="",0,IF(K21="",0,K21-J21))="",0,K21-J21+1) -> 2 | Q21: =IF(L21="",0,IF(M21="",TODAY()-L21,M21-L21+1)) -> 3 | R21: =IF(Q21=0,0,P21-Q21) -> -1
A22: =ROW() - ROW($A$58) + 56 -> 20 | B22: RENT | D22: Rent Details | F22: NA | G22: LIVE | H22: LIVE | I22: LIVE | J22: 44878 | K22: 44880 | L22: 44882 | M22: 44884 | N22: =IF(L22="",IF(M21="",O21+1,M21+1),L22) -> 44882 | O22: =IF(N22="","",N22+P22-1) -> 44884 | P22: =IF(IF(J22="",0,IF(K22="",0,K22-J22))="",0,K22-J22+1) -> 3 | Q22: =IF(L22="",0,IF(M22="",TODAY()-L22,M22-L22+1)) -> 3 | R22: =IF(Q22=0,0,P22-Q22) -> 0
A23: =ROW() - ROW($A$58) + 56 -> 21 | B23: FINANCE | D23: Live Security Type (Fd,Bg,Emd,Cpbg,Spbg,Aps)Notification And Payment Request Notification | F23: COMPLETE | G23: NA | H23: NA | I23: NA | J23: 44886 | K23: 44886 | L23: 44886 | M23: 44886 | N23: =L23 -> 44886 | O23: =N23+P23-1 -> 44886 | P23: =IF(IF(J23="",0,IF(K23="",0,K23-J23))="",0,K23-J23+1) -> 1 | Q23: =IF(L23="",0,IF(M23="",TODAY()-L23,M23-L23+1)) -> 1 | R23: =IF(Q23=0,0,P23-Q23) -> 0
A24: =ROW() - ROW($A$58) + 56 -> 22 | B24: MENU ACCESS | D24: Link Menu Access To The Master Module | F24: LIVE | G24: NOT REQ | H24: NOT REQ | I24: NOT REQ | J24: 44887 | K24: 44889 | L24: 44887 | M24: 44890 | N24: =IF(L24="",IF(M23="",O23+1,M23+1),L24) -> 44887 | O24: =IF(N24="","",N24+P24-1) -> 44889 | P24: =IF(IF(J24="",0,IF(K24="",0,K24-J24))="",0,K24-J24+1) -> 3 | Q24: =IF(L24="",0,IF(M24="",TODAY()-L24,M24-L24+1)) -> 4 | R24: =IF(Q24=0,0,P24-Q24) -> -1
A25: =ROW() - ROW($A$58) + 56 -> 23 | B25: FINANCE | D25: Implenting Security New Design As Per Designer | F25: LIVE | G25: NOT REQ | H25: NOT REQ | I25: NOT REQ | J25: 44893 | K25: 44895 | L25: 44893 | M25: 44897 | N25: =L25 -> 44893 | O25: =N25+P25-1 -> 44895 | P25: =IF(IF(J25="",0,IF(K25="",0,K25-J25))="",0,K25-J25+1) -> 3 | Q25: =IF(L25="",0,IF(M25="",TODAY()-L25,M25-L25+1)) -> 5 | R25: =IF(Q25=0,0,P25-Q25) -> -2
A26: =ROW() - ROW($A$58) + 56 -> 24 | B26: FINANCE | D26: Add Tcs Rate In Po Supplier Payment Request Section. | F26: LIVE | G26: NOT REQ | H26: NOT REQ | I26: NOT REQ | J26: 44896 | K26: =J26+5 -> 44901 | L26: =J26+1 -> 44897 | M26: 44901 | N26: =IF(L26="",IF(M25="",O25+1,M25+1),L26) -> 44897 | O26: =IF(N26="","",N26+P26-1) -> 44902 | P26: =IF(IF(J26="",0,IF(K26="",0,K26-J26))="",0,K26-J26+1) -> 6 | Q26: =IF(L26="",0,IF(M26="",TODAY()-L26,M26-L26+1)) -> 5 | R26: =IF(Q26=0,0,P26-Q26) -> 1
A27: =ROW() - ROW($A$58) + 56 -> 25 | B27: FINANCE | D27: Add Pending Bank Account Details In Pending Approval | F27: LIVE | G27: NOT REQ | H27: NOT REQ | I27: NOT REQ | J27: =K26+1 -> 44902 | K27: =J27+2 -> 44904 | L27: =M26+1 -> 44902 | M27: =L27+2 -> 44904 | N27: =L27 -> 44902 | O27: =N27+P27-1 -> 44904 | P27: =IF(IF(J27="",0,IF(K27="",0,K27-J27))="",0,K27-J27+1) -> 3 | Q27: =IF(L27="",0,IF(M27="",TODAY()-L27,M27-L27+1)) -> 3 | R27: =IF(Q27=0,0,P27-Q27) -> 0
A28: =ROW() - ROW($A$58) + 56 -> 26 | B28: FINANCE | D28: Add Multiple Attachment File In Add Bank Account | E28: MAINTENANCE | F28: LIVE | G28: NOT REQ | H28: NOT REQ | I28: NOT REQ | J28: =K27+1 -> 44905 | K28: 44908 | L28: 44922 | M28: 44924 | N28: =IF(L28="",IF(M27="",O27+1,M27+1),L28) -> 44922 | O28: =IF(N28="","",N28+P28-1) -> 44925 | P28: =IF(IF(J28="",0,IF(K28="",0,K28-J28))="",0,K28-J28+1) -> 4 | Q28: =IF(L28="",0,IF(M28="",TODAY()-L28,M28-L28+1)) -> 3 | R28: =IF(Q28=0,0,P28-Q28) -> 1
A29: =ROW() - ROW($A$58) + 56 -> 27 | B29: FINANCE | D29: Payment Assign In Supplier Section And In Rent Section-Po Number Not Showing At The Time Of Payment Assignment.(Operational Issue) | F29: LIVE | G29: NOT REQ | H29: NOT REQ | I29: NOT REQ | J29: 44909 | K29: 44912 | L29: =J29+1 -> 44910 | M29: =L29+2 -> 44912 | N29: =L29 -> 44910 | O29: =N29+P29-1 -> 44913 | P29: =IF(IF(J29="",0,IF(K29="",0,K29-J29))="",0,K29-J29+1) -> 4 | Q29: =IF(L29="",0,IF(M29="",TODAY()-L29,M29-L29+1)) -> 3 | R29: =IF(Q29=0,0,P29-Q29) -> 1
A30: =ROW() - ROW($A$58) + 56 -> 28 | B30: FINANCE | D30: In Rent View Page Rent Details Should Be Shown | F30: LIVE | G30: NOT REQ | H30: NOT REQ | I30: NOT REQ | J30: 44913 | K30: 44915 | L30: =J30+1 -> 44914 | M30: 44915 | N30: =IF(L30="",IF(M29="",O29+1,M29+1),L30) -> 44914 | O30: =IF(N30="","",N30+P30-1) -> 44916 | P30: =IF(IF(J30="",0,IF(K30="",0,K30-J30))="",0,K30-J30+1) -> 3 | Q30: =IF(L30="",0,IF(M30="",TODAY()-L30,M30-L30+1)) -> 2 | R30: =IF(Q30=0,0,P30-Q30) -> 1
A31: =ROW() - ROW($A$58) + 56 -> 29 | B31: FINANCE | D31: Remove Bank Account & Import Data Form Live Server | F31: LIVE | G31: NOT REQ | H31: NOT REQ | I31: NOT REQ | J31: 44916 | K31: 44918 | L31: 44916 | M31: 44918 | N31: =L31 -> 44916 | O31: =N31+P31-1 -> 44918 | P31: =IF(IF(J31="",0,IF(K31="",0,K31-J31))="",0,K31-J31+1) -> 3 | Q31: =IF(L31="",0,IF(M31="",TODAY()-L31,M31-L31+1)) -> 3 | R31: =IF(Q31=0,0,P31-Q31) -> 0
A32: =ROW() - ROW($A$58) + 56 -> 30 | B32: FINANCE | D32: For Other Payment Request Background Color Should Be Different. | E32: MAINTENANCE | F32: LIVE | G32: NOT REQ | H32: NOT REQ | I32: NOT REQ | J32: =K31+1 -> 44919 | K32: =J32+2 -> 44921 | L32: =K32 -> 44921 | M32: =L32 -> 44921 | N32: =IF(L32="",IF(M31="",O31+1,M31+1),L32) -> 44921 | O32: =IF(N32="","",N32+P32-1) -> 44923 | P32: =IF(IF(J32="",0,IF(K32="",0,K32-J32))="",0,K32-J32+1) -> 3 | Q32: =IF(L32="",0,IF(M32="",TODAY()-L32,M32-L32+1)) -> 1 | R32: =IF(Q32=0,0,P32-Q32) -> 2
A33: =ROW() - ROW($A$58) + 56 -> 31 | B33: HI-TOMI | D33: Pending Approval Of Hi-Tomi | E33: MAINTENANCE | F33: LIVE | G33: NOT REQ | H33: NOT REQ | I33: NOT REQ | J33: =K32+1 -> 44922 | K33: =J33+5 -> 44927 | L33: 44924 | M33: 44929 | N33: =L33 -> 44924 | O33: =N33+P33-1 -> 44929 | P33: =IF(IF(J33="",0,IF(K33="",0,K33-J33))="",0,K33-J33+1) -> 6 | Q33: =IF(L33="",0,IF(M33="",TODAY()-L33,M33-L33+1)) -> 6 | R33: =IF(Q33=0,0,P33-Q33) -> 0
A34: =ROW() - ROW($A$58) + 56 -> 32 | B34: TABLEUE | D34: Prepare Finance Module Table List With All Column In Excel Sheet For Tableau | F34: COMPLETE | G34: NOT REQ | H34: NOT REQ | I34: NOT REQ | J34: 44932 | K34: 44933 | L34: 44932 | M34: 44933 | N34: =IF(L34="",IF(M33="",O33+1,M33+1),L34) -> 44932 | O34: =IF(N34="","",N34+P34-1) -> 44933 | P34: =IF(IF(J34="",0,IF(K34="",0,K34-J34))="",0,K34-J34+1) -> 2 | Q34: =IF(L34="",0,IF(M34="",TODAY()-L34,M34-L34+1)) -> 2 | R34: =IF(Q34=0,0,P34-Q34) -> 0
A35: =ROW() - ROW($A$58) + 56 -> 33 | B35: FINANCE | D35: Same Page Landing After Payment Assignment In Erp | E35: MAINTENANCE | F35: LIVE PENDING | G35: NOT REQ | H35: NOT REQ | I35: NOT REQ | J35: =K33+1 -> 44928 | K35: =J35+5 -> 44933 | L35: 44933 | M35: 44936 | N35: =L35 -> 44933 | O35: =N35+P35-1 -> 44938 | P35: =IF(IF(J35="",0,IF(K35="",0,K35-J35))="",0,K35-J35+1) -> 6 | Q35: =IF(L35="",0,IF(M35="",TODAY()-L35,M35-L35+1)) -> 4 | R35: =IF(Q35=0,0,P35-Q35) -> 2 | S35: live pending doe to Bank api implementation
A36: =ROW() - ROW($A$58) + 56 -> 34 | B36: FINANCE | D36: Date Filter In Payment Assignment | E36: MAINTENANCE | F36: LIVE | G36: NOT REQ | H36: NOT REQ | I36: NOT REQ | J36: =K35+1 -> 44934 | K36: =J36+6 -> 44940 | L36: 44937 | M36: 44943 | N36: =IF(L36="",IF(M35="",O35+1,M35+1),L36) -> 44937 | O36: =IF(N36="","",N36+P36-1) -> 44943 | P36: =IF(IF(J36="",0,IF(K36="",0,K36-J36))="",0,K36-J36+1) -> 7 | Q36: =IF(L36="",0,IF(M36="",TODAY()-L36,M36-L36+1)) -> 7 | R36: =IF(Q36=0,0,P36-Q36) -> 0
A37: =ROW() - ROW($A$58) + 56 -> 35 | B37: FINANCE | D37: Search Functionality In Payment Assign Page . | E37: IMPROVEMENT | F37: LIVE | G37: NOT REQ | H37: NOT REQ | I37: NOT REQ | J37: =K36+1 -> 44941 | K37: =J37+5 -> 44946 | L37: 44944 | M37: 44949 | N37: =L37 -> 44944 | O37: =N37+P37-1 -> 44949 | P37: =IF(IF(J37="",0,IF(K37="",0,K37-J37))="",0,K37-J37+1) -> 6 | Q37: =IF(L37="",0,IF(M37="",TODAY()-L37,M37-L37+1)) -> 6 | R37: =IF(Q37=0,0,P37-Q37) -> 0
A38: =ROW() - ROW($A$58) + 56 -> 36 | B38: FINANCE | D38: Transaction Wise Closing Balance & Bank Statement | E38: IMPROVEMENT | F38: LIVE | J38: =K37+1 -> 44947 | K38: =J38+1+1 -> 44949 | L38: 44950 | M38: 44951 | N38: =IF(L38="",IF(M37="",O37+1,M37+1),L38) -> 44950 | O38: =IF(N38="","",N38+P38-1) -> 44952 | P38: =IF(IF(J38="",0,IF(K38="",0,K38-J38))="",0,K38-J38+1) -> 3 | Q38: =IF(L38="",0,IF(M38="",TODAY()-L38,M38-L38+1)) -> 2 | R38: =IF(Q38=0,0,P38-Q38) -> 1
A39: =ROW() - ROW($A$58) + 56 -> 37 | B39: FINANCE | D39: Recheck Option In Payment Assignment | E39: MAINTENANCE | F39: LIVE PENDING | G39: NOT REQ | H39: NOT REQ | I39: NOT REQ | J39: =K38+1 -> 44950 | K39: =J39+5+1 -> 44956 | L39: 44953 | M39: 44961 | N39: =L39 -> 44953 | O39: =N39+P39-1 -> 44959 | P39: =IF(IF(J39="",0,IF(K39="",0,K39-J39))="",0,K39-J39+1) -> 7 | Q39: =IF(L39="",0,IF(M39="",TODAY()-L39,M39-L39+1)) -> 9 | R39: =IF(Q39=0,0,P39-Q39) -> -2 | S39: live pending doe to Bank api implementation
A40: =ROW() - ROW($A$58) + 56 -> 38 | B40: FINANCE | D40: Create Payment Assign Menu Under Finanace And Upload Searching And Modal Fucntionality In Dev And Live Server | F40: LIVE | G40: NOT REQ | H40: NOT REQ | I40: NOT REQ | J40: =K39+1 -> 44957 | K40: =J40+4 -> 44961 | L40: 44963 | M40: 44964 | N40: =IF(L40="",IF(M39="",O39+1,M39+1),L40) -> 44963 | O40: =IF(N40="","",N40+P40-1) -> 44967 | P40: =IF(IF(J40="",0,IF(K40="",0,K40-J40))="",0,K40-J40+1) -> 5 | Q40: =IF(L40="",0,IF(M40="",TODAY()-L40,M40-L40+1)) -> 2 | R40: =IF(Q40=0,0,P40-Q40) -> 3 | S40: live pending doe to Bank api implementation
A41: =ROW() - ROW($A$58) + 56 -> 39 | B41: FINANCE | D41: Edit Option While Payment Request | F41: LIVE | G41: NOT REQ | H41: NOT REQ | I41: NOT REQ | J41: =K40+1 -> 44962 | K41: =J41+2+2 -> 44966 | L41: 44965 | M41: 44972 | N41: =L41 -> 44965 | O41: =N41+P41-1 -> 44969 | P41: =IF(IF(J41="",0,IF(K41="",0,K41-J41))="",0,K41-J41+1) -> 5 | Q41: =IF(L41="",0,IF(M41="",TODAY()-L41,M41-L41+1)) -> 8 | R41: =IF(Q41=0,0,P41-Q41) -> -3 | S41: live pending doe to Bank api implementation
A42: =ROW() - ROW($A$58) + 56 -> 40 | B42: FINANCE | D42: Payment Assign In Pending Approval (For Initial And Final) | F42: LIVE | J42: =K41+1 -> 44967 | K42: =J42+5 -> 44972 | L42: 44973 | M42: =L42+4 -> 44977 | N42: =IF(L42="",IF(M41="",O41+1,M41+1),L42) -> 44973 | O42: =IF(N42="","",N42+P42-1) -> 44978 | P42: =IF(IF(J42="",0,IF(K42="",0,K42-J42))="",0,K42-J42+1) -> 6 | Q42: =IF(L42="",0,IF(M42="",TODAY()-L42,M42-L42+1)) -> 5 | R42: =IF(Q42=0,0,P42-Q42) -> 1 | S42: live pending doe to Bank api implementation
A43: =ROW() - ROW($A$58) + 56 -> 41 | B43: MASTER | D43: Approval Dynamic Master Flow Guide For Resco Billing | F43: COMPLETE | J43: =K42+1 -> 44973 | K43: =J43+3+1+1 -> 44978 | L43: =M42+1 -> 44978 | M43: =L43+2 -> 44980 | N43: =L43 -> 44978 | O43: =N43+P43-1 -> 44983 | P43: =IF(IF(J43="",0,IF(K43="",0,K43-J43))="",0,K43-J43+1) -> 6 | Q43: =IF(L43="",0,IF(M43="",TODAY()-L43,M43-L43+1)) -> 3 | R43: =IF(Q43=0,0,P43-Q43) -> 3
A44: =ROW() - ROW($A$58) + 56 -> 42 | B44: FINANCE | D44: Live All Payment Related Work, Fooding Related Work Approval Matrix Live. | F44: COMPLETE | J44: =K43+1 -> 44979 | K44: =J44+1 -> 44980 | L44: 44984 | M44: 44986 | N44: =IF(L44="",IF(M43="",O43+1,M43+1),L44) -> 44984 | O44: =+N44+P44-1 -> 44985 | P44: =IF(IF(J44="",0,IF(K44="",0,K44-J44))="",0,K44-J44+1) -> 2 | Q44: =IF(L44="",0,IF(M44="",TODAY()-L44,M44-L44+1)) -> 3 | R44: =IF(Q44=0,0,P44-Q44) -> -1
A45: =ROW() - ROW($A$58) + 56 -> 43 | B45: FINANCE | D45: Beneficiary Account Should Be Linked With Every Payment Request | E45: IMPROVEMENT | F45: LIVE | G45: NOT REQ | H45: NOT REQ | I45: NOT REQ | J45: =K44+1 -> 44981 | K45: =J45+4+2 -> 44987 | L45: 44987 | M45: 44993 | N45: =IF(L45="",IF(M44="",O44+1,M44+1),L45) -> 44987 | O45: =+N45+P45-1 -> 44993 | P45: =IF(IF(J45="",0,IF(K45="",0,K45-J45))="",0,K45-J45+1) -> 7 | Q45: =IF(L45="",0,IF(M45="",TODAY()-L45,M45-L45+1)) -> 7 | R45: =IF(Q45=0,0,P45-Q45) -> 0
A46: =ROW() - ROW($A$58) + 56 -> 44 | B46: 2ND STAGE | D46: Analysis Of 2Nd Stage Work | F46: COMPLETE | J46: =K45+1 -> 44988 | K46: =J46+3 -> 44991 | L46: =M45+1 -> 44994 | M46: =L46 -> 44994 | N46: =IF(L46="",IF(M45="",O45+1,M45+1),L46) -> 44994 | O46: =+N46+P46-1 -> 44997 | P46: =IF(IF(J46="",0,IF(K46="",0,K46-J46))="",0,K46-J46+1) -> 4 | Q46: =IF(L46="",0,IF(M46="",TODAY()-L46,M46-L46+1)) -> 1 | R46: =IF(Q46=0,0,P46-Q46) -> 3
A47: =ROW() - ROW($A$58) + 56 -> 45 | B47: FINANCE | D47: Un-Assigned Payment List | E47: IMPROVEMENT | F47: LIVE | J47: =K46+1 -> 44992 | K47: =J47+2 -> 44994 | L47: 44995 | M47: 44995 | N47: =IF(L47="",IF(M46="",O46+1,M46+1),L47) -> 44995 | O47: =+N47+P47-1 -> 44997 | P47: =IF(IF(J47="",0,IF(K47="",0,K47-J47))="",0,K47-J47+1) -> 3 | Q47: =IF(L47="",0,IF(M47="",TODAY()-L47,M47-L47+1)) -> 1 | R47: =IF(Q47=0,0,P47-Q47) -> 2
A48: =ROW() - ROW($A$58) + 56 -> 46 | B48: FINANCE | D48: Finance Bank Charges Assignment <1K Sangram, <10K Prabodh Sir, >10K Kk Sir, All Notification To Kk Sir | E48: IMPROVEMENT | F48: LIVE | J48: =K47+1 -> 44995 | K48: =J48+2 -> 44997 | L48: 44995 | M48: 44995 | N48: =IF(L48="",IF(M47="",O47+1,M47+1),L48) -> 44995 | O48: =+N48+P48-1 -> 44997 | P48: =IF(IF(J48="",0,IF(K48="",0,K48-J48))="",0,K48-J48+1) -> 3 | Q48: =IF(L48="",0,IF(M48="",TODAY()-L48,M48-L48+1)) -> 1 | R48: =IF(Q48=0,0,P48-Q48) -> 2
A49: =ROW() - ROW($A$58) + 56 -> 47 | B49: FINANCE | D49: Payment Assignment Issue In Live (Listing And Uploading Both Section) | E49: OPERATIONAL ISSUES | F49: COMPLETE | J49: =K48+1 -> 44998 | K49: =J49+2 -> 45000 | L49: =M46+3 -> 44997 | M49: =L49+4 -> 45001 | N49: =IF(L49="",IF(M48="",O48+1,M48+1),L49) -> 44997 | O49: =+N49+P49-1 -> 44999 | P49: =IF(IF(J49="",0,IF(K49="",0,K49-J49))="",0,K49-J49+1) -> 3 | Q49: =IF(L49="",0,IF(M49="",TODAY()-L49,M49-L49+1)) -> 5 | R49: =IF(Q49=0,0,P49-Q49) -> -2
A50: =ROW() - ROW($A$58) + 56 -> 48 | B50: MANUFACTURING | D50: List And Export Table Details For Manufacturing Module And Share With Pabitra | F50: COMPLETE | J50: =K49+1 -> 45001 | K50: =J50+1 -> 45002 | L50: 45002 | M50: =L50 -> 45002 | N50: =IF(L50="",IF(M49="",O49+1,M49+1),L50) -> 45002 | O50: =+N50+P50-1 -> 45003 | P50: =IF(IF(J50="",0,IF(K50="",0,K50-J50))="",0,K50-J50+1) -> 2 | Q50: =IF(L50="",0,IF(M50="",TODAY()-L50,M50-L50+1)) -> 1 | R50: =IF(Q50=0,0,P50-Q50) -> 1
A51: =ROW() - ROW($A$58) + 56 -> 49 | B51: FINANCE | D51: Show Beneficiary Details For Collection,Rent,Operator,Charity In Payment Request In Both Dev And Live Server. | F51: LIVE | J51: =K50+3 -> 45005 | K51: =J51+2 -> 45007 | L51: 45005 | M51: =L51+9 -> 45014 | N51: =IF(L51="",IF(M50="",O50+1,M50+1),L51) -> 45005 | O51: =+N51+P51-1 -> 45007 | P51: =IF(IF(J51="",0,IF(K51="",0,K51-J51))="",0,K51-J51+1) -> 3 | Q51: =IF(L51="",0,IF(M51="",TODAY()-L51,M51-L51+1)) -> 10 | R51: =IF(Q51=0,0,P51-Q51) -> -7
A52: =ROW() - ROW($A$58) + 56 -> 50 | D52: 2Nd Phase Discussion With Krushna Ch Sahoo | F52: COMPLETE | J52: =K51+1 -> 45008 | K52: =J52+1 -> 45009 | L52: =M51+1 -> 45015 | M52: =L52+1 -> 45016 | N52: =IF(L52="",IF(M51="",O51+1,M51+1),L52) -> 45015 | O52: =+N52+P52-1 -> 45016 | P52: =IF(IF(J52="",0,IF(K52="",0,K52-J52))="",0,K52-J52+1) -> 2 | Q52: =IF(L52="",0,IF(M52="",TODAY()-L52,M52-L52+1)) -> 2 | R52: =IF(Q52=0,0,P52-Q52) -> 0
A53: =ROW() - ROW($A$58) + 56 -> 51 | B53: FINANCE | D53: Supplier Payment Request Link With Approval Matrix | E53: 1ST STAGE | F53: LIVE | J53: =K52+1 -> 45010 | K53: =J53+5 -> 45015 | L53: 45017 | M53: =L53+5 -> 45022 | N53: =IF(L53="",IF(M52="",O52+1,M52+1),L53) -> 45017 | O53: =+N53+P53-1 -> 45022 | P53: =IF(IF(J53="",0,IF(K53="",0,K53-J53))="",0,K53-J53+1) -> 6 | Q53: =IF(L53="",0,IF(M53="",TODAY()-L53,M53-L53+1)) -> 6 | R53: =IF(Q53=0,0,P53-Q53) -> 0
A54: =ROW() - ROW($A$58) + 56 -> 52 | B54: FINANCE | D54: Once Click On Job Order All Job Details Will Be Shown In Pop Up | E54: IMPROVEMENT | F54: LIVE | G54: NOT REQ | H54: NOT REQ | I54: NOT REQ | J54: =K53+1 -> 45016 | K54: =J54+2 -> 45018 | L54: 45027 | M54: 45029 | N54: =IF(L54="",IF(M53="",O53+1,M53+1),L54) -> 45027 | O54: =+N54+P54-1 -> 45029 | P54: =IF(IF(J54="",0,IF(K54="",0,K54-J54))="",0,K54-J54+1) -> 3 | Q54: =IF(L54="",0,IF(M54="",TODAY()-L54,M54-L54+1)) -> 3 | R54: =IF(Q54=0,0,P54-Q54) -> 0
A55: =ROW() - ROW($A$58) + 56 -> 53 | B55: FINANCE | D55: Vendor Request As Per Project Work Flow.(Means Based On Credit Limit ) | E55: MAINTENANCE | F55: LIVE | G55: NOT REQ | H55: NOT REQ | I55: NOT REQ | J55: =K54+1 -> 45019 | K55: =J55+2+2+2 -> 45025 | L55: 45031 | M55: 45037 | N55: =IF(L55="",IF(M54="",O54+1,M54+1),L55) -> 45031 | O55: =+N55+P55-1 -> 45037 | P55: =IF(IF(J55="",0,IF(K55="",0,K55-J55))="",0,K55-J55+1) -> 7 | Q55: =IF(L55="",0,IF(M55="",TODAY()-L55,M55-L55+1)) -> 7 | R55: =IF(Q55=0,0,P55-Q55) -> 0
A56: =ROW() - ROW($A$58) + 56 -> 54 | B56: FINANCE | D56: Bank Payment Api | F56: COMPLETE | J56: =K55+1 -> 45026 | K56: =J56+3+1+1 -> 45031 | L56: 45044 | M56: 45049 | N56: =IF(L56="",IF(M55="",O55+1,M55+1),L56) -> 45044 | O56: =+N56+P56-1 -> 45049 | P56: =IF(IF(J56="",0,IF(K56="",0,K56-J56))="",0,K56-J56+1) -> 6 | Q56: =IF(L56="",0,IF(M56="",TODAY()-L56,M56-L56+1)) -> 6 | R56: =IF(Q56=0,0,P56-Q56) -> 0
A57: =ROW() - ROW($A$58) + 56 -> 55 | B57: FINANCE | D57: Check Payment Request Section Using New Approval Matrix And Check Payment Api . | F57: COMPLETE | J57: =K56+1 -> 45032 | K57: =J57+2 -> 45034 | L57: 45050 | M57: 45055 | N57: =IF(L57="",IF(M56="",O56+1,M56+1),L57) -> 45050 | O57: =+N57+P57-1 -> 45052 | P57: =IF(IF(J57="",0,IF(K57="",0,K57-J57))="",0,K57-J57+1) -> 3 | Q57: =IF(L57="",0,IF(M57="",TODAY()-L57,M57-L57+1)) -> 6 | R57: =IF(Q57=0,0,P57-Q57) -> -3
A58: =ROW() - ROW($A$58) + 56 -> 56 | B58: FINANCE | D58: Bank Api Integration For Direct Payment From View Page. | F58: COMPLETE | J58: =K57+1 -> 45035 | K58: =J58+7 -> 45042 | L58: 45056 | M58: 45063 | N58: =IF(L58="",IF(M57="",O57+1,M57+1),L58) -> 45056 | O58: =+N58+P58-1 -> 45063 | P58: =IF(IF(J58="",0,IF(K58="",0,K58-J58))="",0,K58-J58+1) -> 8 | Q58: =IF(L58="",0,IF(M58="",TODAY()-L58,M58-L58+1)) -> 8 | R58: =IF(Q58=0,0,P58-Q58) -> 0
A59: =ROW() - ROW($A$58) + 56 -> 57 | B59: MANUFACTURING | D59: Manufacturing Project Install | F59: COMPLETE | J59: =K58+1 -> 45043 | K59: =J59+5 -> 45048 | L59: 45064 | M59: 45071 | N59: =IF(L59="",IF(M58="",O58+1,M58+1),L59) -> 45064 | O59: =+N59+P59-1 -> 45069 | P59: =IF(IF(J59="",0,IF(K59="",0,K59-J59))="",0,K59-J59+1) -> 6 | Q59: =IF(L59="",0,IF(M59="",TODAY()-L59,M59-L59+1)) -> 8 | R59: =IF(Q59=0,0,P59-Q59) -> -2
A60: =ROW() - ROW($A$58) + 56 -> 58 | B60: APPROVAL MASTER | D60: Issue In Fetching Approval In Project Payment Section | F60: COMPLETE | J60: =K59+1 -> 45049 | K60: =J60+1 -> 45050 | L60: 45071 | M60: =L60+4 -> 45075 | N60: =IF(L60="",IF(M59="",O59+1,M59+1),L60) -> 45071 | O60: =+N60+P60-1 -> 45072 | P60: =IF(IF(J60="",0,IF(K60="",0,K60-J60))="",0,K60-J60+1) -> 2 | Q60: =IF(L60="",0,IF(M60="",TODAY()-L60,M60-L60+1)) -> 5 | R60: =IF(Q60=0,0,P60-Q60) -> -3
A61: =ROW() - ROW($A$58) + 56 -> 59 | B61: NEW | D61: Binding New Approval Matrix Code In Transport And Gst Section In Payment Request,Bind Pending Approval Of New Design Of Pending Approval And Manage Customer And Creditors,Binding Hold And Query. | E61: OTHER | F61: COMPLETE | J61: 45075 | K61: =J61+1+5+1+4 -> 45086 | L61: 45075 | M61: 45087 | N61: =IF(L61="",IF(M60="",O60+1,M60+1),L61) -> 45075 | O61: =+N61+P61-1 -> 45086 | P61: =IF(IF(J61="",0,IF(K61="",0,K61-J61))="",0,K61-J61+1) -> 12 | Q61: =IF(L61="",0,IF(M61="",TODAY()-L61,M61-L61+1)) -> 13 | R61: =IF(Q61=0,0,P61-Q61) -> -1
A62: =ROW() - ROW($A$58) + 56 -> 60 | B62: FINANCE | D62: Indusind Bank Api Integrate | E62: API | F62: PARTLY | L62: 45056 | M62: 45106
A63: =ROW() - ROW($A$58) + 56 -> 61 | B63: FINANCE | D63: Canara Bank Api Integrate | E63: API | F63: PARTLY
A64: =ROW() - ROW($A$58) + 56 -> 62 | B64: FINANCE | D64: Axis Bank Api Integrate | E64: API | F64: COMPLETE
A65: =ROW() - ROW($A$58) + 56 -> 63 | B65: FINANCE | D65: Kotak Bank Api Integrate | E65: API | F65: TO-DO
A66: =ROW() - ROW($A$58) + 56 -> 64 | B66: FINANCE | D66: Payment Request Listing Page New Design | E66: 2ND STAGE | F66: PARTLY | J66: 45094 | K66: 45100 | L66: 45094 | M66: 45099 | N66: =IF(L66="",IF(M65="",O65+1,M65+1),L66) -> 45094 | O66: =+N66+P66-1 -> 45100 | P66: =IF(IF(J66="",0,IF(K66="",0,K66-J66))="",0,K66-J66+1) -> 7 | Q66: =IF(L66="",0,IF(M66="",TODAY()-L66,M66-L66+1)) -> 6 | R66: =IF(Q66=0,0,P66-Q66) -> 1
A67: =ROW() - ROW($A$58) + 56 -> 65 | B67: MASTER | D67: Pending Group Function (Dh And Vh ) | F67: PARTLY
A68: =ROW() - ROW($A$58) + 56 -> 66 | B68: FINANCE | D68: Organization Name To Be Add In Other Payment Request(Epc,Resco,Corporate) | E68: IMPROVEMENT | F68: LIVE | J68: 45106 | K68: 45108 | L68: 45106 | M68: 45108 | N68: =IF(L68="",IF(M67="",O67+1,M67+1),L68) -> 45106 | O68: =+N68+P68-1 -> 45108 | P68: =IF(IF(J68="",0,IF(K68="",0,K68-J68))="",0,K68-J68+1) -> 3 | Q68: =IF(L68="",0,IF(M68="",TODAY()-L68,M68-L68+1)) -> 3 | R68: =IF(Q68=0,0,P68-Q68) -> 0
A69: =ROW() - ROW($A$58) + 56 -> 67 | B69: FINANCE | D69: Insert All Api Response Data Into Database And Create A New Field In Exiting Payment Table For Payment Status.Upload All Payment Section In The Live And Dev Server. | E69: API | F69: LIVE | J69: 45110 | K69: 45120 | L69: 45110 | M69: 45120 | N69: =IF(L69="",IF(M68="",O68+1,M68+1),L69) -> 45110 | O69: =+N69+P69-1 -> 45120 | P69: =IF(IF(J69="",0,IF(K69="",0,K69-J69))="",0,K69-J69+1) -> 11 | Q69: =IF(L69="",0,IF(M69="",TODAY()-L69,M69-L69+1)) -> 11 | R69: =IF(Q69=0,0,P69-Q69) -> 0
A70: =ROW() - ROW($A$58) + 56 -> 68 | B70: FINANCE | D70: Show Organisation Name And Po Currency In Supplier Section And Vendor Part | E70: IMPROVEMENT | F70: LIVE | J70: 45126 | K70: 45131 | L70: 45126 | M70: 45131 | N70: =IF(L70="",IF(M69="",O69+1,M69+1),L70) -> 45126 | O70: =+N70+P70-1 -> 45131 | P70: =IF(IF(J70="",0,IF(K70="",0,K70-J70))="",0,K70-J70+1) -> 6 | Q70: =IF(L70="",0,IF(M70="",TODAY()-L70,M70-L70+1)) -> 6 | R70: =IF(Q70=0,0,P70-Q70) -> 0
A71: =ROW() - ROW($A$58) + 56 -> 69 | B71: FINANCE | D71: Payment For Expense Section In Payment Pending Section | F71: LIVE | J71: =K70+1 -> 45132 | K71: =J71+6 -> 45138 | L71: 45132 | M71: 45139 | N71: =IF(L71="",IF(M70="",O70+1,M70+1),L71) -> 45132 | O71: =+N71+P71-1 -> 45138 | P71: =IF(IF(J71="",0,IF(K71="",0,K71-J71))="",0,K71-J71+1) -> 7 | Q71: =IF(L71="",0,IF(M71="",TODAY()-L71,M71-L71+1)) -> 8 | R71: =IF(Q71=0,0,P71-Q71) -> -1
A72: =ROW() - ROW($A$58) + 56 -> 70 | B72: FINANCE | D72: Approval Functionality In Supllier Payment Request (Checking All Section Including Ra) | E72: IMPROVEMENT | F72: LIVE | J72: 45143 | K72: 45147 | L72: 45143 | M72: 45149 | N72: =IF(L72="",IF(M71="",O71+1,M71+1),L72) -> 45143 | O72: =+N72+P72-1 -> 45147 | P72: =IF(IF(J72="",0,IF(K72="",0,K72-J72))="",0,K72-J72+1) -> 5 | Q72: =IF(L72="",0,IF(M72="",TODAY()-L72,M72-L72+1)) -> 7 | R72: =IF(Q72=0,0,P72-Q72) -> -2
A73: =ROW() - ROW($A$58) + 56 -> 71 | B73: FINANCE | D73: Manual Functionality Of The Api Online Erp Payment - Expense | E73: API | F73: LIVE | J73: 45152 | K73: 45156 | L73: 45152 | M73: 45159 | N73: =IF(L73="",IF(M72="",O72+1,M72+1),L73) -> 45152 | O73: =+N73+P73-1 -> 45156 | P73: =IF(IF(J73="",0,IF(K73="",0,K73-J73))="",0,K73-J73+1) -> 5 | Q73: =IF(L73="",0,IF(M73="",TODAY()-L73,M73-L73+1)) -> 8 | R73: =IF(Q73=0,0,P73-Q73) -> -3
A74: =ROW() - ROW($A$58) + 56 -> 72 | B74: FINANCE | D74: Is Parallel Function (All Modules) | E74: IMPROVEMENT | F74: LIVE
A75: =ROW() - ROW($A$58) + 56 -> 73 | B75: FINANCE | D75: In Pending Approval, A Sub Count Should Be Shown For Different Cash Range | E75: IMPROVEMENT | F75: LIVE
A76: =ROW() - ROW($A$58) + 56 -> 74 | B76: FINANCE | D76: In Pending Approval, When We Approve An Entry Its Still Showing In Pending Approval List | E76: IMPROVEMENT | F76: LIVE
A77: =ROW() - ROW($A$58) + 56 -> 75 | B77: FINANCE | D77: Release Functionality (Notification Id Changed) | E77: IMPROVEMENT | F77: LIVE
A78: =ROW() - ROW($A$58) + 56 -> 76 | B78: FINANCE | D78: Customer & Local Supplier Section Live | E78: IMPROVEMENT | F78: LIVE | J78: 45167 | K78: 45170 | L78: 45167 | M78: 45170 | N78: =IF(L78="",IF(M77="",O77+1,M77+1),L78) -> 45167 | O78: =+N78+P78-1 -> 45170 | P78: =IF(IF(J78="",0,IF(K78="",0,K78-J78))="",0,K78-J78+1) -> 4 | Q78: =IF(L78="",0,IF(M78="",TODAY()-L78,M78-L78+1)) -> 4 | R78: =IF(Q78=0,0,P78-Q78) -> 0 | S78: =S76+S77 -> 0 | T78: 108478
A79: =ROW() - ROW($A$58) + 56 -> 77 | B79: FINANCE | D79: Po Acceptance Mandatory For Supplier Payment | E79: IMPROVEMENT | F79: LIVE | N79: =IF(L79="",IF(M78="",O78+1,M78+1),L79) -> 45171 | O79: =+N79+P79-1 -> 45171 | P79: =IF(IF(J79="",0,IF(K79="",0,K79-J79))="",0,K79-J79+1) -> 1 | Q79: =IF(L79="",0,IF(M79="",TODAY()-L79,M79-L79+1)) -> 0 | R79: =IF(Q79=0,0,P79-Q79) -> 0
A80: =ROW() - ROW($A$58) + 56 -> 78 | B80: FINANCE | D80: Po Acceptance Mandatory For Cheque Processing | E80: IMPROVEMENT | F80: LIVE | N80: =IF(L80="",IF(M79="",O79+1,M79+1),L80) -> 45172 | O80: =+N80+P80-1 -> 45172 | P80: =IF(IF(J80="",0,IF(K80="",0,K80-J80))="",0,K80-J80+1) -> 1 | Q80: =IF(L80="",0,IF(M80="",TODAY()-L80,M80-L80+1)) -> 0 | R80: =IF(Q80=0,0,P80-Q80) -> 0 | T80: =T78-S78 -> 108478
A81: =ROW() - ROW($A$58) + 56 -> 79 | B81: FINANCE | D81: Sms Otp Functionality For Bank Api Erp Payment | E81: API | F81: LIVE | J81: 45170 | K81: 45174 | L81: 45170 | M81: 45175 | N81: =IF(L81="",IF(M80="",O80+1,M80+1),L81) -> 45170 | O81: =+N81+P81-1 -> 45174 | P81: =IF(IF(J81="",0,IF(K81="",0,K81-J81))="",0,K81-J81+1) -> 5 | Q81: =IF(L81="",0,IF(M81="",TODAY()-L81,M81-L81+1)) -> 6 | R81: =IF(Q81=0,0,P81-Q81) -> -1
A82: =ROW() - ROW($A$58) + 56 -> 80 | B82: MASTER | D82: Manage State Isuue Fix | E82: LIVE WORK | F82: LIVE | J82: 45175 | K82: 45176 | L82: 45175 | M82: 45177 | N82: =IF(L82="",IF(M81="",O81+1,M81+1),L82) -> 45175 | O82: =+N82+P82-1 -> 45176 | P82: =IF(IF(J82="",0,IF(K82="",0,K82-J82))="",0,K82-J82+1) -> 2 | Q82: =IF(L82="",0,IF(M82="",TODAY()-L82,M82-L82+1)) -> 3 | R82: =IF(Q82=0,0,P82-Q82) -> -1
A83: =ROW() - ROW($A$58) + 56 -> 81 | B83: MASTER | D83: Expense Module Complete Flow Test & Manage District Flow Check | E83: OTHER | F83: LIVE | J83: 45178 | K83: 45182 | L83: 45178 | M83: 45182 | N83: =IF(L83="",IF(M82="",O82+1,M82+1),L83) -> 45178 | O83: =+N83+P83-1 -> 45182 | P83: =IF(IF(J83="",0,IF(K83="",0,K83-J83))="",0,K83-J83+1) -> 5 | Q83: =IF(L83="",0,IF(M83="",TODAY()-L83,M83-L83+1)) -> 5 | R83: =IF(Q83=0,0,P83-Q83) -> 0
A84: =ROW() - ROW($A$58) + 56 -> 82 | B84: FINANCE | C84: EXPENSE | D84: Sms Otp Functionality Supplier Payment Request | E84: API | F84: DEV COMPLETE | J84: 45183 | K84: 45185 | L84: 45183 | M84: =L84+4 -> 45187 | N84: =IF(L84="",IF(M83="",O83+1,M83+1),L84) -> 45183 | O84: =+N84+P84-1 -> 45185 | P84: =IF(IF(J84="",0,IF(K84="",0,K84-J84))="",0,K84-J84+1) -> 3 | Q84: =IF(L84="",0,IF(M84="",TODAY()-L84,M84-L84+1)) -> 5 | R84: =IF(Q84=0,0,P84-Q84) -> -2
A85: =ROW() - ROW($A$58) + 56 -> 83 | B85: FINANCE | C85: PC PROCESSING | D85: Po Acceptance Mandatory In Lc | E85: IMPROVEMENT | F85: LIVE
A86: =ROW() - ROW($A$58) + 56 -> 84 | B86: MASTER | C86: MANAGE LCATION | D86: Manage Location Testing & Upload In Dev Server | E86: 2ND STAGE | F86: LIVE | J86: 45187 | K86: 45197 | L86: 45188 | M86: 45205 | N86: =IF(L86="",IF(M84="",O84+1,M84+1),L86) -> 45188 | O86: =+N86+P86-1 -> 45198 | P86: =IF(IF(J86="",0,IF(K86="",0,K86-J86))="",0,K86-J86+1) -> 11 | Q86: =IF(L86="",0,IF(M86="",TODAY()-L86,M86-L86+1)) -> 18 | R86: =IF(Q86=0,0,P86-Q86) -> -7
A87: =ROW() - ROW($A$58) + 56 -> 85 | B87: FINANCE | D87: Excel Download | F87: LIVE
A88: =ROW() - ROW($A$58) + 56 -> 86 | B88: MASTER | C88: MANAGE CUSTOMER | D88: Manage Customer Live Issue | E88: TESTING ISSUE | F88: LIVE | J88: 45225 | K88: 45226 | L88: 45225 | M88: 45227 | N88: =IF(L88="",IF(M86="",O86+1,M86+1),L88) -> 45225 | O88: =+N88+P88-1 -> 45226 | P88: =IF(IF(J88="",0,IF(K88="",0,K88-J88))="",0,K88-J88+1) -> 2 | Q88: =IF(L88="",0,IF(M88="",TODAY()-L88,M88-L88+1)) -> 3 | R88: =IF(Q88=0,0,P88-Q88) -> -1
A89: =ROW() - ROW($A$58) + 56 -> 87 | B89: FINANCE | D89: Issue checking of team | E89: TESTING ISSUE | F89: LIVE | J89: 45229 | K89: 45233 | L89: 45229 | M89: 45238 | N89: =IF(L89="",IF(M87="",O87+1,M87+1),L89) -> 45229 | O89: =+N89+P89-1 -> 45228
A90: =ROW() - ROW($A$58) + 56 -> 88 | B90: FINANCE | D90: Axis Bank Api Postman Checking | E90: API | F90: LIVE | J90: 45236 | K90: 45240 | L90: 45236 | M90: 45244 | N90: =IF(L90="",IF(M88="",O88+1,M88+1),L90) -> 45236 | O90: =+N90+P90-1 -> 45240 | P90: =IF(IF(J90="",0,IF(K90="",0,K90-J90))="",0,K90-J90+1) -> 5 | Q90: =IF(L90="",0,IF(M90="",TODAY()-L90,M90-L90+1)) -> 9 | R90: =IF(Q90=0,0,P90-Q90) -> -4
A91: =ROW() - ROW($A$58) + 56 -> 89 | B91: MASTER | C91: MANAGE CUSTOMER | D91: Issue In Manage Customer In Edit Part., Check Code In Manage Organisation (Soumya Part) | E91: TESTING ISSUE | F91: LIVE | J91: 45245 | K91: 45246 | L91: 45245 | M91: 45246 | N91: =IF(L91="",IF(M89="",O89+1,M89+1),L91) -> 45245 | O91: =+N91+P91-1 -> 45246 | P91: =IF(IF(J91="",0,IF(K91="",0,K91-J91))="",0,K91-J91+1) -> 2 | Q91: =IF(L91="",0,IF(M91="",TODAY()-L91,M91-L91+1)) -> 2 | R91: =IF(Q91=0,0,P91-Q91) -> 0
A92: =ROW() - ROW($A$58) + 56 -> 90 | B92: FINANCE | C92: CHECQ PROCESSING | D92: Show Po Details In Cheque Processing An Live it.Check and upload fd register into llive server under security . | E92: OTHER | F92: LIVE | J92: 45248 | K92: 45248 | L92: 45248 | M92: 45253 | N92: =IF(L92="",IF(M90="",O90+1,M90+1),L92) -> 45248 | O92: =+N92+P92-1 -> 45248 | P92: =IF(IF(J92="",0,IF(K92="",0,K92-J92))="",0,K92-J92+1) -> 1 | Q92: =IF(L92="",0,IF(M92="",TODAY()-L92,M92-L92+1)) -> 6 | R92: =IF(Q92=0,0,P92-Q92) -> -5
A93: =ROW() - ROW($A$58) + 56 -> 91 | B93: FINANCE | C93: OPERATER PAYMENT REQUEST | D93: operator payment not showing in pending approval and axis api access process in its portal | E93: OTHER | F93: COMPLETE | J93: 45254 | K93: 45259 | L93: 45254 | M93: 45261 | N93: =IF(L93="",IF(M91="",O91+1,M91+1),L93) -> 45254 | O93: =+N93+P93-1 -> 45259 | P93: =IF(IF(J93="",0,IF(K93="",0,K93-J93))="",0,K93-J93+1) -> 6 | Q93: =IF(L93="",0,IF(M93="",TODAY()-L93,M93-L93+1)) -> 8 | R93: =IF(Q93=0,0,P93-Q93) -> -2
A94: =ROW() - ROW($A$58) + 56 -> 92 | B94: MASTER | D94: RA Link In the Dynamic approval Master | E94: IMPROVEMENT | F94: LIVE | J94: 45261 | K94: 45265 | L94: 45261 | N94: =IF(L94="",IF(M92="",O92+1,M92+1),L94) -> 45261 | O94: =+N94+P94-1 -> 45265 | P94: =IF(IF(J94="",0,IF(K94="",0,K94-J94))="",0,K94-J94+1) -> 5 | R94: =IF(Q94=0,0,P94-Q94) -> 0
A95: =ROW() - ROW($A$58) + 56 -> 93 | B95: FINANCE | D95: Binding pending approval changes in design and optimise some code in finanace module in live server. | E95: IMPROVEMENT | F95: LIVE | J95: 45262 | K95: 45262 | L95: 45262 | M95: 45263 | N95: =IF(L95="",IF(M93="",O93+1,M93+1),L95) -> 45262 | O95: =+N95+P95-1 -> 45262 | P95: =IF(IF(J95="",0,IF(K95="",0,K95-J95))="",0,K95-J95+1) -> 1 | Q95: =IF(L95="",0,IF(M95="",TODAY()-L95,M95-L95+1)) -> 2 | R95: =IF(Q95=0,0,P95-Q95) -> -1
A96: =ROW() - ROW($A$58) + 56 -> 94 | B96: FINANCE | D96: Transfer dev server code into new server. | E96: IMPROVEMENT | F96: COMPLETE | J96: 45264 | K96: 45265 | L96: 45264 | M96: 45282 | N96: =IF(L96="",IF(M94="",O94+1,M94+1),L96) -> 45264 | O96: =+N96+P96-1 -> 45265 | P96: =IF(IF(J96="",0,IF(K96="",0,K96-J96))="",0,K96-J96+1) -> 2 | Q96: =IF(L96="",0,IF(M96="",TODAY()-L96,M96-L96+1)) -> 19 | R96: =IF(Q96=0,0,P96-Q96) -> -17
A97: =ROW() - ROW($A$58) + 56 -> 95 | B97: FINANCE | D97: Axis bank api implementation in postman | E97: IMPROVEMENT | F97: COMPLETE | J97: 45275 | K97: 45283 | L97: 45275 | M97: 45283 | N97: =IF(L97="",IF(M95="",O95+1,M95+1),L97) -> 45275 | O97: =+N97+P97-1 -> 45283 | P97: =IF(IF(J97="",0,IF(K97="",0,K97-J97))="",0,K97-J97+1) -> 9 | Q97: =IF(L97="",0,IF(M97="",TODAY()-L97,M97-L97+1)) -> 9 | R97: =IF(Q97=0,0,P97-Q97) -> 0
A98: =ROW() - ROW($A$58) + 56 -> 96 | B98: MASTER | D98: Manage category , sub category ,manage group ,manage sub group and material issue and payment request issue in dev server. | E98: TESTING ISSUE | F98: LIVE | J98: 45285 | K98: 45286 | L98: 45283 | M98: 45286 | N98: =IF(L98="",IF(M96="",O96+1,M96+1),L98) -> 45283 | O98: =+N98+P98-1 -> 45284 | P98: =IF(IF(J98="",0,IF(K98="",0,K98-J98))="",0,K98-J98+1) -> 2 | Q98: =IF(L98="",0,IF(M98="",TODAY()-L98,M98-L98+1)) -> 4 | R98: =IF(Q98=0,0,P98-Q98) -> -2
A99: =ROW() - ROW($A$58) + 56 -> 97 | B99: FINANCE | D99: Modification in EMD processing | E99: IMPROVEMENT | F99: LIVE | J99: 45287 | K99: 45288 | L99: 45286 | M99: 45289 | N99: =IF(L99="",IF(M97="",O97+1,M97+1),L99) -> 45286 | O99: =+N99+P99-1 -> 45287 | P99: =IF(IF(J99="",0,IF(K99="",0,K99-J99))="",0,K99-J99+1) -> 2 | Q99: =IF(L99="",0,IF(M99="",TODAY()-L99,M99-L99+1)) -> 4 | R99: =IF(Q99=0,0,P99-Q99) -> -2
A100: =ROW() - ROW($A$58) + 56 -> 98 | B100: FINANCE | D100: Implement dd processing changes in payment assign. | E100: OTHER | F100: LIVE PENDING | J100: 45290 | K100: 45292 | L100: 45290 | M100: 45293 | N100: =IF(L100="",IF(M98="",O98+1,M98+1),L100) -> 45290 | O100: =+N100+P100-1 -> 45292 | P100: =IF(IF(J100="",0,IF(K100="",0,K100-J100))="",0,K100-J100+1) -> 3 | Q100: =IF(L100="",0,IF(M100="",TODAY()-L100,M100-L100+1)) -> 4 | R100: =IF(Q100=0,0,P100-Q100) -> -1
...

Sheet SAILESH DAKUA
P1: =SUM(P3:P1037) -> 229 | Q1: =SUM(Q3:Q1037) -> 484 | R1: =SUM(R3:R1037) -> -255
A2: SL.NO. | B2: MODULE | C2: SUB MODULE | D2: ACTIVITIES | E2: WORK TYPE | F2: STATUS | G2: APPROVAL | H2: RESTRICTION | I2: NOTIFICATION | J2: TGT ST DATE | K2: TGT END DATE | L2: ACT ST DATE | M2: ACT END DATE | N2: PROB ST DT | O2: PROB END DT | P2: TGT DUR | Q2: ACT DUR | R2: T SAVING | S2: DELAY REASON STATUS
A3: 1 | B3: FINANCE | D3: Set Up Erp In Local Host. Analysis Finance Payment Section. | F3: COMPLETE | J3: 45211 | K3: 45212 | L3: 45211 | M3: 45215 | N3: =L3 -> 45211 | O3: =N3+P3-1 -> 45212 | P3: =IF(IF(J3="",0,IF(K3="",0,K3-J3))="",0,K3-J3+1) -> 2 | Q3: =IF(L3="",0,IF(M3="",TODAY()-L3,M3-L3+1)) -> 5 | R3: =IF(Q3=0,0,P3-Q3) -> -3
A4: 2 | B4: FINANCE | C4: ALL SECURITY TYPE | D4: Excel Download Functionality In all scerity type | E4: Excel download | F4: LIVE | J4: 45215 | K4: 45219 | L4: 45215 | M4: 45219 | N4: =IF(L4="",IF(M3="",O3+1,M3+1),L4) -> 45215 | O4: =IF(N4="","",N4+P4-1) -> 45219 | P4: =IF(IF(J4="",0,IF(K4="",0,K4-J4))="",0,K4-J4+1) -> 5 | Q4: =IF(L4="",0,IF(M4="",TODAY()-L4,M4-L4+1)) -> 5 | R4: =IF(Q4=0,0,P4-Q4) -> 0
A5: 3 | B5: FINANCE | C5: FD PROCESSING | D5: Fd processing (All securiry)2nd stage design | E5: 2nd stage | F5: COMPLETE | J5: 45220 | K5: 45268 | L5: 45220 | M5: 45280 | N5: =IF(L5="",IF(M4="",O4+1,M4+1),L5) -> 45220 | O5: =IF(N5="","",N5+P5-1) -> 45268 | P5: =IF(IF(J5="",0,IF(K5="",0,K5-J5))="",0,K5-J5+1) -> 49 | Q5: =IF(L5="",0,IF(M5="",TODAY()-L5,M5-L5+1)) -> 61 | R5: =IF(Q5=0,0,P5-Q5) -> -12
A6: 4 | B6: FINANCE | C6: FD REGISTER | D6: FD REGISTER NEW DESIGN. | F6: LIVE | J6: 45232 | K6: 45236 | L6: 45236 | M6: 45238 | N6: =IF(L6="",IF(M5="",O5+1,M5+1),L6) -> 45236 | O6: =IF(N6="","",N6+P6-1) -> 45240 | P6: =IF(IF(J6="",0,IF(K6="",0,K6-J6))="",0,K6-J6+1) -> 5 | Q6: =IF(L6="",0,IF(M6="",TODAY()-L6,M6-L6+1)) -> 3 | R6: =IF(Q6=0,0,P6-Q6) -> 2
A7: 5 | B7: MASTER | C7: MANAGE CUSTOMER | D7: Php Pagination And Create A New Page For Edit/Update In Manage Customers. | E7: Pagination | F7: LIVE | J7: 45237 | K7: 45239 | L7: 45238 | M7: 45246 | N7: =IF(L7="",IF(M6="",#REF!+1,M6+1),L7) -> 45238 | O7: =IF(N7="","",N7+P7-1) -> 45240 | P7: =IF(IF(J7="",0,IF(K7="",0,K7-J7))="",0,K7-J7+1) -> 3 | Q7: =IF(L7="",0,IF(M7="",TODAY()-L7,M7-L7+1)) -> 9 | R7: =IF(Q7=0,0,P7-Q7) -> -6
A8: 6 | B8: FINANCE | C8: PAYMENT ASSIGN | D8: Payment assign pagination and exccel download | E8: Page slow issue solve | F8: LIVE | J8: 45245 | K8: 45248 | L8: 45246 | M8: 45250 | N8: =IF(L8="",IF(M7="",O7+1,M7+1),L8) -> 45246 | O8: =IF(N8="","",N8+P8-1) -> 45249 | P8: =IF(IF(J8="",0,IF(K8="",0,K8-J8))="",0,K8-J8+1) -> 4 | Q8: =IF(L8="",0,IF(M8="",TODAY()-L8,M8-L8+1)) -> 5 | R8: =IF(Q8=0,0,P8-Q8) -> -1
A9: 7 | B9: FINANCE | C9: DD REGISTER | D9: DD register 2nd phase design | E9: Register | F9: LIVE | J9: 45250 | K9: 45257 | L9: 45250 | M9: 45254 | N9: =IF(L9="",IF(#REF!="",#REF!+1,#REF!+1),L9) -> 45250 | O9: =IF(N9="","",N9+P9-1) -> 45257 | P9: =IF(IF(J9="",0,IF(K9="",0,K9-J9))="",0,K9-J9+1) -> 8 | Q9: =IF(L9="",0,IF(M9="",TODAY()-L9,M9-L9+1)) -> 5 | R9: =IF(Q9=0,0,P9-Q9) -> 3
A10: 8 | B10: FINANCE | C10: DD PROCESSING | D10: pdf issue in view page of dd | F10: COMPLETE | J10: 45260 | K10: 45262 | L10: 45260 | M10: 45260 | N10: =IF(L10="",IF(#REF!="",#REF!+1,#REF!+1),L10) -> 45260 | O10: =IF(N10="","",N10+P10-1) -> 45262 | P10: =IF(IF(J10="",0,IF(K10="",0,K10-J10))="",0,K10-J10+1) -> 3 | Q10: =IF(L10="",0,IF(M10="",TODAY()-L10,M10-L10+1)) -> 1 | R10: =IF(Q10=0,0,P10-Q10) -> 2
A11: 9 | B11: FINANCE | C11: FD PROCESSING | D11: FD Processing (All securiry)2nd stage implementation | E11: IMPROVEMENT | F11: TESTING | J11: 45232 | K11: 45268 | L11: 45260 | M11: 45313 | N11: =IF(L11="",IF(#REF!="",#REF!+1,#REF!+1),L11) -> 45260 | O11: =IF(N11="","",N11+P11-1) -> 45296 | P11: =IF(IF(J11="",0,IF(K11="",0,K11-J11))="",0,K11-J11+1) -> 37 | Q11: =IF(L11="",0,IF(M11="",TODAY()-L11,M11-L11+1)) -> 54 | R11: =IF(Q11=0,0,P11-Q11) -> -17
A12: 10 | B12: MASTER | C12: DD PROCESSING | D12: Dd processing and fd processing with dynaic approval | E12: IMPROVEMENT | F12: TESTING | J12: 45269 | K12: 45271 | L12: 45281 | M12: 45313 | N12: =IF(L12="",IF(#REF!="",#REF!+1,#REF!+1),L12) -> 45281 | O12: =IF(N12="","",N12+P12-1) -> 45283 | P12: =IF(IF(J12="",0,IF(K12="",0,K12-J12))="",0,K12-J12+1) -> 3 | Q12: =IF(L12="",0,IF(M12="",TODAY()-L12,M12-L12+1)) -> 33 | R12: =IF(Q12=0,0,P12-Q12) -> -30
A13: 11 | B13: FINANCE | C13: PAYMENT REQUEST | D13: Excel Download Functionality In all payment request | E13: IMPROVEMENT | F13: LIVE | J13: 45288 | K13: 45289 | L13: 45288 | M13: 45295 | N13: =IF(L13="",IF(#REF!="",#REF!+1,#REF!+1),L13) -> 45288 | O13: =IF(N13="","",N13+P13-1) -> 45289 | P13: =IF(IF(J13="",0,IF(K13="",0,K13-J13))="",0,K13-J13+1) -> 2 | Q13: =IF(L13="",0,IF(M13="",TODAY()-L13,M13-L13+1)) -> 8 | R13: =IF(Q13=0,0,P13-Q13) -> -6
A14: 12 | B14: FINANCE | C14: LOAN REGISTER | D14: Add all organisation in term loan section | E14: IMPROVEMENT | F14: LIVE | J14: 45294 | K14: 45297 | L14: 45295 | M14: 45301 | N14: =IF(L14="",IF(#REF!="",#REF!+1,#REF!+1),L14) -> 45295 | O14: =IF(N14="","",N14+P14-1) -> 45298 | P14: =IF(IF(J14="",0,IF(K14="",0,K14-J14))="",0,K14-J14+1) -> 4 | Q14: =IF(L14="",0,IF(M14="",TODAY()-L14,M14-L14+1)) -> 7 | R14: =IF(Q14=0,0,P14-Q14) -> -3
A15: 13 | D15: Create Database Diagram of ERP . | E15: IMPROVEMENT | F15: COMPLETE | J15: 45299 | K15: 45306 | L15: 45299 | M15: 45315 | N15: =IF(L15="",IF(#REF!="",#REF!+1,#REF!+1),L15) -> 45299 | O15: =IF(N15="","",N15+P15-1) -> 45306 | P15: =IF(IF(J15="",0,IF(K15="",0,K15-J15))="",0,K15-J15+1) -> 8 | Q15: =IF(L15="",0,IF(M15="",TODAY()-L15,M15-L15+1)) -> 17 | R15: =IF(Q15=0,0,P15-Q15) -> -9
A16: 14 | B16: FINANCE | C16: BG REGISTER | D16: BG register 2nd stage design with new modification | E16: 2nd stage design | F16: LIVE | J16: 45301 | K16: 45303 | L16: 45301 | M16: 45302 | N16: =IF(L16="",IF(#REF!="",#REF!+1,#REF!+1),L16) -> 45301 | O16: =IF(N16="","",N16+P16-1) -> 45303 | P16: =IF(IF(J16="",0,IF(K16="",0,K16-J16))="",0,K16-J16+1) -> 3 | Q16: =IF(L16="",0,IF(M16="",TODAY()-L16,M16-L16+1)) -> 2 | R16: =IF(Q16=0,0,P16-Q16) -> 1
A17: 15 | B17: FINANCE | C17: REGISTER | D17: New design implement in the view page register of dd,fd and bg page | E17: 2nd stage design | F17: DEV COMPLETE | J17: 45303 | K17: 45307 | L17: 45307 | M17: 45307 | N17: =IF(L17="",IF(#REF!="",#REF!+1,#REF!+1),L17) -> 45307 | O17: =IF(N17="","",N17+P17-1) -> 45311 | P17: =IF(IF(J17="",0,IF(K17="",0,K17-J17))="",0,K17-J17+1) -> 5 | Q17: =IF(L17="",0,IF(M17="",TODAY()-L17,M17-L17+1)) -> 1 | R17: =IF(Q17=0,0,P17-Q17) -> 4
A18: 16 | B18: FINANCE | C18: FD | D18: Cash range in fd section | E18: IMPROVEMENT | F18: HOLD | J18: 45309 | K18: 45310 | L18: 45309 | N18: =IF(L18="",IF(#REF!="",#REF!+1,#REF!+1),L18) -> 45309 | O18: =IF(N18="","",N18+P18-1) -> 45310 | P18: =IF(IF(J18="",0,IF(K18="",0,K18-J18))="",0,K18-J18+1) -> 2 | Q18: =IF(L18="",0,IF(M18="",TODAY()-L18,M18-L18+1)) -> 139 | R18: =IF(Q18=0,0,P18-Q18) -> -137
A19: 17 | B19: IRUS | D19: Segregate Finance module. and remove dynamic approval from the segrigated finance module and testing issue fix in fd and dd | E19: TESTING ISSUE | F19: COMPLETE | J19: 45314 | K19: 45324 | L19: 45315 | M19: 45334 | N19: =IF(L19="",IF(#REF!="",#REF!+1,#REF!+1),L19) -> 45315 | O19: =IF(N19="","",N19+P19-1) -> 45325 | P19: =IF(IF(J19="",0,IF(K19="",0,K19-J19))="",0,K19-J19+1) -> 11 | Q19: =IF(L19="",0,IF(M19="",TODAY()-L19,M19-L19+1)) -> 20 | R19: =IF(Q19=0,0,P19-Q19) -> -9
A20: 18 | B20: HR | C20: SALARY PROCESSING | D20: Payment for HR salary processing (Show unpaid salary of employees in hsalary processing) | E20: IMPROVEMENT | F20: DEV COMPLETE | J20: 45335 | K20: 45343 | L20: 45335 | M20: 45351 | N20: =IF(L20="",IF(#REF!="",#REF!+1,#REF!+1),L20) -> 45335 | O20: =IF(N20="","",N20+P20-1) -> 45343 | P20: =IF(IF(J20="",0,IF(K20="",0,K20-J20))="",0,K20-J20+1) -> 9 | Q20: =IF(L20="",0,IF(M20="",TODAY()-L20,M20-L20+1)) -> 17 | R20: =IF(Q20=0,0,P20-Q20) -> -8
A21: 19 | B21: FINANCE | D21: MIS report of cpbg register,spbg register,aps register | E21: MIS | F21: LIVE | J21: 45337 | K21: 45338 | L21: 45339 | M21: 45339 | N21: =IF(L21="",IF(#REF!="",#REF!+1,#REF!+1),L21) -> 45339 | O21: =IF(N21="","",N21+P21-1) -> 45340 | P21: =IF(IF(J21="",0,IF(K21="",0,K21-J21))="",0,K21-J21+1) -> 2 | Q21: =IF(L21="",0,IF(M21="",TODAY()-L21,M21-L21+1)) -> 1 | R21: =IF(Q21=0,0,P21-Q21) -> 1
A22: 20 | B22: REAL ESTATE | D22: set up laravel in local system,setup live finance module in local and install laravel them. | E22: OTHER | F22: COMPLETE | J22: 45349 | K22: 45349 | L22: 45351 | M22: 45351 | N22: =IF(L22="",IF(#REF!="",#REF!+1,#REF!+1),L22) -> 45351 | O22: =IF(N22="","",N22+P22-1) -> 45351 | P22: =IF(IF(J22="",0,IF(K22="",0,K22-J22))="",0,K22-J22+1) -> 1 | Q22: =IF(L22="",0,IF(M22="",TODAY()-L22,M22-L22+1)) -> 1 | R22: =IF(Q22=0,0,P22-Q22) -> 0
A23: 21 | B23: REAL ESTATE | D23: Sign up page and remove unused menu and files from realestate theme | E23: OTHER | F23: COMPLETE | J23: 45351 | K23: 45353 | L23: 45351 | M23: 45357 | N23: =IF(L23="",IF(#REF!="",#REF!+1,#REF!+1),L23) -> 45351 | O23: =IF(N23="","",N23+P23-1) -> 45353 | P23: =IF(IF(J23="",0,IF(K23="",0,K23-J23))="",0,K23-J23+1) -> 3 | Q23: =IF(L23="",0,IF(M23="",TODAY()-L23,M23-L23+1)) -> 7 | R23: =IF(Q23=0,0,P23-Q23) -> -4
A24: 22 | B24: IRUS | D24: Sign_in page for realestate crm ,and check processing testing for irus,dynamic menu listiong for irus | E24: OTHER | F24: COMPLETE | J24: 45357 | K24: 45363 | L24: 45358 | M24: 45363 | N24: =IF(L24="",IF(#REF!="",#REF!+1,#REF!+1),L24) -> 45358 | O24: =IF(N24="","",N24+P24-1) -> 45364 | P24: =IF(IF(J24="",0,IF(K24="",0,K24-J24))="",0,K24-J24+1) -> 7 | Q24: =IF(L24="",0,IF(M24="",TODAY()-L24,M24-L24+1)) -> 6 | R24: =IF(Q24=0,0,P24-Q24) -> 1
A25: 23 | B25: REAL ESTATE | D25: Create blade file for forgot password, edit profile page,create routes,Test flow of pages for real estate | E25: OTHER | F25: COMPLETE | J25: 45364 | K25: 45366 | L25: 45364 | M25: 45367 | N25: =IF(L25="",IF(#REF!="",#REF!+1,#REF!+1),L25) -> 45364 | O25: =IF(N25="","",N25+P25-1) -> 45366 | P25: =IF(IF(J25="",0,IF(K25="",0,K25-J25))="",0,K25-J25+1) -> 3 | Q25: =IF(L25="",0,IF(M25="",TODAY()-L25,M25-L25+1)) -> 4 | R25: =IF(Q25=0,0,P25-Q25) -> -1
A26: 26 | B26: REAL ESTATE | D26: System Admin menu of Realestate project. | E26: OTHER | F26: COMPLETE | G26: 45367 | H26: 45369 | I26: 45367 | J26: 45367 | K26: 45369 | L26: 45367 | M26: 45373 | N26: =IF(L26="",IF(#REF!="",#REF!+1,#REF!+1),L26) -> 45367 | O26: =IF(N26="","",N26+P26-1) -> 45369 | P26: =IF(IF(J26="",0,IF(K26="",0,K26-J26))="",0,K26-J26+1) -> 3 | Q26: =IF(L26="",0,IF(M26="",TODAY()-L26,M26-L26+1)) -> 7 | R26: =IF(Q26=0,0,P26-Q26) -> -4
A27: 27 | B27: REAL ESTATE | D27: Branch info's submenu to add or update data. | E27: OTHER | F27: COMPLETE | J27: 45371 | K27: 45374 | L27: 45373 | M27: 45378 | N27: =IF(L27="",IF(#REF!="",#REF!+1,#REF!+1),L27) -> 45373 | O27: =IF(N27="","",N27+P27-1) -> 45376 | P27: =IF(IF(J27="",0,IF(K27="",0,K27-J27))="",0,K27-J27+1) -> 4 | Q27: =IF(L27="",0,IF(M27="",TODAY()-L27,M27-L27+1)) -> 6 | R27: =IF(Q27=0,0,P27-Q27) -> -2
A28: 28 | B28: REAL ESTATE | D28: Project master in realestate project. | E28: OTHER | F28: COMPLETE | J28: 45378 | K28: 45380 | L28: 45378 | M28: 45385 | N28: =IF(L28="",IF(#REF!="",#REF!+1,#REF!+1),L28) -> 45378 | O28: =IF(N28="","",N28+P28-1) -> 45380 | P28: =IF(IF(J28="",0,IF(K28="",0,K28-J28))="",0,K28-J28+1) -> 3 | Q28: =IF(L28="",0,IF(M28="",TODAY()-L28,M28-L28+1)) -> 8 | R28: =IF(Q28=0,0,P28-Q28) -> -5
A29: 29 | B29: REAL ESTATE | D29: Business Management menus all master submenus in real estate project | E29: OTHER | F29: COMPLETE | J29: 45379 | K29: 45384 | L29: 45381 | M29: 45385 | N29: =IF(L29="",IF(#REF!="",#REF!+1,#REF!+1),L29) -> 45381 | O29: =IF(N29="","",N29+P29-1) -> 45386 | P29: =IF(IF(J29="",0,IF(K29="",0,K29-J29))="",0,K29-J29+1) -> 6 | Q29: =IF(L29="",0,IF(M29="",TODAY()-L29,M29-L29+1)) -> 5 | R29: =IF(Q29=0,0,P29-Q29) -> 1
A30: 30 | B30: REAL ESTATE | D30: Create Add new Project page. | E30: OTHER | F30: COMPLETE | J30: 45385 | K30: 45386 | L30: 45385 | M30: 45386 | N30: =IF(L30="",IF(#REF!="",#REF!+1,#REF!+1),L30) -> 45385 | O30: =IF(N30="","",N30+P30-1) -> 45386 | P30: =IF(IF(J30="",0,IF(K30="",0,K30-J30))="",0,K30-J30+1) -> 2 | Q30: =IF(L30="",0,IF(M30="",TODAY()-L30,M30-L30+1)) -> 2 | R30: =IF(Q30=0,0,P30-Q30) -> 0
A31: 31 | B31: REAL ESTATE | D31: Create Location menu's Zone,Area,Teritorry,Point pages. | E31: OTHER | F31: COMPLETE | J31: 45387 | K31: 45388 | L31: 45387 | M31: 45390 | N31: =IF(L31="",IF(#REF!="",#REF!+1,#REF!+1),L31) -> 45387 | O31: =IF(N31="","",N31+P31-1) -> 45388 | P31: =IF(IF(J31="",0,IF(K31="",0,K31-J31))="",0,K31-J31+1) -> 2 | Q31: =IF(L31="",0,IF(M31="",TODAY()-L31,M31-L31+1)) -> 4 | R31: =IF(Q31=0,0,P31-Q31) -> -2
A32: 32 | B32: REAL ESTATE | D32: Add aleart and clean all form with handling arror in realestate. | E32: OTHER | F32: COMPLETE | J32: 45390 | K32: 45392 | L32: 45390 | M32: 45394 | N32: =IF(L32="",IF(#REF!="",#REF!+1,#REF!+1),L32) -> 45390 | O32: =IF(N32="","",N32+P32-1) -> 45392 | P32: =IF(IF(J32="",0,IF(K32="",0,K32-J32))="",0,K32-J32+1) -> 3 | Q32: =IF(L32="",0,IF(M32="",TODAY()-L32,M32-L32+1)) -> 5 | R32: =IF(Q32=0,0,P32-Q32) -> -2
A33: 33 | B33: REAL ESTATE | D33: update and delete branch info in realestate project | E33: OTHER | F33: COMPLETE | J33: 45394 | K33: 45398 | L33: 45399 | M33: 45399 | N33: =IF(L33="",IF(#REF!="",#REF!+1,#REF!+1),L33) -> 45399 | O33: =IF(N33="","",N33+P33-1) -> 45403 | P33: =IF(IF(J33="",0,IF(K33="",0,K33-J33))="",0,K33-J33+1) -> 5 | Q33: =IF(L33="",0,IF(M33="",TODAY()-L33,M33-L33+1)) -> 1 | R33: =IF(Q33=0,0,P33-Q33) -> 4
A34: 34 | B34: REAL ESTATE | D34: create update and view board of directer sub menu | E34: OTHER | F34: COMPLETE | J34: 45399 | K34: 45400 | L34: 45399 | M34: 45402 | N34: =IF(L34="",IF(#REF!="",#REF!+1,#REF!+1),L34) -> 45399 | O34: =IF(N34="","",N34+P34-1) -> 45400 | P34: =IF(IF(J34="",0,IF(K34="",0,K34-J34))="",0,K34-J34+1) -> 2 | Q34: =IF(L34="",0,IF(M34="",TODAY()-L34,M34-L34+1)) -> 4 | R34: =IF(Q34=0,0,P34-Q34) -> -2
A35: 35 | B35: REAL ESTATE | D35: Create Team Management's update,delete,view,listing. | E35: OTHER | F35: COMPLETE | J35: 45401 | K35: 45402 | L35: 45402 | M35: 45404 | N35: =IF(L35="",IF(#REF!="",#REF!+1,#REF!+1),L35) -> 45402 | O35: =IF(N35="","",N35+P35-1) -> 45403 | P35: =IF(IF(J35="",0,IF(K35="",0,K35-J35))="",0,K35-J35+1) -> 2 | Q35: =IF(L35="",0,IF(M35="",TODAY()-L35,M35-L35+1)) -> 3 | R35: =IF(Q35=0,0,P35-Q35) -> -1
A36: 36 | B36: REAL ESTATE | D36: Add edit fiunction and creat view page and add new project | E36: OTHER | F36: COMPLETE | J36: 45406 | K36: 45406 | L36: 45406 | M36: 45412 | N36: =IF(L36="",IF(#REF!="",#REF!+1,#REF!+1),L36) -> 45406 | O36: =IF(N36="","",N36+P36-1) -> 45406 | P36: =IF(IF(J36="",0,IF(K36="",0,K36-J36))="",0,K36-J36+1) -> 1 | Q36: =IF(L36="",0,IF(M36="",TODAY()-L36,M36-L36+1)) -> 7 | R36: =IF(Q36=0,0,P36-Q36) -> -6
A37: 37 | B37: FINANCE | C37: FD PROCESSING | D37: Remove star mark from FD and add parallel approval in FD. | F37: DEV COMPLETE | J37: 45411 | K37: 45414 | L37: 45411 | M37: 45415 | N37: =IF(L37="",IF(#REF!="",#REF!+1,#REF!+1),L37) -> 45411 | O37: =IF(N37="","",N37+P37-1) -> 45414 | P37: =IF(IF(J37="",0,IF(K37="",0,K37-J37))="",0,K37-J37+1) -> 4 | Q37: =IF(L37="",0,IF(M37="",TODAY()-L37,M37-L37+1)) -> 5 | R37: =IF(Q37=0,0,P37-Q37) -> -1
A38: 38 | B38: FINANCE | C38: DD PROCESSING | D38: Add IP address and Remove * mark from DD section. | F38: DEV COMPLETE | J38: 45415 | K38: 45419 | L38: 45418 | M38: 45426 | N38: =IF(L38="",IF(#REF!="",#REF!+1,#REF!+1),L38) -> 45418 | O38: =IF(N38="","",N38+P38-1) -> 45422 | P38: =IF(IF(J38="",0,IF(K38="",0,K38-J38))="",0,K38-J38+1) -> 5 | Q38: =IF(L38="",0,IF(M38="",TODAY()-L38,M38-L38+1)) -> 9 | R38: =IF(Q38=0,0,P38-Q38) -> -4
A39: 39 | B39: FINANCE | D39: Excel Download of payment assign.(initial,conformation,final) | F39: LIVE | J39: 45416 | K39: 45416 | L39: 45416 | M39: 45418 | N39: =IF(L39="",IF(#REF!="",#REF!+1,#REF!+1),L39) -> 45416 | O39: =IF(N39="","",N39+P39-1) -> 45416 | P39: =IF(IF(J39="",0,IF(K39="",0,K39-J39))="",0,K39-J39+1) -> 1 | Q39: =IF(L39="",0,IF(M39="",TODAY()-L39,M39-L39+1)) -> 3 | R39: =IF(Q39=0,0,P39-Q39) -> -2
A40: 40 | B40: FINANCE | D40: Analyse the GST report work and setup in local system | E40: OTHER | F40: COMPLETE | J40: 45421 | K40: 45426 | L40: 45426 | M40: 45428 | N40: =IF(L40="",IF(#REF!="",#REF!+1,#REF!+1),L40) -> 45426 | O40: =IF(N40="","",N40+P40-1) -> 45431 | P40: =IF(IF(J40="",0,IF(K40="",0,K40-J40))="",0,K40-J40+1) -> 6 | Q40: =IF(L40="",0,IF(M40="",TODAY()-L40,M40-L40+1)) -> 3 | R40: =IF(Q40=0,0,P40-Q40) -> 3
A41: 41 | B41: HR | C41: Salary P[rocessing | D41: Add New listing Style In HR salary Processing. | E41: IMPROVEMENT | F41: LIVE PENDING | J41: 45427 | K41: 45427 | L41: 45428 | M41: 45428 | N41: =IF(L41="",IF(#REF!="",#REF!+1,#REF!+1),L41) -> 45428 | O41: =IF(N41="","",N41+P41-1) -> 45428 | P41: =IF(IF(J41="",0,IF(K41="",0,K41-J41))="",0,K41-J41+1) -> 1 | Q41: =IF(L41="",0,IF(M41="",TODAY()-L41,M41-L41+1)) -> 1 | R41: =IF(Q41=0,0,P41-Q41) -> 0
A42: 42 | B42: COLLECTION | D42: Output gst report of collection modules El listing), and analyse of the work. | E42: IMPROVEMENT | F42: INPROGRESS | J42: 45428 | K42: 45434 | L42: 45428

Sheet JYOSTNAMAYEE NAYAK
O1: =SUM(O3:O1018) -> 328 | P1: =SUM(P3:P1018) -> 529 | Q1: =SUM(Q3:Q1018) -> -201
A2: SL.NO. | B2: MODULE | C2: SUB MODULE | D2: ACTIVITIES | E2: WORK TYPE | F2: STATUS | G2: RESTRICTION | H2: NOTIFICATION | I2: TGT ST DATE | J2: TGT END DATE | K2: ACT ST DATE | L2: ACT END DATE | M2: PROB ST DT | N2: PROB END DT | O2: TGT DUR | P2: ACT DUR | Q2: T SAVING | R2: DELAY REASON STATUS
A3: 1 | B3: APPROVAL STAGE MASTER | D3: Add Payment approval employee name for all module. | F3: LIVE | I3: 44848 | J3: 44852 | K3: 44851 | L3: 44855 | O3: =IF(IF(I3="",0,IF(J3="",0,J3-I3))="",0,J3-I3+1) -> 5 | P3: =IF(K3="",0,IF(L3="",TODAY()-K3,L3-K3+1)) -> 5 | Q3: =IF(P3=0,0,O3-P3) -> 0
A4: 2 | B4: APPROVAL STAGE MASTER | D4: Edit and View page for approval stage name | F4: LIVE | I4: 44853 | J4: 44855 | K4: 44846 | L4: 44849 | O4: =IF(IF(I4="",0,IF(J4="",0,J4-I4))="",0,J4-I4+1) -> 3 | P4: =IF(K4="",0,IF(L4="",TODAY()-K4,L4-K4+1)) -> 4 | Q4: =IF(P4=0,0,O4-P4) -> -1
A5: 3 | B5: APPROVAL STAGE MASTER | D5: Add Approval Stage for all master menu Section. | F5: LIVE | I5: 44856 | J5: 44857 | K5: 44856 | L5: 44857 | O5: =IF(IF(I5="",0,IF(J5="",0,J5-I5))="",0,J5-I5+1) -> 2 | P5: =IF(K5="",0,IF(L5="",TODAY()-K5,L5-K5+1)) -> 2 | Q5: =IF(P5=0,0,O5-P5) -> 0 | R5: SHE IS IN LEAVE DUE TO HEALTH ISSUES
A6: 4 | B6: APPROVAL STAGE MASTER | D6: View page for approval employee page for all module | F6: LIVE | I6: 44856 | J6: 44857 | K6: 44859 | L6: 44862 | O6: =IF(IF(I6="",0,IF(J6="",0,J6-I6))="",0,J6-I6+1) -> 2 | P6: =IF(K6="",0,IF(L6="",TODAY()-K6,L6-K6+1)) -> 4 | Q6: =IF(P6=0,0,O6-P6) -> -2
A7: 5 | B7: APPROVAL STAGE MASTER | D7: Edit page for approval employee name section | F7: LIVE | I7: 44865 | J7: 44868 | K7: 44865 | L7: 44869 | O7: =IF(IF(I7="",0,IF(J7="",0,J7-I7))="",0,J7-I7+1) -> 4 | P7: =IF(K7="",0,IF(L7="",TODAY()-K7,L7-K7+1)) -> 5 | Q7: =IF(P7=0,0,O7-P7) -> -1
A8: 6 | B8: HI-TOMI | D8: Multiple selector in all hitomi report section. | F8: LIVE | I8: 44870 | J8: 44872 | K8: 44870 | L8: 44872 | O8: =IF(IF(I8="",0,IF(J8="",0,J8-I8))="",0,J8-I8+1) -> 3 | P8: =IF(K8="",0,IF(L8="",TODAY()-K8,L8-K8+1)) -> 3 | Q8: =IF(P8=0,0,O8-P8) -> 0
A9: 7 | B9: APPROVAL STAGE MASTER | D9: Modifications on master approval stage | F9: LIVE | I9: 44873 | J9: 44875 | K9: 44873 | L9: 44876 | O9: =IF(IF(I9="",0,IF(J9="",0,J9-I9))="",0,J9-I9+1) -> 3 | P9: =IF(K9="",0,IF(L9="",TODAY()-K9,L9-K9+1)) -> 4 | Q9: =IF(P9=0,0,O9-P9) -> -1
A10: 8 | B10: APPROVAL STAGE MASTER | D10: Bug Fixing in module approval stage | F10: LIVE | I10: 44879 | J10: 44883 | K10: 44909 | L10: 44917 | O10: =IF(IF(I10="",0,IF(J10="",0,J10-I10))="",0,J10-I10+1) -> 5 | P10: =IF(K10="",0,IF(L10="",TODAY()-K10,L10-K10+1)) -> 9 | Q10: =IF(P10=0,0,O10-P10) -> -4
A11: 9 | B11: HI-TOMI | D11: Subtask creation option will be available fir raiser, creater and responsible person | F11: LIVE | I11: 44882 | J11: 44883 | K11: 44882 | L11: 44883 | O11: =IF(IF(I11="",0,IF(J11="",0,J11-I11))="",0,J11-I11+1) -> 2 | P11: =IF(K11="",0,IF(L11="",TODAY()-K11,L11-K11+1)) -> 2 | Q11: =IF(P11=0,0,O11-P11) -> 0
A12: 10 | B12: HI-TOMI | D12: For complete status update there should be message box & attachment option | F12: LIVE | I12: 44884 | J12: 44884 | K12: 44884 | L12: 44884 | O12: =IF(IF(I12="",0,IF(J12="",0,J12-I12))="",0,J12-I12+1) -> 1 | P12: =IF(K12="",0,IF(L12="",TODAY()-K12,L12-K12+1)) -> 1 | Q12: =IF(P12=0,0,O12-P12) -> 0
A13: 11 | B13: HI-TOMI | D13: Hitomi Cannot be closed Until its sub task are not closed. | F13: LIVE | I13: 44884 | J13: 44884 | K13: 44884 | L13: 44884 | O13: =IF(IF(I13="",0,IF(J13="",0,J13-I13))="",0,J13-I13+1) -> 1 | P13: =IF(K13="",0,IF(L13="",TODAY()-K13,L13-K13+1)) -> 1 | Q13: =IF(P13=0,0,O13-P13) -> 0
A14: 12 | B14: HI-TOMI | D14: In hitomi master search department should be selected responsible person wise | F14: LIVE | I14: 44886 | J14: 44888 | K14: 44886 | L14: 44888 | O14: =IF(IF(I14="",0,IF(J14="",0,J14-I14))="",0,J14-I14+1) -> 3 | P14: =IF(K14="",0,IF(L14="",TODAY()-K14,L14-K14+1)) -> 3 | Q14: =IF(P14=0,0,O14-P14) -> 0
A15: 13 | B15: HI-TOMI | D15: And new status (hold) in hi tomi section . and change menu section as per user requirement | F15: LIVE | I15: 44889 | J15: 44889 | K15: 44889 | L15: 44889 | O15: =IF(IF(I15="",0,IF(J15="",0,J15-I15))="",0,J15-I15+1) -> 1 | P15: =IF(K15="",0,IF(L15="",TODAY()-K15,L15-K15+1)) -> 1 | Q15: =IF(P15=0,0,O15-P15) -> 0
A16: 14 | B16: HI-TOMI | D16: Add remark while reopen a task by raiser person. | F16: LIVE | I16: 44890 | J16: 44890 | K16: 44890 | L16: 44890 | O16: =IF(IF(I16="",0,IF(J16="",0,J16-I16))="",0,J16-I16+1) -> 1 | P16: =IF(K16="",0,IF(L16="",TODAY()-K16,L16-K16+1)) -> 1 | Q16: =IF(P16=0,0,O16-P16) -> 0
A17: 15 | B17: HI-TOMI | D17: Sub Task should be similar to the main hitomi task. | F17: LIVE | I17: 44891 | J17: 44891 | K17: 44891 | L17: 44891 | O17: =IF(IF(I17="",0,IF(J17="",0,J17-I17))="",0,J17-I17+1) -> 1 | P17: =IF(K17="",0,IF(L17="",TODAY()-K17,L17-K17+1)) -> 1 | Q17: =IF(P17=0,0,O17-P17) -> 0
... A19: 17 | B19: HI-TOMI | D19: A new column for assigned person department head name and department name with extra modification in hi-tomi listings | F19: LIVE | I19: 44895 | J19: 44898 | K19: 44896 | L19: 44898 | O19: =IF(IF(I19="",0,IF(J19="",0,J19-I19))="",0,J19-I19+1) -> 4 | P19: =IF(K19="",0,IF(L19="",TODAY()-K19,L19-K19+1)) -> 3 | Q19: =IF(P19=0,0,O19-P19) -> 1
A20: 18 | B20: HI-TOMI | D20: DELETE OPTION IN HI-TOMI | F20: LIVE | I20: 44900 | J20: 44902 | K20: =I20 -> 44900 | L20: 44903 | O20: =IF(IF(I20="",0,IF(J20="",0,J20-I20))="",0,J20-I20+1) -> 3 | P20: =IF(K20="",0,IF(L20="",TODAY()-K20,L20-K20+1)) -> 4 | Q20: =IF(P20=0,0,O20-P20) -> -1
A21: 19 | B21: HI-TOMI | D21: Create on extended date in hitomi section and number of changes in due date | F21: LIVE | I21: 44904 | J21: 44906 | K21: 44904 | L21: 44911 | O21: =IF(IF(I21="",0,IF(J21="",0,J21-I21))="",0,J21-I21+1) -> 3 | P21: =IF(K21="",0,IF(L21="",TODAY()-K21,L21-K21+1)) -> 8 | Q21: =IF(P21=0,0,O21-P21) -> -5
A22: 20 | B22: HI-TOMI | D22: NOTIFICATIONS | F22: LIVE | I22: =J21+1 -> 44907 | J22: =I22+5 -> 44912 | K22: 44917 | L22: 44921 | O22: =IF(IF(I22="",0,IF(J22="",0,J22-I22))="",0,J22-I22+1) -> 6 | P22: =IF(K22="",0,IF(L22="",TODAY()-K22,L22-K22+1)) -> 5 | Q22: =IF(P22=0,0,O22-P22) -> 1
A23: 21 | B23: HI-TOMI | D23: MESSAGE BOX WHILE REJECTING A HI-TOMI | E23: MAINTENANCE | F23: LIVE | I23: =J22+1 -> 44913 | J23: =I23+1 -> 44914 | K23: 44922 | L23: 44924 | O23: =IF(IF(I23="",0,IF(J23="",0,J23-I23))="",0,J23-I23+1) -> 2 | P23: =IF(K23="",0,IF(L23="",TODAY()-K23,L23-K23+1)) -> 3 | Q23: =IF(P23=0,0,O23-P23) -> -1
A24: 22 | B24: HI-TOMI | D24: PENDING APPROVAL OF HI-TOMI | F24: COMPLETED | R24: ASSIGN TO GAYATRI MAM
A25: 23 | B25: HI-TOMI | D25: NOTIFICATIONS MODIFICATION | F25: LIVE | I25: =J23+1 -> 44915 | J25: =I25+4 -> 44919 | K25: 44929 | L25: 44933 | O25: =IF(IF(I25="",0,IF(J25="",0,J25-I25))="",0,J25-I25+1) -> 5 | P25: =IF(K25="",0,IF(L25="",TODAY()-K25,L25-K25+1)) -> 5 | Q25: =IF(P25=0,0,O25-P25) -> 0
A26: 24 | B26: HI-TOMI | D26: Add new tab under hitomi for ( pending for final complete) in pending approval section . | E26: MAINTENANCE | F26: LIVE | I26: =J25+1 -> 44920 | J26: =I26+1 -> 44921 | K26: 44935 | L26: 44936 | O26: =IF(IF(I26="",0,IF(J26="",0,J26-I26))="",0,J26-I26+1) -> 2 | P26: =IF(K26="",0,IF(L26="",TODAY()-K26,L26-K26+1)) -> 2 | Q26: =IF(P26=0,0,O26-P26) -> 0
A27: 25 | B27: HI-TOMI | D27: Each employee can give comments for multiple times on a particular task | E27: MAINTENANCE | F27: LIVE | I27: =J26+1 -> 44922 | J27: =I27 -> 44922 | K27: 44937 | L27: 44937 | O27: =IF(IF(I27="",0,IF(J27="",0,J27-I27))="",0,J27-I27+1) -> 1 | P27: =IF(K27="",0,IF(L27="",TODAY()-K27,L27-K27+1)) -> 1 | Q27: =IF(P27=0,0,O27-P27) -> 0
A28: 26 | B28: HI-TOMI | D28: Search Box For Assigned By Department And The Department Search Box Name Should Be Assigned By Department Search Box. | E28: MAINTENANCE | F28: LIVE | I28: =J27+1 -> 44923 | J28: =I28+1 -> 44924 | K28: 44938 | L28: 44942 | O28: =IF(IF(I28="",0,IF(J28="",0,J28-I28))="",0,J28-I28+1) -> 2 | P28: =IF(K28="",0,IF(L28="",TODAY()-K28,L28-K28+1)) -> 5 | Q28: =IF(P28=0,0,O28-P28) -> -3
A29: 27 | B29: HI-TOMI | D29: Show reject message and reopen message in view pages | E29: MAINTENANCE | F29: LIVE | I29: =J28+1 -> 44925 | J29: =I29+1 -> 44926 | K29: 44943 | L29: 44944 | O29: =IF(IF(I29="",0,IF(J29="",0,J29-I29))="",0,J29-I29+1) -> 2 | P29: =IF(K29="",0,IF(L29="",TODAY()-K29,L29-K29+1)) -> 2 | Q29: =IF(P29=0,0,O29-P29) -> 0
A30: 28 | B30: FINANCE | D30: Setting of fooding rates(All fooding list) | E30: FORM | F30: LIVE | I30: =J29+1 -> 44927 | J30: =I30+6 -> 44933 | K30: 44945 | L30: 44949 | O30: =IF(IF(I30="",0,IF(J30="",0,J30-I30))="",0,J30-I30+1) -> 7 | P30: =IF(K30="",0,IF(L30="",TODAY()-K30,L30-K30+1)) -> 5 | Q30: =IF(P30=0,0,O30-P30) -> 2
A31: 29 | B31: FINANCE | D31: FOODING-VIEW PAGE | E31: FORM | F31: LIVE | I31: =J30+1 -> 44934 | J31: =I31+2 -> 44936 | K31: =L30+2 -> 44951 | L31: =K31+2 -> 44953 | O31: =IF(IF(I31="",0,IF(J31="",0,J31-I31))="",0,J31-I31+1) -> 3 | P31: =IF(K31="",0,IF(L31="",TODAY()-K31,L31-K31+1)) -> 3 | Q31: =IF(P31=0,0,O31-P31) -> 0
A32: 30 | B32: FINANCE | D32: Setting of fooding rates(My pending list) | E32: FORM | F32: STOPED | I32: =J30+1 -> 44934 | J32: =I32+4 -> 44938 | K32: =L31+1 -> 44954 | L32: =K32+4 -> 44958 | O32: =IF(IF(I32="",0,IF(J32="",0,J32-I32))="",0,J32-I32+1) -> 5 | P32: =IF(K32="",0,IF(L32="",TODAY()-K32,L32-K32+1)) -> 5 | Q32: =IF(P32=0,0,O32-P32) -> 0
A33: 31 | B33: FINANCE | D33: Setting of fooding rates(Approved list) | E33: FORM | F33: STOPED | I33: =J32+1 -> 44939 | J33: =I33+2 -> 44941 | K33: =L32 -> 44958 | L33: =K33+2 -> 44960 | O33: =IF(IF(I33="",0,IF(J33="",0,J33-I33))="",0,J33-I33+1) -> 3 | P33: =IF(K33="",0,IF(L33="",TODAY()-K33,L33-K33+1)) -> 3 | Q33: =IF(P33=0,0,O33-P33) -> 0
A34: 32 | B34: FINANCE | D34: Setting of fooding rates(Recheck list) | E34: FORM | F34: STOPED | I34: =J33+1 -> 44942 | J34: =I34+3 -> 44945 | K34: =L33+1 -> 44961 | L34: =K34+2 -> 44963 | O34: =IF(IF(I34="",0,IF(J34="",0,J34-I34))="",0,J34-I34+1) -> 4 | P34: =IF(K34="",0,IF(L34="",TODAY()-K34,L34-K34+1)) -> 3 | Q34: =IF(P34=0,0,O34-P34) -> 1
A35: 33 | B35: FINANCE | D35: Setting of fooding rates(Cancelled list) | E35: FORM | F35: STOPED | I35: =J34+1 -> 44946 | J35: =I35+4 -> 44950 | K35: =L34+0 -> 44963 | L35: 44968 | O35: =IF(IF(I35="",0,IF(J35="",0,J35-I35))="",0,J35-I35+1) -> 5 | P35: =IF(K35="",0,IF(L35="",TODAY()-K35,L35-K35+1)) -> 6 | Q35: =IF(P35=0,0,O35-P35) -> -1
A36: 34 | B36: FINANCE | D36: recheck and cancel functionality in fooding section | E36: FORM | F36: STOPED | I36: =J35+1 -> 44951 | J36: =I36+4 -> 44955 | K36: 44970 | L36: 44974 | O36: =IF(IF(I36="",0,IF(J36="",0,J36-I36))="",0,J36-I36+1) -> 5 | P36: =IF(K36="",0,IF(L36="",TODAY()-K36,L36-K36+1)) -> 5 | Q36: =IF(P36=0,0,O36-P36) -> 0
A37: 35 | B37: FINANCE | D37: Modification of HI-TOMII reports | E37: FORM | F37: LIVE | I37: =J36+1 -> 44956 | J37: =I37+1 -> 44957 | K37: =L36+3 -> 44977 | L37: =K37+1 -> 44978 | O37: =IF(IF(I37="",0,IF(J37="",0,J37-I37))="",0,J37-I37+1) -> 2 | P37: =IF(K37="",0,IF(L37="",TODAY()-K37,L37-K37+1)) -> 2 | Q37: =IF(P37=0,0,O37-P37) -> 0
A38: 36 | B38: FINANCE | D38: Edit function of fodding page | E38: FORM | F38: STOPED | I38: =J37+1 -> 44958 | J38: =I38+2 -> 44960 | K38: 44979 | L38: 44984 | O38: =IF(IF(I38="",0,IF(J38="",0,J38-I38))="",0,J38-I38+1) -> 3 | P38: =IF(K38="",0,IF(L38="",TODAY()-K38,L38-K38+1)) -> 6 | Q38: =IF(P38=0,0,O38-P38) -> -3
A39: 37 | B39: FINANCE | D39: PENDING APPROVAL IN FOODING SECTION USING DYNAMICALLY APPROVAL MATRIX | E39: FORM | F39: STOPED | I39: =J38+1 -> 44961 | J39: =I39+3 -> 44964 | K39: 44985 | L39: 44989 | O39: =IF(IF(I39="",0,IF(J39="",0,J39-I39))="",0,J39-I39+1) -> 4 | P39: =IF(K39="",0,IF(L39="",TODAY()-K39,L39-K39+1)) -> 5 | Q39: =IF(P39=0,0,O39-P39) -> -1
A40: 38 | B40: MASTER | D40: ISSUE FIXING IN APPROVAL MATRIX MODULE | F40: LIVE | I40: =J39+1 -> 44965 | J40: =I40+1 -> 44966 | K40: 44989 | L40: 44989 | O40: =IF(IF(I40="",0,IF(J40="",0,J40-I40))="",0,J40-I40+1) -> 2 | P40: =IF(K40="",0,IF(L40="",TODAY()-K40,L40-K40+1)) -> 1 | Q40: =IF(P40=0,0,O40-P40) -> 1
A41: 39 | B41: MASTER | D41: DYNAMIC APPROVAL MATRIX | F41: LIVE | I41: =J40+1 -> 44967 | J41: =I41+4+3 -> 44974 | K41: 44991 | L41: 45002 | O41: =IF(IF(I41="",0,IF(J41="",0,J41-I41))="",0,J41-I41+1) -> 8 | P41: =IF(K41="",0,IF(L41="",TODAY()-K41,L41-K41+1)) -> 12 | Q41: =IF(P41=0,0,O41-P41) -> -4
A42: 40 | B42: FINANCE | D42: Payment Request For Fooding | E42: FORM | F42: STOPED | I42: =J41+1 -> 44975 | J42: =I42+5 -> 44980
A43: 41 | B43: FINANCE | D43: Fooding Payment Request Approval | E43: FORM | F43: STOPED | I43: =J42+1 -> 44981 | J43: =I43+5 -> 44986
A44: 42 | B44: FINANCE | D44: Payment Assignment | E44: FORM | F44: STOPED | I44: =J43+1 -> 44987 | J44: =I44+5 -> 44992
A45: 43 | B45: FINANCE | D45: Pending Approval Of Fooding With Notification | E45: FORM | F45: STOPED | I45: =J44+1 -> 44993 | J45: =I45+5 -> 44998
A46: 44 | B46: FINANCE | D46: Fooding Chart Current Report | E46: MIS | F46: STOPED | I46: =J45+1 -> 44999 | J46: =I46+3 -> 45002
A47: 45 | B47: FINANCE | D47: Employee Fooding Report Page | E47: MIS | F47: STOPED | I47: =J46+1 -> 45003 | J47: =I47+3 -> 45006
A48: 46 | B48: HI-TOMI | D48: Modification In Hitomi Pending Approval | F48: LIVE | I48: =J47+1 -> 45007 | J48: =I48+5 -> 45012 | K48: 45005 | L48: 45012 | O48: =IF(IF(I48="",0,IF(J48="",0,J48-I48))="",0,J48-I48+1) -> 6 | P48: =IF(K48="",0,IF(L48="",TODAY()-K48,L48-K48+1)) -> 8 | Q48: =IF(P48=0,0,O48-P48) -> -2
A49: 47 | B49: APPROVAL STAGE MASTER | D49: Parallel Approval Functionality | E49: FORM | F49: LIVE | I49: 45013 | J49: 45016 | K49: 45013 | L49: =J49 -> 45016 | O49: =IF(IF(I49="",0,IF(J49="",0,J49-I49))="",0,J49-I49+1) -> 4 | P49: =IF(K49="",0,IF(L49="",TODAY()-K49,L49-K49+1)) -> 4 | Q49: =IF(P49=0,0,O49-P49) -> 0
A50: 48 | B50: APPROVAL STAGE MASTER | D50: Cash Range Edit Section | E50: FORM | F50: DEV COMPLETE | I50: =J49+1 -> 45017 | J50: =I50+3+2+4 -> 45026 | K50: 45018 | L50: 45027 | O50: =IF(IF(I50="",0,IF(J50="",0,J50-I50))="",0,J50-I50+1) -> 10 | P50: =IF(K50="",0,IF(L50="",TODAY()-K50,L50-K50+1)) -> 10 | Q50: =IF(P50=0,0,O50-P50) -> 0
A51: 49 | B51: HI-TOMI | D51: 1.In Action Message List, It Should Show All The Status Updates & Comment Regarding That Hi-Tomi 2.In Hitomi Next Functionality Show Alert After Updating A Task And Then Redirect To Next Task. | F51: LIVE | I51: =J50+1 -> 45027 | J51: =I51+2+4 -> 45033 | K51: 45028 | L51: 45034 | O51: =IF(IF(I51="",0,IF(J51="",0,J51-I51))="",0,J51-I51+1) -> 7 | P51: =IF(K51="",0,IF(L51="",TODAY()-K51,L51-K51+1)) -> 7 | Q51: =IF(P51=0,0,O51-P51) -> 0
A52: 50 | B52: HR | D52: Edit Functionality In Fooding Expense | F52: LIVE | I52: =J51+1 -> 45034 | J52: =I52+1 -> 45035 | K52: 45036 | L52: 45037 | O52: =IF(IF(I52="",0,IF(J52="",0,J52-I52))="",0,J52-I52+1) -> 2 | P52: =IF(K52="",0,IF(L52="",TODAY()-K52,L52-K52+1)) -> 2 | Q52: =IF(P52=0,0,O52-P52) -> 0
A53: 51 | B53: HI-TOMI | D53: Shorting Option In Hi-Tomi Report | F53: LIVE | I53: =J52+1 -> 45036 | J53: =I53+3 -> 45039 | K53: 45042 | L53: =K53+3 -> 45045 | O53: =IF(IF(I53="",0,IF(J53="",0,J53-I53))="",0,J53-I53+1) -> 4 | P53: =IF(K53="",0,IF(L53="",TODAY()-K53,L53-K53+1)) -> 4 | Q53: =IF(P53=0,0,O53-P53) -> 0
A54: 52 | B54: HI-TOMI | D54: Add Next , Previous And Go To List Button Functionality In Hitomi View Page After Identifying The Request Is From Normal List Page Or The Pending Approval List Page | E54: MASTER CODE | F54: LIVE | I54: =J53+1 -> 45040 | J54: =I54+1+2 -> 45043 | K54: 45047 | L54: 45052 | O54: =IF(IF(I54="",0,IF(J54="",0,J54-I54))="",0,J54-I54+1) -> 4 | P54: =IF(K54="",0,IF(L54="",TODAY()-K54,L54-K54+1)) -> 6 | Q54: =IF(P54=0,0,O54-P54) -> -2
A55: 53 | B55: HI-TOMI | D55: If Someone Hold A Hi-Tomi Then He Will Fill A Compulsory Remark Box. | E55: MAINTENANCE | F55: LIVE
A56: 54 | B56: MASTER | D56: Modification In Approval Master Matrix | E56: OPERATIONAL ISSUE | F56: LIVE | I56: =J54+1 -> 45044 | J56: =I56+1 -> 45045
A57: 55 | B57: FINANCE | D57: Testing Issue Fix Of Fooding Expense | F57: LIVE | I57: 45071 | J57: 45080 | K57: 45072 | L57: 45078 | O57: =IF(IF(I57="",0,IF(J57="",0,J57-I57))="",0,J57-I57+1) -> 10 | P57: =IF(K57="",0,IF(L57="",TODAY()-K57,L57-K57+1)) -> 7 | Q57: =IF(P57=0,0,O57-P57) -> 3
A58: 56 | B58: MASTER | D58: Modification In Approval Master | E58: IMPROVEMENT | F58: LIVE | I58: =J57+1 -> 45081 | J58: =I58+5 -> 45086 | K58: 45082 | L58: 45094 | O58: =IF(IF(I58="",0,IF(J58="",0,J58-I58))="",0,J58-I58+1) -> 6 | P58: =IF(K58="",0,IF(L58="",TODAY()-K58,L58-K58+1)) -> 13 | Q58: =IF(P58=0,0,O58-P58) -> -7
A59: 57 | B59: FINANCE | D59: Add Validation In The Pay Botton Of Bank Api Implementation | E59: IMPROVEMENT | F59: LIVE | I59: =J58+1 -> 45087 | J59: =I59+6 -> 45093 | K59: 45096 | L59: 45100 | O59: =IF(IF(I59="",0,IF(J59="",0,J59-I59))="",0,J59-I59+1) -> 7 | P59: =IF(K59="",0,IF(L59="",TODAY()-K59,L59-K59+1)) -> 5 | Q59: =IF(P59=0,0,O59-P59) -> 2
A60: 58 | B60: MASTER | D60: Cash Range Entries Approval Matrix Issue Fix | E60: TESTING ISSUE | F60: DEV COMPLETE | I60: 45103 | J60: 45105 | K60: 45103 | L60: 45108 | O60: =IF(IF(I60="",0,IF(J60="",0,J60-I60))="",0,J60-I60+1) -> 3 | P60: =IF(K60="",0,IF(L60="",TODAY()-K60,L60-K60+1)) -> 6 | Q60: =IF(P60=0,0,O60-P60) -> -3
A61: 59 | B61: MASTER | D61: Manage Benificiary Form Page And Edit Page | E61: IMPROVEMENT | F61: LIVE | I61: 45106 | J61: 45109 | K61: 45110 | L61: 45114 | O61: =IF(IF(I61="",0,IF(J61="",0,J61-I61))="",0,J61-I61+1) -> 4 | P61: =IF(K61="",0,IF(L61="",TODAY()-K61,L61-K61+1)) -> 5 | Q61: =IF(P61=0,0,O61-P61) -> -1
A62: 60 | B62: MASTER | D62: Testing Issue Fix Of The Approval Master Module | E62: TESTING ISSUE | F62: LIVE | I62: 45110 | J62: 45112 | K62: 45117 | L62: 45119 | O62: =IF(IF(I62="",0,IF(J62="",0,J62-I62))="",0,J62-I62+1) -> 3 | P62: =IF(K62="",0,IF(L62="",TODAY()-K62,L62-K62+1)) -> 3 | Q62: =IF(P62=0,0,O62-P62) -> 0
A63: 61 | B63: HI-TOMI | D63: Multiple Attachment | E63: IMPROVEMENT | F63: LIVE | I63: 45120 | J63: 45121 | K63: 45125 | L63: 45132 | O63: =IF(IF(I63="",0,IF(J63="",0,J63-I63))="",0,J63-I63+1) -> 2 | P63: =IF(K63="",0,IF(L63="",TODAY()-K63,L63-K63+1)) -> 8 | Q63: =IF(P63=0,0,O63-P63) -> -6
A64: 62 | B64: FINANCE | D64: Fooding Pending Approval Issue Fix | E64: TESTING ISSUE | F64: COMPLETE | I64: 45135 | J64: 45138 | K64: 45135 | L64: 45142 | O64: =IF(IF(I64="",0,IF(J64="",0,J64-I64))="",0,J64-I64+1) -> 4 | P64: =IF(K64="",0,IF(L64="",TODAY()-K64,L64-K64+1)) -> 8 | Q64: =IF(P64=0,0,O64-P64) -> -4
A65: 63 | B65: MASTER | D65: Parallel & Non Parallel Function Implment In The Approval Matrix | E65: IMPROVEMENT | F65: COMPLETE | I65: 45139 | J65: 45147 | K65: 45143 | L65: 45156 | O65: =IF(IF(I65="",0,IF(J65="",0,J65-I65))="",0,J65-I65+1) -> 9 | P65: =IF(K65="",0,IF(L65="",TODAY()-K65,L65-K65+1)) -> 14 | Q65: =IF(P65=0,0,O65-P65) -> -5
A66: 64 | B66: FINANCE | D66: Parallel & Non Parallel Code Bind In The Fooding Section | E66: TESTING ISSUE | F66: COMPLETE | I66: 45148 | J66: 45151 | K66: 45157 | L66: 45159 | O66: =IF(IF(I66="",0,IF(J66="",0,J66-I66))="",0,J66-I66+1) -> 4 | P66: =IF(K66="",0,IF(L66="",TODAY()-K66,L66-K66+1)) -> 3 | Q66: =IF(P66=0,0,O66-P66) -> 1
A67: 65 | B67: MASTER | D67: In A 4Stage Approval, After 3Rd Stage When We Delete 2Nd & 3Rd Stage, The Status Of The Entry Is Showing Blank | E67: 2ND PHASE | F67: LIVE
A68: 66 | B68: MASTER | D68: In Cash Range If We Select Same Approver For Both Ranges It Not Showing All Entries | E68: 2ND PHASE | F68: LIVE
A69: 67 | B69: MASTER | D69: Fix Sequential Stage No Entry Issue In Approval Matrix | E69: LIVE ISSUE | F69: LIVE | I69: 45161 | J69: 45163 | K69: 45161 | L69: 45166 | O69: =IF(IF(I69="",0,IF(J69="",0,J69-I69))="",0,J69-I69+1) -> 3 | P69: =IF(K69="",0,IF(L69="",TODAY()-K69,L69-K69+1)) -> 6 | Q69: =IF(P69=0,0,O69-P69) -> -3
A70: 68 | B70: HI-TOMI | D70: Modification In Person Wise Hi Tomi Generation Mis Report Page As Per New Design Section | E70: LIVE ISSUE | F70: LIVE | I70: 45167 | J70: 45171 | K70: 45168 | L70: 45180 | O70: =IF(IF(I70="",0,IF(J70="",0,J70-I70))="",0,J70-I70+1) -> 5 | P70: =IF(K70="",0,IF(L70="",TODAY()-K70,L70-K70+1)) -> 13 | Q70: =IF(P70=0,0,O70-P70) -> -8
A71: 69 | B71: MASTER | D71: Update Process Guide For Approval Matrix | E71: OTHER | F71: COMPLETE | I71: =J70+1 -> 45172 | J71: =I71+2 -> 45174 | K71: 45181 | L71: =K71+4 -> 45185 | O71: =IF(IF(I71="",0,IF(J71="",0,J71-I71))="",0,J71-I71+1) -> 3 | P71: =IF(K71="",0,IF(L71="",TODAY()-K71,L71-K71+1)) -> 5 | Q71: =IF(P71=0,0,O71-P71) -> -2
A72: 70 | B72: MASTER | D72: Solve Parallel And Non Parallel Issue In Fooding Section | E72: TESTING ISSUE | F72: DEV COMPLETE | I72: 45188 | J72: 45190 | K72: 45189 | L72: 45191 | O72: =IF(IF(I72="",0,IF(J72="",0,J72-I72))="",0,J72-I72+1) -> 3 | P72: =IF(K72="",0,IF(L72="",TODAY()-K72,L72-K72+1)) -> 3 | Q72: =IF(P72=0,0,O72-P72) -> 0
A73: 71 | B73: HI-TOMI | D73: Person Wise Hi Tomi Generation Mis Report 2Nd Stage Implementation | E73: 2ND PHASE | F73: LIVE | I73: 45194 | J73: 45196 | K73: 45194 | L73: 45205 | O73: =IF(IF(I73="",0,IF(J73="",0,J73-I73))="",0,J73-I73+1) -> 3 | P73: =IF(K73="",0,IF(L73="",TODAY()-K73,L73-K73+1)) -> 12 | Q73: =IF(P73=0,0,O73-P73) -> -9
A74: 72 | B74: HI-TOMI | D74: Dept Head Wise Hi-Tomi Generation Mis 2Nd Stage Implementation | E74: 2ND PHASE | F74: LIVE | I74: 45206 | J74: 45209 | K74: 45206 | L74: 45212 | O74: =IF(IF(I74="",0,IF(J74="",0,J74-I74))="",0,J74-I74+1) -> 4 | P74: =IF(K74="",0,IF(L74="",TODAY()-K74,L74-K74+1)) -> 7 | Q74: =IF(P74=0,0,O74-P74) -> -3
A75: 73 | B75: HI-TOMI | D75: Person Wise Hi-Tomi Mis Report 2Nd Stage Implementation | E75: 2ND PHASE | F75: LIVE | I75: 45213 | J75: 45216 | K75: 45213 | L75: 45216 | O75: =IF(IF(I75="",0,IF(J75="",0,J75-I75))="",0,J75-I75+1) -> 4 | P75: =IF(K75="",0,IF(L75="",TODAY()-K75,L75-K75+1)) -> 4 | Q75: =IF(P75=0,0,O75-P75) -> 0
A76: 74 | B76: HI-TOMI | D76: Dept Head Wise Hi-Tomi Mis 2Nd Stage Implementation | E76: 2ND PHASE | F76: LIVE | I76: 45217 | J76: 45219 | K76: 45217 | L76: 45219 | O76: =IF(IF(I76="",0,IF(J76="",0,J76-I76))="",0,J76-I76+1) -> 3 | P76: =IF(K76="",0,IF(L76="",TODAY()-K76,L76-K76+1)) -> 3 | Q76: =IF(P76=0,0,O76-P76) -> 0
A77: 75 | B77: HI-TOMI | D77: Generation And Closer Report | E77: 2ND PHASE | F77: LIVE | I77: 45224 | J77: 45227 | K77: 45224 | L77: 45229 | O77: =IF(IF(I77="",0,IF(J77="",0,J77-I77))="",0,J77-I77+1) -> 4 | P77: =IF(K77="",0,IF(L77="",TODAY()-K77,L77-K77+1)) -> 6 | Q77: =IF(P77=0,0,O77-P77) -> -2
A78: 76 | B78: HI-TOMI | D78: Re Assign Hi-Tomi | E78: IMPROVEMENT | F78: LIVE | I78: 45200 | J78: 45204 | K78: 45200 | L78: 45206 | O78: =IF(IF(I78="",0,IF(J78="",0,J78-I78))="",0,J78-I78+1) -> 5 | P78: =IF(K78="",0,IF(L78="",TODAY()-K78,L78-K78+1)) -> 7 | Q78: =IF(P78=0,0,O78-P78) -> -2
A79: 77 | B79: HI-TOMI | D79: Solve Hitomi Issue In View Page | F79: LIVE | I79: 45233 | J79: 45234 | K79: 45233 | L79: 45237 | O79: =IF(IF(I79="",0,IF(J79="",0,J79-I79))="",0,J79-I79+1) -> 2 | P79: =IF(K79="",0,IF(L79="",TODAY()-K79,L79-K79+1)) -> 5 | Q79: =IF(P79=0,0,O79-P79) -> -3
A80: 78 | B80: HI-TOMI | D80: Hi tomi assigned points issue fix. | E80: TESTING ISSUE | F80: COMPLETE | I80: 45259 | J80: 45260 | K80: 45259 | L80: 45264 | O80: =IF(IF(I80="",0,IF(J80="",0,J80-I80))="",0,J80-I80+1) -> 2 | P80: =IF(K80="",0,IF(L80="",TODAY()-K80,L80-K80+1)) -> 6 | Q80: =IF(P80=0,0,O80-P80) -> -4
A81: 79 | B81: HI-TOMI | D81: Download excel in all hitomi list page. | E81: TESTING ISSUE | F81: COMPLETE | I81: 45262 | J81: 45262 | K81: 45264 | L81: 45266 | O81: =IF(IF(I81="",0,IF(J81="",0,J81-I81))="",0,J81-I81+1) -> 1 | P81: =IF(K81="",0,IF(L81="",TODAY()-K81,L81-K81+1)) -> 3 | Q81: =IF(P81=0,0,O81-P81) -> -2
A82: 80 | B82: HI-TOMI | D82: Calculation And Header Issues In Hitomi Excel Reports | E82: TESTING ISSUE | F82: DEV COMPLETE | I82: 45248 | J82: 45250 | K82: 45251 | L82: 45264 | O82: =IF(IF(I82="",0,IF(J82="",0,J82-I82))="",0,J82-I82+1) -> 3 | P82: =IF(K82="",0,IF(L82="",TODAY()-K82,L82-K82+1)) -> 14 | Q82: =IF(P82=0,0,O82-P82) -> -11
A83: 81 | B83: HI-TOMI | D83: Modification in all hitomi listpage | E83: IMPROVEMENT | F83: COMPLETE | I83: 45259 | J83: 45260 | K83: 45259 | L83: 45264 | O83: =IF(IF(I83="",0,IF(J83="",0,J83-I83))="",0,J83-I83+1) -> 2 | P83: =IF(K83="",0,IF(L83="",TODAY()-K83,L83-K83+1)) -> 6 | Q83: =IF(P83=0,0,O83-P83) -> -4
A84: 82 | B84: HI-TOMI | D84: download excel in all hitomi list page. | E84: IMPROVEMENT | F84: COMPLETE | I84: 45262 | J84: 45262 | K84: 45264 | L84: 45266 | O84: =IF(IF(I84="",0,IF(J84="",0,J84-I84))="",0,J84-I84+1) -> 1 | P84: =IF(K84="",0,IF(L84="",TODAY()-K84,L84-K84+1)) -> 3 | Q84: =IF(P84=0,0,O84-P84) -> -2
A85: 83 | B85: HI-TOMI | D85: Solve wrong calculation in person wise hitomi mis report | E85: IMPROVEMENT | F85: DEV COMPLETE | I85: 45266 | J85: 45267 | K85: 45267 | L85: 45286 | O85: =IF(IF(I85="",0,IF(J85="",0,J85-I85))="",0,J85-I85+1) -> 2 | P85: =IF(K85="",0,IF(L85="",TODAY()-K85,L85-K85+1)) -> 20 | Q85: =IF(P85=0,0,O85-P85) -> -18
A86: 84 | B86: HI-TOMI | D86: Design modification in all hitomi report pages | E86: IMPROVEMENT | F86: COMPLETE | I86: 45272 | J86: 45272 | K86: 45271 | L86: 45275 | O86: =IF(IF(I86="",0,IF(J86="",0,J86-I86))="",0,J86-I86+1) -> 1 | P86: =IF(K86="",0,IF(L86="",TODAY()-K86,L86-K86+1)) -> 5 | Q86: =IF(P86=0,0,O86-P86) -> -4
A87: 85 | B87: HI-TOMI | D87: solve hitomi error | E87: ISSUE FIX | F87: COMPLETE | I87: 45275 | J87: 45276 | K87: 45275 | L87: 45279 | O87: =IF(IF(I87="",0,IF(J87="",0,J87-I87))="",0,J87-I87+1) -> 2 | P87: =IF(K87="",0,IF(L87="",TODAY()-K87,L87-K87+1)) -> 5 | Q87: =IF(P87=0,0,O87-P87) -> -3
A88: 86 | B88: HI-TOMI | D88: show re-assign status details in hitomi view page | F88: COMPLETE | I88: 45279 | J88: 45279 | K88: 45279 | L88: 45281 | O88: =IF(IF(I88="",0,IF(J88="",0,J88-I88))="",0,J88-I88+1) -> 1 | P88: =IF(K88="",0,IF(L88="",TODAY()-K88,L88-K88+1)) -> 3 | Q88: =IF(P88=0,0,O88-P88) -> -2
A89: 87 | B89: HI-TOMI | D89: Approval matrix non cash range edit page issue check | E89: DEV ISSUE FIX | F89: TESTING | I89: 45285 | J89: 45286 | K89: 45286 | L89: 45292 | O89: =IF(IF(I89="",0,IF(J89="",0,J89-I89))="",0,J89-I89+1) -> 2 | P89: =IF(K89="",0,IF(L89="",TODAY()-K89,L89-K89+1)) -> 7 | Q89: =IF(P89=0,0,O89-P89) -> -5
A90: 88 | B90: HI-TOMI | D90: Design modification in all hitomi report pages | F90: DEV COMPLETE | I90: 45272 | J90: 45272 | K90: 45271 | L90: 45275 | O90: =IF(IF(I90="",0,IF(J90="",0,J90-I90))="",0,J90-I90+1) -> 1 | P90: =IF(K90="",0,IF(L90="",TODAY()-K90,L90-K90+1)) -> 5 | Q90: =IF(P90=0,0,O90-P90) -> -4
A91: 89 | B91: HI-TOMI | D91: solve hitomi error - When we click on Go to list from notification section of a Hi-tomi. The page is showing insufficient & wrong Data | E91: TESTING ISSUE | F91: LIVE | I91: 45275 | J91: 45276 | K91: 45275 | L91: 45279 | O91: =IF(IF(I91="",0,IF(J91="",0,J91-I91))="",0,J91-I91+1) -> 2 | P91: =IF(K91="",0,IF(L91="",TODAY()-K91,L91-K91+1)) -> 5 | Q91: =IF(P91=0,0,O91-P91) -> -3
A92: 90 | B92: HI-TOMI | D92: Show re-assign status details in hitomi view page | E92: IMPROVEMENT | F92: LIVE | I92: 45279 | J92: 45279 | K92: 45279 | L92: 45281 | O92: =IF(IF(I92="",0,IF(J92="",0,J92-I92))="",0,J92-I92+1) -> 1 | P92: =IF(K92="",0,IF(L92="",TODAY()-K92,L92-K92+1)) -> 3 | Q92: =IF(P92=0,0,O92-P92) -> -2
A93: 91 | B93: HI-TOMI | C93: aLL ASSIGNED BY MW,,ALL ASSIGNED TO ME | D93: show color coding of different Hi-tomi task status details in all hitomi ,all assigned by me , all assigned to me list pages | E93: IMPROVEMENT | F93: DEV COMPLETE | I93: 45281 | J93: 45282 | K93: 45281 | L93: 45286 | O93: =IF(IF(I93="",0,IF(J93="",0,J93-I93))="",0,J93-I93+1) -> 2 | P93: =IF(K93="",0,IF(L93="",TODAY()-K93,L93-K93+1)) -> 6 | Q93: =IF(P93=0,0,O93-P93) -> -4
A94: 92 | B94: MASTER | C94: Approval matrix | D94: analyse and solve approval matrix non cash range and cash range edit page issue | F94: COMPLETE | I94: 45285 | J94: 45293 | K94: 45286 | L94: 45294 | O94: =IF(IF(I94="",0,IF(J94="",0,J94-I94))="",0,J94-I94+1) -> 9 | P94: =IF(K94="",0,IF(L94="",TODAY()-K94,L94-K94+1)) -> 9 | Q94: =IF(P94=0,0,O94-P94) -> 0
A95: 93 | B95: PURCHASE | C95: RATE REQUEST | D95: Rate request form page modification in purchase module | E95: MIS | F95: DEV COMPLETE | I95: 45294 | J95: 45295 | K95: 45294 | L95: 45299 | O95: =IF(IF(I95="",0,IF(J95="",0,J95-I95))="",0,J95-I95+1) -> 2 | P95: =IF(K95="",0,IF(L95="",TODAY()-K95,L95-K95+1)) -> 6 | Q95: =IF(P95=0,0,O95-P95) -> -4
A96: 94 | B96: MASTER | C96: Approval matrix | D96: Approval matrix issue fix | E96: OTHER | F96: DEV COMPLETE | I96: 45299 | J96: 45303 | K96: 45301 | L96: 45334 | O96: =IF(IF(I96="",0,IF(J96="",0,J96-I96))="",0,J96-I96+1) -> 5 | P96: =IF(K96="",0,IF(L96="",TODAY()-K96,L96-K96+1)) -> 34 | Q96: =IF(P96=0,0,O96-P96) -> -29
A97: 95 | B97: SALES | D97: Approval matrix | F97: COMPLETE | I97: 45322 | J97: 45327 | K97: 45322 | L97: 45334 | O97: =IF(IF(I97="",0,IF(J97="",0,J97-I97))="",0,J97-I97+1) -> 6 | P97: =IF(K97="",0,IF(L97="",TODAY()-K97,L97-K97+1)) -> 13 | Q97: =IF(P97=0,0,O97-P97) -> -7
A98: 96 | B98: FINANCE | C98: EMD REGISTER | D98: EMD Register mis with new design and all functionality | E98: 2ND PHASE | F98: DEV COMPLETE | I98: 45334 | J98: 45337 | K98: 45339 | L98: 45339 | O98: =IF(IF(I98="",0,IF(J98="",0,J98-I98))="",0,J98-I98+1) -> 4 | P98: =IF(K98="",0,IF(L98="",TODAY()-K98,L98-K98+1)) -> 1 | Q98: =IF(P98=0,0,O98-P98) -> 3
A99: 97 | B99: FINANCE | C99: WORKING CAPITAL | D99: Registered Working Capital mis with new design and all functionality and isssue fix | E99: 2ND PHASE | F99: DEV COMPLETE | I99: 45338 | J99: 45341 | K99: 45338 | L99: 45340 | O99: =IF(IF(I99="",0,IF(J99="",0,J99-I99))="",0,J99-I99+1) -> 4 | P99: =IF(K99="",0,IF(L99="",TODAY()-K99,L99-K99+1)) -> 3 | Q99: =IF(P99=0,0,O99-P99) -> 1
A100: 98 | B100: MASTER | C100: APPROVAL MATRIX | D100: Modification in get approver function in approvalmatrix function page . | E100: MODIFICATION | F100: COMPLETE | I100: 45342 | J100: 45345 | K100: 45351 | L100: 45351 | O100: =IF(IF(I100="",0,IF(J100="",0,J100-I100))="",0,J100-I100+1) -> 4 | P100: =IF(K100="",0,IF(L100="",TODAY()-K100,L100-K100+1)) -> 1 | Q100: =IF(P100=0,0,O100-P100) -> 3
A101: 99 | B101: HI-TOMI | C101: RECENT UPDATE HI TOMI | D101: Recently updated hitomi excel download issue and test getapprover function in fd processing | E101: ISSUE FIX | F101: COMPLETE | I101: 45356 | J101: 45358 | K101: 45367 | L101: 45367 | O101: =IF(IF(I101="",0,IF(J101="",0,J101-I101))="",0,J101-I101+1) -> 3 | P101: =IF(K101="",0,IF(L101="",TODAY()-K101,L101-K101+1)) -> 1 | Q101: =IF(P101=0,0,O101-P101) -> 2
...

Sheet SREEDHAR
P1: =SUM(P3:P1070) -> 248 | Q1: =SUM(Q3:Q1070) -> 307 | R1: =SUM(R3:R1070) -> -63
A2: L NO | B2: MODULE | C2: SUB MODULE | D2: ACTIVITIES | E2: WORK TYPE | F2: STATUS | G2: APPROVAL | H2: RESTRICTION | I2: NOTIFICATION | J2: TGT ST DATE | K2: TGT END DATE | L2: ACT ST DATE | M2: ACT END DATE | N2: PROB ST DT | O2: PROB END DT | P2: TGT DUR | Q2: ACT DUR | R2: T SAVING | S2: DELAY REASON STATUS
A3: 1 | B3: PURCHASE | D3: In List View Page Supplier Name Column Required Rate Request | E3: IMPROVEMENT | F3: LIVE | J3: 45090 | K3: 45090 | L3: 45090 | M3: 45090 | N3: =L3 -> 45090 | O3: =N3+P3-1 -> 45090 | P3: =IF(IF(J3="",0,IF(K3="",0,K3-J3))="",0,K3-J3+1) -> 1 | Q3: =IF(L3="",0,IF(M3="",TODAY()-L3,M3-L3+1)) -> 1 | R3: =IF(Q3=0,0,P3-Q3) -> 0
A4: 2 | B4: PURCHASE | D4: Cs Must Sort From L1 To Highest From Left To Right | E4: IMPROVEMENT | F4: LIVE | J4: 45090 | K4: 45091 | L4: 45090 | M4: 45091 | N4: =IF(L4="",IF(M3="",O3+1,M3+1),L4) -> 45090 | O4: =IF(N4="","",N4+P4-1) -> 45091 | P4: =IF(IF(J4="",0,IF(K4="",0,K4-J4))="",0,K4-J4+1) -> 2 | Q4: =IF(L4="",0,IF(M4="",TODAY()-L4,M4-L4+1)) -> 2 | R4: =IF(Q4=0,0,P4-Q4) -> 0
A5: 3 | B5: MGMT | D5: Target Acchiment Approval Work With Notification | E5: IMPROVEMENT | F5: LIVE | J5: 45092 | K5: 45098 | L5: 45092 | M5: 45098 | N5: =IF(L5="",IF(M4="",O4+1,M4+1),L5) -> 45092 | O5: =IF(N5="","",N5+P5-1) -> 45098 | P5: =IF(IF(J5="",0,IF(K5="",0,K5-J5))="",0,K5-J5+1) -> 7 | Q5: =IF(L5="",0,IF(M5="",TODAY()-L5,M5-L5+1)) -> 7 | R5: =IF(Q5=0,0,P5-Q5) -> 0
A6: 4 | B6: MGMT | D6: Changing Supervisor To Ra In Add Target Page,Ra Specific Pdf Excel In Acv List | E6: IMPROVEMENT | F6: LIVE | J6: 45099 | K6: 45104 | L6: 45103 | M6: 45104 | N6: =IF(L6="",IF(M5="",O5+1,M5+1),L6) -> 45103 | O6: =IF(N6="","",N6+P6-1) -> 45108 | P6: =IF(IF(J6="",0,IF(K6="",0,K6-J6))="",0,K6-J6+1) -> 6 | Q6: =IF(L6="",0,IF(M6="",TODAY()-L6,M6-L6+1)) -> 2 | R6: =IF(Q6=0,0,P6-Q6) -> 4
A7: 5 | B7: MGMT | C7: TARGET VS ACHIVMENT | D7: Target Vs Achievement Listing Change As Per The Final Approval | E7: IMPROVEMENT | F7: LIVE | J7: 45105 | K7: 45106 | L7: 45106 | M7: 45110 | N7: =IF(L7="",IF(M6="",O6+1,M6+1),L7) -> 45106 | O7: =IF(N7="","",N7+P7-1) -> 45107 | P7: =IF(IF(J7="",0,IF(K7="",0,K7-J7))="",0,K7-J7+1) -> 2 | Q7: =IF(L7="",0,IF(M7="",TODAY()-L7,M7-L7+1)) -> 5 | R7: =IF(Q7=0,0,P7-Q7) -> -3
A8: 6 | B8: MGMT | C8: TARGET VS ACHIVMENT | D8: Target Achiment Pending Approval Work With Notification | E8: IMPROVEMENT | F8: LIVE | J8: 45107 | K8: 45110 | L8: 45118 | M8: 45124 | N8: =IF(L8="",IF(M7="",O7+1,M7+1),L8) -> 45118 | O8: =IF(N8="","",N8+P8-1) -> 45121 | P8: =IF(IF(J8="",0,IF(K8="",0,K8-J8))="",0,K8-J8+1) -> 4 | Q8: =IF(L8="",0,IF(M8="",TODAY()-L8,M8-L8+1)) -> 7 | R8: =IF(Q8=0,0,P8-Q8) -> -3
A9: 7 | B9: MGMT | C9: TARGET VS ACHIVMENT | D9: Issue Fixation In Target Vs Achievement | E9: LIVE ISSUE | F9: LIVE | J9: 45111 | K9: 45115 | L9: 45113 | M9: 45117 | N9: =IF(L9="",IF(M8="",O8+1,M8+1),L9) -> 45113 | O9: =IF(N9="","",N9+P9-1) -> 45117 | P9: =IF(IF(J9="",0,IF(K9="",0,K9-J9))="",0,K9-J9+1) -> 5 | Q9: =IF(L9="",0,IF(M9="",TODAY()-L9,M9-L9+1)) -> 5 | R9: =IF(Q9=0,0,P9-Q9) -> 0
A10: 8 | D10: Kt Transfer From Sandeep Jena - Transport ,Vendor , Suplier Invoice Processing | F10: COMPLETE | J10: 45126 | K10: 45147 | L10: 45126 | M10: 45147 | N10: =IF(L10="",IF(M9="",O9+1,M9+1),L10) -> 45126 | O10: =IF(N10="","",N10+P10-1) -> 45147 | P10: =IF(IF(J10="",0,IF(K10="",0,K10-J10))="",0,K10-J10+1) -> 22 | Q10: =IF(L10="",0,IF(M10="",TODAY()-L10,M10-L10+1)) -> 22 | R10: =IF(Q10=0,0,P10-Q10) -> 0
A11: 9 | B11: FINANCE | C11: PFR REPORT | D11: Purpose Fullfillment Report | E11: REPORT | F11: LIVE | J11: 45149 | K11: 45166 | L11: 45149 | M11: 45166 | N11: =IF(L11="",IF(M10="",O10+1,M10+1),L11) -> 45149 | O11: =IF(N11="","",N11+P11-1) -> 45166 | P11: =IF(IF(J11="",0,IF(K11="",0,K11-J11))="",0,K11-J11+1) -> 18 | Q11: =IF(L11="",0,IF(M11="",TODAY()-L11,M11-L11+1)) -> 18 | R11: =IF(Q11=0,0,P11-Q11) -> 0
A12: 10 | B12: FINANCE | C12: PFR REPORT | D12: Purpose Fullfillment Report Dynamic Approval Link | E12: 2ND STAGE | F12: LIVE | J12: 45166 | K12: 45169 | L12: 45169 | M12: 45171 | N12: =IF(L12="",IF(M11="",O11+1,M11+1),L12) -> 45169 | O12: =IF(N12="","",N12+P12-1) -> 45172 | P12: =IF(IF(J12="",0,IF(K12="",0,K12-J12))="",0,K12-J12+1) -> 4 | Q12: =IF(L12="",0,IF(M12="",TODAY()-L12,M12-L12+1)) -> 3 | R12: =IF(Q12=0,0,P12-Q12) -> 1
A13: 11 | B13: FINANCE | C13: BENEFICIARY | D13: Beneficiary Processing In Pending Approval . | E13: IMPROVEMENT | F13: LIVE | J13: 45173 | K13: 45174 | L13: 45173 | M13: 45174 | N13: =IF(L13="",IF(M12="",O12+1,M12+1),L13) -> 45173 | O13: =IF(N13="","",N13+P13-1) -> 45174 | P13: =IF(IF(J13="",0,IF(K13="",0,K13-J13))="",0,K13-J13+1) -> 2 | Q13: =IF(L13="",0,IF(M13="",TODAY()-L13,M13-L13+1)) -> 2 | R13: =IF(Q13=0,0,P13-Q13) -> 0
A14: 12 | B14: FINANCE | C14: SUPPLIER INVOICE | D14: Supplier Invoice Enhancements | E14: IMPROVEMENT | F14: COMPLETE | J14: 45175 | K14: 45179 | L14: 45174 | M14: 45182 | N14: =IF(L14="",IF(M13="",O13+1,M13+1),L14) -> 45174 | O14: =IF(N14="","",N14+P14-1) -> 45178 | P14: =IF(IF(J14="",0,IF(K14="",0,K14-J14))="",0,K14-J14+1) -> 5 | Q14: =IF(L14="",0,IF(M14="",TODAY()-L14,M14-L14+1)) -> 9 | R14: =IF(Q14=0,0,P14-Q14) -> -4
A15: 13 | B15: FINANCE | C15: PFR REPORT | D15: Multiple Attachment And Pfr Related Fields Showing In Other Payment Request View Page. | E15: IMPROVEMENT | F15: LIVE | J15: 45180 | K15: 45182 | L15: 45183 | M15: 45183 | N15: =IF(L15="",IF(M14="",O14+1,M14+1),L15) -> 45183 | O15: =IF(N15="","",N15+P15-1) -> 45185 | P15: =IF(IF(J15="",0,IF(K15="",0,K15-J15))="",0,K15-J15+1) -> 3 | Q15: =IF(L15="",0,IF(M15="",TODAY()-L15,M15-L15+1)) -> 1 | R15: =IF(Q15=0,0,P15-Q15) -> 2
A16: 14 | B16: FINANCE | C16: PFR REPORT | D16: Pfr Pending Approval Link With Notification | E16: IMPROVEMENT | F16: LIVE | J16: 45183 | K16: 45189 | L16: 45184 | M16: 45188 | N16: =IF(L16="",IF(M15="",O15+1,M15+1),L16) -> 45184 | O16: =IF(N16="","",N16+P16-1) -> 45190 | P16: =IF(IF(J16="",0,IF(K16="",0,K16-J16))="",0,K16-J16+1) -> 7 | Q16: =IF(L16="",0,IF(M16="",TODAY()-L16,M16-L16+1)) -> 5 | R16: =IF(Q16=0,0,P16-Q16) -> 2
A17: 15 | B17: FINANCE | C17: SUPPLIER INVOICE | D17: Supplier Invoice Enhancements & Dynamic Approval | E17: 2ND STAGE | F17: LIVE | J17: 45196 | K17: 45204 | L17: 45196 | M17: 45210 | N17: =IF(L17="",IF(M16="",O16+1,M16+1),L17) -> 45196 | O17: =IF(N17="","",N17+P17-1) -> 45204 | P17: =IF(IF(J17="",0,IF(K17="",0,K17-J17))="",0,K17-J17+1) -> 9 | Q17: =IF(L17="",0,IF(M17="",TODAY()-L17,M17-L17+1)) -> 15 | R17: =IF(Q17=0,0,P17-Q17) -> -6
A18: 16 | B18: FINANCE | C18: OTHER PAYMENT REQUEST | D18: Modification In Add Other Payment Request And View Other Payment Request | E18: IMPROVEMENT | F18: LIVE | J18: 45210 | K18: 45212 | L18: 45211 | M18: 45212 | N18: =IF(L18="",IF(M17="",O17+1,M17+1),L18) -> 45211 | O18: =IF(N18="","",N18+P18-1) -> 45213 | P18: =IF(IF(J18="",0,IF(K18="",0,K18-J18))="",0,K18-J18+1) -> 3 | Q18: =IF(L18="",0,IF(M18="",TODAY()-L18,M18-L18+1)) -> 2 | R18: =IF(Q18=0,0,P18-Q18) -> 1
A19: 17 | B19: FINANCE | D19: Excel Download | E19: OTHER | F19: LIVE | J19: 45215 | K19: 45215 | L19: 45215 | M19: 45217 | N19: =IF(L19="",IF(M18="",O18+1,M18+1),L19) -> 45215 | O19: =IF(N19="","",N19+P19-1) -> 45215 | P19: =IF(IF(J19="",0,IF(K19="",0,K19-J19))="",0,K19-J19+1) -> 1 | Q19: =IF(L19="",0,IF(M19="",TODAY()-L19,M19-L19+1)) -> 3 | R19: =IF(Q19=0,0,P19-Q19) -> -2
A20: 18 | B20: FINANCE | C20: PAYMENT REQUEST | D20: Image Zooming And Rotate Functionlity In Payment Request | E20: IMPROVEMENT | F20: LIVE | J20: 45217 | K20: 45217 | L20: 45217 | M20: 45217 | N20: =IF(L20="",IF(M19="",O19+1,M19+1),L20) -> 45217 | O20: =IF(N20="","",N20+P20-1) -> 45217 | P20: =IF(IF(J20="",0,IF(K20="",0,K20-J20))="",0,K20-J20+1) -> 1 | Q20: =IF(L20="",0,IF(M20="",TODAY()-L20,M20-L20+1)) -> 1 | R20: =IF(Q20=0,0,P20-Q20) -> 0
A21: 19 | B21: FINANCE | C21: PAYMENT REQUEST | D21: All Payment Requests (Php Pagination, Filter, Sorting, Searching ,Excel) | E21: IMPROVEMENT | F21: LIVE | J21: 45217 | K21: 45219 | L21: 45217 | M21: 45226 | N21: =IF(L21="",IF(M20="",O20+1,M20+1),L21) -> 45217 | O21: =IF(N21="","",N21+P21-1) -> 45219 | P21: =IF(IF(J21="",0,IF(K21="",0,K21-J21))="",0,K21-J21+1) -> 3 | Q21: =IF(L21="",0,IF(M21="",TODAY()-L21,M21-L21+1)) -> 10 | R21: =IF(Q21=0,0,P21-Q21) -> -7
A22: 20 | B22: FINANCE | C22: SUPPLIER INVOICE ENRY, SUPPLIER INVOICE APPROVAL | D22: Php Pagination Adding In Supplier Invoice Entry Listing. 2.Adding Pending Supplier Invoice Processing (Approval) In Pending Approva | E22: IMPROVEMENT | F22: LIVE | J22: 45224 | K22: 45229 | L22: 45226 | M22: 45232 | N22: =IF(L22="",IF(M21="",O21+1,M21+1),L22) -> 45226 | O22: =IF(N22="","",N22+P22-1) -> 45231 | P22: =IF(IF(J22="",0,IF(K22="",0,K22-J22))="",0,K22-J22+1) -> 6 | Q22: =IF(L22="",0,IF(M22="",TODAY()-L22,M22-L22+1)) -> 7 | R22: =IF(Q22=0,0,P22-Q22) -> -1
A23: 21 | B23: FINANCE | C23: ALL PAYMENT REQUEST | D23: Live Issue Modification In All Payment Requests. | E23: LIVE ISSUE | F23: LIVE | J23: 45229 | K23: 45231 | L23: 45232 | M23: 45232 | N23: =IF(L23="",IF(#REF!="",#REF!+1,#REF!+1),L23) -> 45232 | O23: =IF(N23="","",N23+P23-1) -> 45234 | P23: =IF(IF(J23="",0,IF(K23="",0,K23-J23))="",0,K23-J23+1) -> 3 | Q23: =IF(L23="",0,IF(M23="",TODAY()-L23,M23-L23+1)) -> 1 | R23: =IF(Q23=0,0,P23-Q23) -> 2
A24: 22 | B24: FINANCE | C24: MANAGE LOCATION | D24: Manage Location issue fix | E24: ISSUE FIX | F24: LIVE | J24: 45236 | K24: 45237 | L24: 45236 | M24: 45238 | N24: =IF(L24="",IF(M23="",O23+1,M23+1),L24) -> 45236 | O24: =IF(N24="","",N24+P24-1) -> 45237 | P24: =IF(IF(J24="",0,IF(K24="",0,K24-J24))="",0,K24-J24+1) -> 2 | Q24: =IF(L24="",0,IF(M24="",TODAY()-L24,M24-L24+1)) -> 3 | R24: =IF(Q24=0,0,P24-Q24) -> -1
A25: 23 | B25: FINANCE | C25: SUPPLIER INVOICE ENRY | D25: Testing All Functionality In Supplier Invoice Entry And Approval | E25: OTHER | F25: COMPLETE | J25: 45237 | K25: 45237 | L25: 45238 | M25: 45238 | N25: =IF(L25="",IF(M24="",O24+1,M24+1),L25) -> 45238 | O25: =IF(N25="","",N25+P25-1) -> 45238 | P25: =IF(IF(J25="",0,IF(K25="",0,K25-J25))="",0,K25-J25+1) -> 1 | Q25: =IF(L25="",0,IF(M25="",TODAY()-L25,M25-L25+1)) -> 1 | R25: =IF(Q25=0,0,P25-Q25) -> 0
A26: 24 | B26: FINANCE | C26: VEBDER CREADIT LIMIT | D26: Vendor credit limit link with payment request . | E26: IMPROVEMENT | F26: LIVE | J26: 45238 | K26: 45286 | L26: 45241 | M26: 45286 | N26: =IF(L26="",IF(M25="",O25+1,M25+1),L26) -> 45241 | O26: =IF(N26="","",N26+P26-1) -> 45289 | P26: =IF(IF(J26="",0,IF(K26="",0,K26-J26))="",0,K26-J26+1) -> 49 | Q26: =IF(L26="",0,IF(M26="",TODAY()-L26,M26-L26+1)) -> 46 | R26: =IF(Q26=0,0,P26-Q26) -> 3
A27: 25 | B27: FINANCE | C27: SUPPIER INVOICE APPROVAL | D27: Test Supplier Invoice entry and approval for Update in Live | E27: OTHER | F27: COMPLETE | J27: 45258 | K27: 45258 | L27: 45261 | M27: 45261 | N27: =IF(L27="",IF(M26="",O26+1,M26+1),L27) -> 45261 | O27: =IF(N27="","",N27+P27-1) -> 45261 | P27: =IF(IF(J27="",0,IF(K27="",0,K27-J27))="",0,K27-J27+1) -> 1 | Q27: =IF(L27="",0,IF(M27="",TODAY()-L27,M27-L27+1)) -> 1 | R27: =IF(Q27=0,0,P27-Q27) -> 0
A28: 26 | B28: FINANCE | C28: PFR REPORT | D28: PFR issue solving and modification | E28: TESTING ISSUE | F28: LIVE | J28: 45251 | K28: 45253 | L28: 45253 | M28: 45253 | N28: =IF(L28="",IF(M27="",O27+1,M27+1),L28) -> 45253 | O28: =IF(N28="","",N28+P28-1) -> 45255 | P28: =IF(IF(J28="",0,IF(K28="",0,K28-J28))="",0,K28-J28+1) -> 3 | Q28: =IF(L28="",0,IF(M28="",TODAY()-L28,M28-L28+1)) -> 1 | R28: =IF(Q28=0,0,P28-Q28) -> 2
A29: 27 | B29: All | C29: PFR REPORT | D29: Data base transforming for new Dev server | E29: OTHER | F29: COMPLETE | J29: 45266 | K29: 45266 | L29: 45272 | M29: 45272 | N29: =IF(L29="",IF(M28="",O28+1,M28+1),L29) -> 45272 | O29: =IF(N29="","",N29+P29-1) -> 45272 | P29: =IF(IF(J29="",0,IF(K29="",0,K29-J29))="",0,K29-J29+1) -> 1 | Q29: =IF(L29="",0,IF(M29="",TODAY()-L29,M29-L29+1)) -> 1 | R29: =IF(Q29=0,0,P29-Q29) -> 0
A30: 28 | B30: FINANCE | C30: CREDIT LIMIT | D30: Expiry date in CREDIT LIMIT (Vendor ) . | E30: IMPROVEMENT | F30: COMPLETE | J30: 45280 | K30: 45281 | L30: 45280 | M30: 45282 | N30: =IF(L30="",IF(M29="",O29+1,M29+1),L30) -> 45280 | O30: =IF(N30="","",N30+P30-1) -> 45281 | P30: =IF(IF(J30="",0,IF(K30="",0,K30-J30))="",0,K30-J30+1) -> 2 | Q30: =IF(L30="",0,IF(M30="",TODAY()-L30,M30-L30+1)) -> 3 | R30: =IF(Q30=0,0,P30-Q30) -> -1
A31: 29 | B31: FINANCE | C31: PFR REPORT | D31: Entry old payment request in PFR and changes | E31: MODIFICATION | F31: LIVE | J31: 45283 | K31: 45283 | L31: 45283 | M31: 45283 | N31: =IF(L31="",IF(M30="",O30+1,M30+1),L31) -> 45283 | O31: =IF(N31="","",N31+P31-1) -> 45283 | P31: =IF(IF(J31="",0,IF(K31="",0,K31-J31))="",0,K31-J31+1) -> 1 | Q31: =IF(L31="",0,IF(M31="",TODAY()-L31,M31-L31+1)) -> 1 | R31: =IF(Q31=0,0,P31-Q31) -> 0
A32: 30 | B32: FINANCE | C32: VENDER PAYMENT REQUEST | D32: Adding Restriction in Vendor Payment request while raise request. | E32: IMPROVEMENT | F32: LIVE | J32: 45285 | K32: 45286 | L32: 45285 | M32: 45288 | N32: =IF(L32="",IF(M31="",O31+1,M31+1),L32) -> 45285 | O32: =IF(N32="","",N32+P32-1) -> 45286 | P32: =IF(IF(J32="",0,IF(K32="",0,K32-J32))="",0,K32-J32+1) -> 2 | Q32: =IF(L32="",0,IF(M32="",TODAY()-L32,M32-L32+1)) -> 4 | R32: =IF(Q32=0,0,P32-Q32) -> -2
A33: 32 | B33: FINANCE | C33: ALL SECURITY REPORT | D33: Excel download in security report | E33: IMPROVEMENT | F33: LIVE | J33: 45288 | K33: 45290 | L33: 45288 | M33: 45292 | N33: =IF(L33="",IF(M36="",O36+1,M36+1),L33) -> 45288 | O33: =IF(N33="","",N33+P33-1) -> 45290 | P33: =IF(IF(J33="",0,IF(K33="",0,K33-J33))="",0,K33-J33+1) -> 3 | Q33: =IF(L33="",0,IF(M33="",TODAY()-L33,M33-L33+1)) -> 5 | R33: =IF(Q33=0,0,P33-Q33) -> -2
A34: 33 | B34: FINANCE | C34: PAYMENT REQUEST | D34: Testing the Finance Payment Request module and pending approvals payment request in the Dev Server. | E34: OTHER | F34: COMPLETE | J34: 45287 | K34: 45287 | L34: 45288 | M34: 45295 | N34: =IF(L34="",IF(M33="",O33+1,M33+1),L34) -> 45288 | O34: =IF(N34="","",N34+P34-1) -> 45288 | P34: =IF(IF(J34="",0,IF(K34="",0,K34-J34))="",0,K34-J34+1) -> 1 | Q34: =IF(L34="",0,IF(M34="",TODAY()-L34,M34-L34+1)) -> 8 | R34: =IF(Q34=0,0,P34-Q34) -> -7
A35: 34 | B35: FINANCE | C35: GENERAL LEDGER | D35: General Ledger MIS report | E35: MIS | F35: LIVE | J35: 45292 | K35: 45295 | L35: 45295 | M35: 45299 | N35: =IF(L35="",IF(M34="",O34+1,M34+1),L35) -> 45295 | O35: =IF(N35="","",N35+P35-1) -> 45298 | P35: =IF(IF(J35="",0,IF(K35="",0,K35-J35))="",0,K35-J35+1) -> 4 | Q35: =IF(L35="",0,IF(M35="",TODAY()-L35,M35-L35+1)) -> 5 | R35: =IF(Q35=0,0,P35-Q35) -> -1
A36: 35 | B36: FINANCE | C36: VENDER INVOICE PROCESSING | D36: Vende invoice processing with 2nd stage dynamic approval and design | E36: 2ND STAGE | F36: DEV COMPLETE | J36: 45299 | K36: 45302 | L36: 45292 | M36: 45313 | N36: =IF(L36="",IF(M35="",O35+1,M35+1),L36) -> 45292 | O36: =IF(N36="","",N36+P36-1) -> 45295 | P36: =IF(IF(J36="",0,IF(K36="",0,K36-J36))="",0,K36-J36+1) -> 4 | Q36: =IF(L36="",0,IF(M36="",TODAY()-L36,M36-L36+1)) -> 22 | R36: =IF(Q36=0,0,P36-Q36) -> -18 | S36: TESTING ISSUE FIX
A37: 36 | B37: FINANCE | C37: TRANSPORTER INVOICE PROCESSING | D37: Dynamic approval link in transporter invoice processing and 2nd stage design | E37: 2ND STAGE | F37: HOLD | J37: 45313 | K37: 45316 | L37: 45313 | N37: =IF(L37="",IF(M36="",O36+1,M36+1),L37) -> 45313 | O37: =IF(N37="","",N37+P37-1) -> 45316 | P37: =IF(IF(J37="",0,IF(K37="",0,K37-J37))="",0,K37-J37+1) -> 4 | R37: =IF(Q37=0,0,P37-Q37) -> 0
A38: 37 | B38: FINANCE | D38: Add all fieldname(date,expense no, particulars) in searching in general ledger. | E38: IMPROVEMENT | F38: LIVE | J38: 45324 | K38: 45324 | L38: 45324 | M38: 45334 | N38: =IF(L38="",IF(M37="",O37+1,M37+1),L38) -> 45324 | O38: =IF(N38="","",N38+P38-1) -> 45324 | P38: =IF(IF(J38="",0,IF(K38="",0,K38-J38))="",0,K38-J38+1) -> 1 | Q38: =IF(L38="",0,IF(M38="",TODAY()-L38,M38-L38+1)) -> 11 | R38: =IF(Q38=0,0,P38-Q38) -> -10
A39: 41 | B39: FINANCE | C39: LC PROCESSING | D39: LC Entry New design in listing page. | E39: IMPROVEMENT | F39: LIVE | L39: 45335 | M39: =L39+2 -> 45337
A40: 39 | B40: FINANCE | C40: LC PROCESSING | D40: LC Assignement New design in listing page. | E40: IMPROVEMENT | F40: LIVE | J40: 45332 | K40: 45334 | L40: 45336 | M40: 45337 | N40: =IF(L40="",IF(M38="",O38+1,M38+1),L40) -> 45336 | O40: =IF(N40="","",N40+P40-1) -> 45338 | P40: =IF(IF(J40="",0,IF(K40="",0,K40-J40))="",0,K40-J40+1) -> 3 | Q40: =IF(L40="",0,IF(M40="",TODAY()-L40,M40-L40+1)) -> 2 | R40: =IF(Q40=0,0,P40-Q40) -> 1
A41: 43 | B41: FINANCE | C41: CREDIT LIMIT | D41: Job Order Credit Limit New Design & Dynamic Approval | E41: 2ND PHASE | F41: LIVE | J41: 45342 | K41: 45347 | L41: 45345 | M41: 45349 | N41: =IF(L41="",IF(M39="",O39+1,M39+1),L41) -> 45345 | O41: =IF(N41="","",N41+P41-1) -> 45350 | P41: =IF(IF(J41="",0,IF(K41="",0,K41-J41))="",0,K41-J41+1) -> 6 | Q41: =IF(L41="",0,IF(M41="",TODAY()-L41,M41-L41+1)) -> 5 | R41: =IF(Q41=0,0,P41-Q41) -> 1
A42: 44 | B42: FINANCE | C42: SUPPLIER INVOICE PROCESSING | D42: Supplier Invoice Live issue fixing | E42: OPERATIONAL ISSUES | F42: LIVE | J42: 45350 | K42: 45351 | L42: 45350 | M42: 45358 | N42: =IF(L42="",IF(M40="",O40+1,M40+1),L42) -> 45350 | O42: =IF(N42="","",N42+P42-1) -> 45351 | P42: =IF(IF(J42="",0,IF(K42="",0,K42-J42))="",0,K42-J42+1) -> 2 | Q42: =IF(L42="",0,IF(M42="",TODAY()-L42,M42-L42+1)) -> 9 | R42: =IF(Q42=0,0,P42-Q42) -> -7
A43: 45 | B43: FINANCE | C43: payment assign | D43: Payment Assign for LC processing (live issue for show multiple invoice) . flow checking LC entry ,Payment Initial Assign View page Rectification for LC processing type | E43: OPERATIONAL ISSUES | F43: LIVE | J43: 45356 | K43: 45357 | L43: 45358 | M43: 45358 | N43: =IF(L43="",IF(M41="",O41+1,M41+1),L43) -> 45358 | O43: =IF(N43="","",N43+P43-1) -> 45359 | P43: =IF(IF(J43="",0,IF(K43="",0,K43-J43))="",0,K43-J43+1) -> 2 | Q43: =IF(L43="",0,IF(M43="",TODAY()-L43,M43-L43+1)) -> 1 | R43: =IF(Q43=0,0,P43-Q43) -> 1
A44: 46 | B44: FINANCE | C44: VENDER INVOICEPROCESSIING | D44: VENDER INVOICE PROCESSING TESTING ISSUE FIX | E44: OPERATIONAL ISSUES | F44: COMPLETE | J44: 45360 | K44: 45362 | L44: 45364 | M44: 45364 | N44: =IF(L44="",IF(M42="",O42+1,M42+1),L44) -> 45364 | O44: =IF(N44="","",N44+P44-1) -> 45366 | P44: =IF(IF(J44="",0,IF(K44="",0,K44-J44))="",0,K44-J44+1) -> 3 | Q44: =IF(L44="",0,IF(M44="",TODAY()-L44,M44-L44+1)) -> 1 | R44: =IF(Q44=0,0,P44-Q44) -> 2
A45: 47 | B45: IYRO ERP SALES | D45: IYRO CRM approval removing (finance module Vendor ,Lc) | E45: SALES | F45: COMPLETE | J45: 45363 | K45: 45365 | L45: 45364 | M45: 45371 | N45: =IF(L45="",IF(M43="",O43+1,M43+1),L45) -> 45364 | O45: =IF(N45="","",N45+P45-1) -> 45366 | P45: =IF(IF(J45="",0,IF(K45="",0,K45-J45))="",0,K45-J45+1) -> 3 | Q45: =IF(L45="",0,IF(M45="",TODAY()-L45,M45-L45+1)) -> 8 | R45: =IF(Q45=0,0,P45-Q45) -> -5
A46: 48 | B46: FINANCE | C46: VENDER INVOICEPROCESSIING | D46: Live issue and changes in Supplier Entry access // Working on tester report (vendor invoice ) | E46: Testing Issue | F46: COMPLETE | J46: 45370 | K46: 45373 | L46: 45371 | M46: 45373 | N46: =IF(L46="",IF(M44="",O44+1,M44+1),L46) -> 45371 | O46: =IF(N46="","",N46+P46-1) -> 45374 | P46: =IF(IF(J46="",0,IF(K46="",0,K46-J46))="",0,K46-J46+1) -> 4 | Q46: =IF(L46="",0,IF(M46="",TODAY()-L46,M46-L46+1)) -> 3 | R46: =IF(Q46=0,0,P46-Q46) -> 1
A47: 49 | B47: FINANCE | D47: Bank Transaction API testing in postman. | E47: API | F47: COMPLETE | J47: 45372 | K47: 45376 | L47: 45372 | M47: 45378 | N47: =IF(L47="",IF(M45="",O45+1,M45+1),L47) -> 45372 | O47: =IF(N47="","",N47+P47-1) -> 45376 | P47: =IF(IF(J47="",0,IF(K47="",0,K47-J47))="",0,K47-J47+1) -> 5 | Q47: =IF(L47="",0,IF(M47="",TODAY()-L47,M47-L47+1)) -> 7 | R47: =IF(Q47=0,0,P47-Q47) -> -2
A48: 50 | B48: FINANCE | D48: All Payment page API work | E48: API | F48: COMPLETE | J48: 45378 | K48: 45397 | L48: 45378 | M48: 45388 | N48: =IF(L48="",IF(M46="",O46+1,M46+1),L48) -> 45378 | O48: =IF(N48="","",N48+P48-1) -> 45397 | P48: =IF(IF(J48="",0,IF(K48="",0,K48-J48))="",0,K48-J48+1) -> 20 | Q48: =IF(L48="",0,IF(M48="",TODAY()-L48,M48-L48+1)) -> 11 | R48: =IF(Q48=0,0,P48-Q48) -> 9
A49: 51 | B49: FINANCE | D49: Working on Payment pending Modal page | E49: API | F49: LIVE | J49: 45388 | K49: 45390 | L49: 45388 | M49: 45399 | N49: =IF(L49="",IF(M47="",O47+1,M47+1),L49) -> 45388 | O49: =IF(N49="","",N49+P49-1) -> 45390 | P49: =IF(IF(J49="",0,IF(K49="",0,K49-J49))="",0,K49-J49+1) -> 3 | Q49: =IF(L49="",0,IF(M49="",TODAY()-L49,M49-L49+1)) -> 12 | R49: =IF(Q49=0,0,P49-Q49) -> -9
A50: 52 | D50: Some research related to FinTech Service (given by K.K sir ) | E50: OTHER | F50: COMPLETE | J50: 45397 | K50: 45398 | L50: 45399 | M50: 45399 | N50: =IF(L50="",IF(M48="",O48+1,M48+1),L50) -> 45399 | O50: =IF(N50="","",N50+P50-1) -> 45400 | P50: =IF(IF(J50="",0,IF(K50="",0,K50-J50))="",0,K50-J50+1) -> 2 | Q50: =IF(L50="",0,IF(M50="",TODAY()-L50,M50-L50+1)) -> 1 | R50: =IF(Q50=0,0,P50-Q50) -> 1
A51: 53 | B51: FINANCE | C51: PFR REPORT | D51: PFR section all excel and other payment request trail | E51: IMPROVEMENT | F51: LIVE | J51: 45398 | K51: 45399 | L51: 45399 | M51: 45405 | N51: =IF(L51="",IF(M49="",O49+1,M49+1),L51) -> 45399 | O51: =IF(N51="","",N51+P51-1) -> 45400 | P51: =IF(IF(J51="",0,IF(K51="",0,K51-J51))="",0,K51-J51+1) -> 2 | Q51: =IF(L51="",0,IF(M51="",TODAY()-L51,M51-L51+1)) -> 7 | R51: =IF(Q51=0,0,P51-Q51) -> -5
A52: 55 | B52: FINANCE | D52: Supplier invoice Billied Value and Total value backend chagnes (435) recoreds | E52: OTHER | F52: HOLD | J52: 45405 | K52: 45405 | L52: 45405
A53: 56 | B53: FINANCE | C53: VENDER INVOICEPROCESSIING | D53: parallel approval for vendor payment request. | E53: IMPROVEMENT | F53: DEV COMPLETE | J53: 45407 | K53: 45409 | L53: 45407 | M53: 45415
A54: 97 | B54: FINANCE | D54: Finance Report ( Rectification listing amount and ledger amount miss match) rectification work. | F54: LIVE | J54: 45411 | K54: 45417 | L54: 45411 | M54: 45426
A55: 98 | B55: FINANCE | D55: Vendor invoice testing issue report solving | E55: TESTING ISSUE | F55: COMPLETE | J55: 45426 | K55: 45427 | L55: 45426 | M55: 45428
A56: 99 | B56: HR | D56: Pending approvals HR section review and Design analysis | E56: OTHER | F56: COMPLETE | J56: 45428 | K56: 45430 | L56: 45428 | M56: 45433
A57: 101 | B57: FINANCE | D57: Vendor invoice testing issue report solving | E57: TESTING ISSUE | F57: COMPLETE | J57: 45426 | K57: 45427 | L57: 45426 | M57: 45428
A58: 100 | B58: OTHER | D58: New pending approval Count and Finance listing part | E58: IMPROVEMENT | F58: COMPLETE | J58: 45433 | K58: 45437 | L58: 45433
A59: 101 | B59: OTHER | D59: Pending count function creation with old sql query optimization of (Tender, Purchase, Expense) For new pending approval | E59: IMPROVEMENT | F59: INPROGRESS | J59: 45443 | K59: 45448 | L59: 45443
A60: 102 | B60: FINANCE | D60: Additional Invoice without PO | E60: FORM | F60: TO-DO
A61: 103 | B61: FINANCE | D61: Mrn,Lc,Cheque Link In Payment | E61: IMPROVEMENT | F61: TO-DO
A62: 104 | B62: TGT VS ACV | D62: Dynamic approval implementation in target achievement module | E62: 2ND PHASE | F62: TO-DO

Sheet RAKESH
Q3: =SUM(Q5:Q1014) -> 179 | R3: =SUM(R5:R1014) -> 287 | S3: =SUM(S5:S1014) -> -108
A4: SL.NO. | B4: MODULE | C4: SUB MODULE | D4: SUB SUB MODULE | E4: ACTIVITIES | F4: WORK TYPE | G4: STATUS | H4: APPROVAL | I4: RESTRICTION | J4: NOTIFICATION | K4: TGT ST DATE | L4: TGT END DATE | M4: ACT ST DATE | N4: ACT END DATE | O4: PROB ST DT | P4: PROB END DT | Q4: TGT DUR | R4: ACT DUR | S4: T SAVING | T4: DELAY REASON STATUS | U4: REMARKES
A5: =ROW() - 4 -> 1 | B5: MASTER | C5: INPUTER MATRIX | E5: Inputer Matrix | F5: 2ND PHASE | G5: HOLD | K5: 45021 | L5: 45036 | M5: 45021 | N5: 45036 | O5: =M5 -> 45021 | P5: =O5+Q5-1 -> 45036 | Q5: =IF(IF(K5="",0,IF(L5="",0,L5-K5))="",0,L5-K5+1) -> 16 | R5: =IF(M5="",0,IF(N5="",TODAY()-M5,N5-M5+1)) -> 16 | S5: =IF(R5=0,0,Q5-R5) -> 0
A6: =ROW() - 4 -> 2 | B6: MASTER GENERAL | C6: MANAGE CUSTOMER | E6: Manage Customer Listing | F6: 2ND PHASE | G6: LIVE | K6: 45049 | L6: 45061 | M6: 45050 | N6: 45075 | O6: =IF(M6="",IF(N5="",P5+1,N5+1),M6) -> 45050 | P6: =IF(O6="","",O6+Q6-1) -> 45062 | Q6: =IF(IF(K6="",0,IF(L6="",0,L6-K6))="",0,L6-K6+1) -> 13 | R6: =IF(M6="",0,IF(N6="",TODAY()-M6,N6-M6+1)) -> 26 | S6: =IF(R6=0,0,Q6-R6) -> -13
A7: =ROW() - 4 -> 3 | B7: MASTER GENERAL | C7: MANAGE CREADITOR | E7: Manage Creditor Listing | F7: 2ND PHASE | G7: COMPLETE | K7: =L6+1 -> 45062 | L7: =K7+12 -> 45074 | M7: 45076 | N7: 45093 | O7: =IF(M7="",IF(N6="",P6+1,N6+1),M7) -> 45076 | P7: =IF(O7="","",O7+Q7-1) -> 45088 | Q7: =IF(IF(K7="",0,IF(L7="",0,L7-K7))="",0,L7-K7+1) -> 13 | R7: =IF(M7="",0,IF(N7="",TODAY()-M7,N7-M7+1)) -> 18 | S7: =IF(R7=0,0,Q7-R7) -> -5
A8: =ROW() - 4 -> 4 | B8: MASTER GENERAL | C8: MANAGE CUSTOMER | E8: Testing Issue Of Manage Customer, Creditor | F8: TESTING ISSUE | G8: COMPLETE | K8: 45077 | L8: 45078 | M8: 45091 | N8: 45093 | O8: =IF(M8="",IF(N7="",P7+1,N7+1),M8) -> 45091 | P8: =IF(O8="","",O8+Q8-1) -> 45092 | Q8: =IF(IF(K8="",0,IF(L8="",0,L8-K8))="",0,L8-K8+1) -> 2 | R8: =IF(M8="",0,IF(N8="",TODAY()-M8,N8-M8+1)) -> 3 | S8: =IF(R8=0,0,Q8-R8) -> -1
A9: =ROW() - 4 -> 5 | B9: RENT | E9: Dynamic Approval Functionality In Rent Module . | G9: HOLD | K9: 45094 | L9: 45096 | M9: 45094 | N9: 45096 | O9: =IF(M9="",IF(N8="",P8+1,N8+1),M9) -> 45094 | P9: =IF(O9="","",O9+Q9-1) -> 45096 | Q9: =IF(IF(K9="",0,IF(L9="",0,L9-K9))="",0,L9-K9+1) -> 3 | R9: =IF(M9="",0,IF(N9="",TODAY()-M9,N9-M9+1)) -> 3 | S9: =IF(R9=0,0,Q9-R9) -> 0
A10: =ROW() - 4 -> 6 | B10: RENT | C10: RENT CLOSER | E10: Close Functionality (Rent Closure) In Rent Section (Entry Part) | G10: COMPLETE | K10: 45087 | L10: 45090 | M10: 45087 | N10: 45090 | O10: =IF(M10="",IF(N9="",P9+1,N9+1),M10) -> 45087 | P10: =IF(O10="","",O10+Q10-1) -> 45090 | Q10: =IF(IF(K10="",0,IF(L10="",0,L10-K10))="",0,L10-K10+1) -> 4 | R10: =IF(M10="",0,IF(N10="",TODAY()-M10,N10-M10+1)) -> 4 | S10: =IF(R10=0,0,Q10-R10) -> 0
A11: =ROW() - 4 -> 7 | B11: RENT | C11: RENT DETAILS | E11: Show Approval Trail In Rent View Page. | G11: COMPLETE | K11: 45090 | L11: 45090 | M11: 45090 | N11: 45090 | O11: =IF(M11="",IF(N10="",P10+1,N10+1),M11) -> 45090 | P11: =IF(O11="","",O11+Q11-1) -> 45090 | Q11: =IF(IF(K11="",0,IF(L11="",0,L11-K11))="",0,L11-K11+1) -> 1 | R11: =IF(M11="",0,IF(N11="",TODAY()-M11,N11-M11+1)) -> 1 | S11: =IF(R11=0,0,Q11-R11) -> 0
A12: =ROW() - 4 -> 8 | B12: MASTER GENERAL | C12: MANAGE CUSTOMER | E12: Dynamic Approval Link With Manage Customer | F12: 2ND PHASE | G12: LIVE | K12: =L11+1 -> 45091 | L12: =K12+15 -> 45106 | M12: 45110 | N12: 45145 | O12: =IF(M12="",IF(N11="",P11+1,N11+1),M12) -> 45110 | P12: =IF(O12="","",O12+Q12-1) -> 45125 | Q12: =IF(IF(K12="",0,IF(L12="",0,L12-K12))="",0,L12-K12+1) -> 16 | R12: =IF(M12="",0,IF(N12="",TODAY()-M12,N12-M12+1)) -> 36 | S12: =IF(R12=0,0,Q12-R12) -> -20
A13: =ROW() - 4 -> 9 | B13: HI-TOMI | E13: Excel Download In The Hi-Tomi | G13: LIVE | K13: 45147 | L13: 45150 | M13: 45148 | N13: 45148 | O13: =IF(M13="",IF(N12="",P12+1,N12+1),M13) -> 45148 | P13: =IF(O13="","",O13+Q13-1) -> 45151 | Q13: =IF(IF(K13="",0,IF(L13="",0,L13-K13))="",0,L13-K13+1) -> 4 | R13: =IF(M13="",0,IF(N13="",TODAY()-M13,N13-M13+1)) -> 1 | S13: =IF(R13=0,0,Q13-R13) -> 3
A14: =ROW() - 4 -> 10 | B14: MASTER GENERAL | C14: MANAGE CREADITOR | E14: Dynamic Approval Link With Manage Creditor | F14: 2ND PHASE | G14: TESTING | K14: 45150 | L14: 45155 | M14: 45150 | N14: 45163 | O14: =IF(M14="",IF(N13="",P13+1,N13+1),M14) -> 45150 | P14: =IF(O14="","",O14+Q14-1) -> 45155 | Q14: =IF(IF(K14="",0,IF(L14="",0,L14-K14))="",0,L14-K14+1) -> 6 | R14: =IF(M14="",0,IF(N14="",TODAY()-M14,N14-M14+1)) -> 14 | S14: =IF(R14=0,0,Q14-R14) -> -8
A15: =ROW() - 4 -> 11 | B15: MASTER | C15: MANAGE CREADITOR | E15: Manage Creditor Testing Issue Fix | F15: 2ND PHASE | G15: COMPLETE | K15: 45173 | L15: 45179 | M15: 45174 | N15: 45178 | O15: =IF(M15="",IF(N14="",P14+1,N14+1),M15) -> 45174 | P15: =IF(O15="","",O15+Q15-1) -> 45180 | Q15: =IF(IF(K15="",0,IF(L15="",0,L15-K15))="",0,L15-K15+1) -> 7 | R15: =IF(M15="",0,IF(N15="",TODAY()-M15,N15-M15+1)) -> 5 | S15: =IF(R15=0,0,Q15-R15) -> 2
A16: =ROW() - 4 -> 12 | B16: MASTER | C16: MANAGE CUSTOMER | E16: Manage Customer In Pending Approval | F16: 2ND PHASE | G16: COMPLETE | K16: 45180 | L16: 45183 | M16: 45180 | N16: 45183 | O16: =IF(M16="",IF(N15="",P15+1,N15+1),M16) -> 45180 | P16: =IF(O16="","",O16+Q16-1) -> 45183 | Q16: =IF(IF(K16="",0,IF(L16="",0,L16-K16))="",0,L16-K16+1) -> 4 | R16: =IF(M16="",0,IF(N16="",TODAY()-M16,N16-M16+1)) -> 4 | S16: =IF(R16=0,0,Q16-R16) -> 0
A17: =ROW() - 4 -> 13 | B17: MASTER | C17: MANAGE CREADITOR | E17: Manage Creditor In Pending Approval (All Four Section ) | F17: 2ND PHASE | G17: COMPLETE | K17: =L16+1 -> 45184 | L17: =K17+6 -> 45190 | M17: 45184 | N17: =M17+1 -> 45185 | O17: =IF(M17="",IF(N16="",P16+1,N16+1),M17) -> 45184 | P17: =IF(O17="","",O17+Q17-1) -> 45190 | Q17: =IF(IF(K17="",0,IF(L17="",0,L17-K17))="",0,L17-K17+1) -> 7 | R17: =IF(M17="",0,IF(N17="",TODAY()-M17,N17-M17+1)) -> 2 | S17: =IF(R17=0,0,Q17-R17) -> 5
A18: =ROW() - 4 -> 14 | B18: MASTER | C18: MANAGE CREADITOR | D18: Documentatation | E18: Documentation Of Manage Creditor | F18: 2ND PHASE | G18: COMPLETE | K18: 45185 | L18: 45191 | M18: 45185 | N18: 45191 | O18: =IF(M18="",IF(N17="",P17+1,N17+1),M18) -> 45185 | P18: =IF(O18="","",O18+Q18-1) -> 45191 | Q18: =IF(IF(K18="",0,IF(L18="",0,L18-K18))="",0,L18-K18+1) -> 7 | R18: =IF(M18="",0,IF(N18="",TODAY()-M18,N18-M18+1)) -> 7 | S18: =IF(R18=0,0,Q18-R18) -> 0
A19: =ROW() - 4 -> 15 | B19: MASTER | E19: Pagination In Creditor'S Supplier Section | G19: IN COMPLETE | K19: 45246 | L19: 45252 | M19: 45250 | N19: 45253 | O19: =IF(M19="",IF(N18="",P18+1,N18+1),M19) -> 45250 | P19: =IF(O19="","",O19+Q19-1) -> 45256 | Q19: =IF(IF(K19="",0,IF(L19="",0,L19-K19))="",0,L19-K19+1) -> 7 | R19: =IF(M19="",0,IF(N19="",TODAY()-M19,N19-M19+1)) -> 4 | S19: =IF(R19=0,0,Q19-R19) -> 3 | U19: RE ASSIGNED TO SAILESH
A20: =ROW() - 4 -> 16 | B20: FINANCE | C20: All security type | D20: BG processing | E20: BG Processing new desigh implementation with dynamic approval | F20: 2ND PHASE | G20: RETURN TO DEV | K20: 45251 | L20: 45259 | M20: 45253 | N20: 45295 | O20: =IF(M20="",IF(N19="",P19+1,N19+1),M20) -> 45253 | P20: =IF(O20="","",O20+Q20-1) -> 45261 | Q20: =IF(IF(K20="",0,IF(L20="",0,L20-K20))="",0,L20-K20+1) -> 9 | R20: =IF(M20="",0,IF(N20="",TODAY()-M20,N20-M20+1)) -> 43 | S20: =IF(R20=0,0,Q20-R20) -> -34 | U20: DEVELOPER IS ON LEAVE
A21: =ROW() - 4 -> 17 | B21: MASTER | C21: General | D21: Manage creditor | E21: Modifications in supplier, vendor, transport, other of manage creditor with dynamic approval | F21: 2ND PHASE | G21: TESTING | K21: 45290 | L21: 45297 | M21: 45295 | N21: 45309 | O21: =IF(M21="",IF(N20="",P20+1,N20+1),M21) -> 45295 | P21: =IF(O21="","",O21+Q21-1) -> 45302 | Q21: =IF(IF(K21="",0,IF(L21="",0,L21-K21))="",0,L21-K21+1) -> 8 | R21: =IF(M21="",0,IF(N21="",TODAY()-M21,N21-M21+1)) -> 15 | S21: =IF(R21=0,0,Q21-R21) -> -7
A22: 18 | B22: FINANCE | C22: CHARITY | E22: Charity 2nd stage design implementation | F22: 2ND PHASE DESIGN | G22: DEV COMPLETE | K22: 45306 | L22: 45309 | M22: 45309 | N22: 45315 | O22: =IF(M22="",IF(N21="",P21+1,N21+1),M22) -> 45309 | P22: =IF(O22="","",O22+Q22-1) -> 45312 | Q22: =IF(IF(K22="",0,IF(L22="",0,L22-K22))="",0,L22-K22+1) -> 4 | R22: =IF(M22="",0,IF(N22="",TODAY()-M22,N22-M22+1)) -> 7 | S22: =IF(R22=0,0,Q22-R22) -> -3
A23: 19 | B23: FINANCE | C23: BG PROCESSING | D23: Documentatation | E23: Documentation of BG processing by ER diagram | F23: 2ND PHASE DESIGN | G23: COMPLETE | K23: 45309 | L23: 45310 | M23: 45310 | N23: 45310 | O23: =IF(M23="",IF(N22="",P22+1,N22+1),M23) -> 45310 | P23: =IF(O23="","",O23+Q23-1) -> 45311 | Q23: =IF(IF(K23="",0,IF(L23="",0,L23-K23))="",0,L23-K23+1) -> 2 | R23: =IF(M23="",0,IF(N23="",TODAY()-M23,N23-M23+1)) -> 1 | S23: =IF(R23=0,0,Q23-R23) -> 1
A24: 20 | B24: IRUS | E24: Segregate Expense Module | G24: COMPLETE | K24: 45313 | L24: 45316 | M24: 45315 | N24: 45324 | O24: =IF(M24="",IF(N23="",P23+1,N23+1),M24) -> 45315 | P24: =IF(O24="","",O24+Q24-1) -> 45318 | Q24: =IF(IF(K24="",0,IF(L24="",0,L24-K24))="",0,L24-K24+1) -> 4 | R24: =IF(M24="",0,IF(N24="",TODAY()-M24,N24-M24+1)) -> 10 | S24: =IF(R24=0,0,Q24-R24) -> -6
A25: 21 | B25: FINANCE | C25: BG PROCESSING | E25: New edit page creation in bg processing | G25: DEV COMPLETE | K25: 45313 | L25: 45318 | M25: 45327 | N25: 45328 | O25: =IF(M25="",IF(N24="",P24+1,N24+1),M25) -> 45327 | P25: =IF(O25="","",O25+Q25-1) -> 45332 | Q25: =IF(IF(K25="",0,IF(L25="",0,L25-K25))="",0,L25-K25+1) -> 6 | R25: =IF(M25="",0,IF(N25="",TODAY()-M25,N25-M25+1)) -> 2 | S25: =IF(R25=0,0,Q25-R25) -> 4
A26: 22 | B26: MASTER | C26: MANAGE CUSTOMER | E26: Modifications in manage customer | G26: COMPLETE | K26: 45328 | L26: 45330 | M26: 45334 | N26: 45335 | O26: =IF(M26="",IF(N25="",P25+1,N25+1),M26) -> 45334 | P26: =IF(O26="","",O26+Q26-1) -> 45336 | Q26: =IF(IF(K26="",0,IF(L26="",0,L26-K26))="",0,L26-K26+1) -> 3 | R26: =IF(M26="",0,IF(N26="",TODAY()-M26,N26-M26+1)) -> 2 | S26: =IF(R26=0,0,Q26-R26) -> 1
A27: 23 | B27: MASTER | C27: MANAGE CREADITOR | E27: Manage creaditor testing issue fix | F27: TESTING ISSUE | G27: COMPLETE | K27: 45328 | L27: 45330 | M27: 45334 | N27: 45335 | O27: =IF(M27="",IF(N26="",P26+1,N26+1),M27) -> 45334 | P27: =IF(O27="","",O27+Q27-1) -> 45336 | Q27: =IF(IF(K27="",0,IF(L27="",0,L27-K27))="",0,L27-K27+1) -> 3 | R27: =IF(M27="",0,IF(N27="",TODAY()-M27,N27-M27+1)) -> 2 | S27: =IF(R27=0,0,Q27-R27) -> 1
A28: 24 | B28: FINANCE | C28: BG processing | E28: Changes in bg processing | F28: TESTING ISSUE | G28: COMPLETE | K28: 45344 | L28: 45344 | M28: 45345 | N28: 45346 | O28: =IF(M28="",IF(N27="",P27+1,N27+1),M28) -> 45345 | P28: =IF(O28="","",O28+Q28-1) -> 45345 | Q28: =IF(IF(K28="",0,IF(L28="",0,L28-K28))="",0,L28-K28+1) -> 1 | R28: =IF(M28="",0,IF(N28="",TODAY()-M28,N28-M28+1)) -> 2 | S28: =IF(R28=0,0,Q28-R28) -> -1
A29: 25 | B29: HI-TOMI | C29: RECENTLY UPDATED HI TOMI LIST | E29: New design implementation in hi tomi (RECENTLY UPDATED HI TOMI LIST) | F29: 2ND PHASE DESIGN | G29: HOLD | K29: 45348 | L29: 45350 | M29: 45349 | S29: =IF(R29=0,0,Q29-R29) -> 0
A30: 26 | B30: HI-TOMI | C30: ASSIGNED BY ME | D30: ALL HITOMI | E30: Code optimization and implementation of new design in All HI TOMI List Assigned By Me | F30: 2ND PHASE DESIGN | G30: HOLD | K30: 45356 | L30: 45358 | M30: 45356 | S30: =IF(R30=0,0,Q30-R30) -> 0
A31: 27 | B31: IRUS | E31: Modification in finance security in irus erp | F31: OTHER | G31: COMPLETE | K31: 45362 | L31: 45364 | M31: 45364 | N31: 45367 | O31: =IF(M31="",IF(N30="",P30+1,N30+1),M31) -> 45364 | P31: =IF(O31="","",O31+Q31-1) -> 45366 | Q31: =IF(IF(K31="",0,IF(L31="",0,L31-K31))="",0,L31-K31+1) -> 3 | R31: =IF(M31="",0,IF(N31="",TODAY()-M31,N31-M31+1)) -> 4 | S31: =IF(R31=0,0,Q31-R31) -> -1
A32: 28 | B32: HI-TOMI | C32: ASSIGNED BY ME | D32: OPENED HITOMI | E32: Code optimization and implementatin of new dsign in All Opened HITOMI List Assigned By Me | F32: 2ND PHASE DESIGN | G32: TESTING | K32: 45366 | L32: 45367 | M32: 45367 | N32: 45367 | O32: =IF(M32="",IF(N31="",P31+1,N31+1),M32) -> 45367 | P32: =IF(O32="","",O32+Q32-1) -> 45368 | Q32: =IF(IF(K32="",0,IF(L32="",0,L32-K32))="",0,L32-K32+1) -> 2 | R32: =IF(M32="",0,IF(N32="",TODAY()-M32,N32-M32+1)) -> 1 | S32: =IF(R32=0,0,Q32-R32) -> 1
A33: 29 | B33: HI-TOMI | C33: ASSIGNED BY ME | D33: CLOSED HITOMI | E33: code optimization and implementation of new design in All Closed HITOMI List Assigned By Me | F33: 2ND PHASE DESIGN | G33: TESTING | K33: 45366 | L33: 45367 | M33: 45367 | N33: 45367 | O33: =IF(M33="",IF(N32="",P32+1,N32+1),M33) -> 45367 | P33: =IF(O33="","",O33+Q33-1) -> 45368 | Q33: =IF(IF(K33="",0,IF(L33="",0,L33-K33))="",0,L33-K33+1) -> 2 | R33: =IF(M33="",0,IF(N33="",TODAY()-M33,N33-M33+1)) -> 1 | S33: =IF(R33=0,0,Q33-R33) -> 1
A34: 30 | B34: HI-TOMI | C34: ASSIGNED BY ME | E34: Fixing issues of pending hitomi assigned by me (reassign to me from soumya task) | F34: ISSUE FIX | G34: DEV COMPLETE | K34: 45369 | L34: 45369 | M34: 45369 | N34: 45373 | O34: =IF(M34="",IF(N33="",P33+1,N33+1),M34) -> 45369 | P34: =IF(O34="","",O34+Q34-1) -> 45369 | Q34: =IF(IF(K34="",0,IF(L34="",0,L34-K34))="",0,L34-K34+1) -> 1 | R34: =IF(M34="",0,IF(N34="",TODAY()-M34,N34-M34+1)) -> 5 | S34: =IF(R34=0,0,Q34-R34) -> -4
A35: 31 | B35: FINANCE | C35: BG processing | E35: Fixing Issue in bg processing of devlopment server and also in manage creaditor issue fixing. | F35: ISSUE FIX | G35: COMPLETE | K35: 45371 | L35: 45371 | M35: 45371 | N35: 45373 | O35: =IF(M35="",IF(N34="",P34+1,N34+1),M35) -> 45371 | P35: =IF(O35="","",O35+Q35-1) -> 45371 | Q35: =IF(IF(K35="",0,IF(L35="",0,L35-K35))="",0,L35-K35+1) -> 1 | R35: =IF(M35="",0,IF(N35="",TODAY()-M35,N35-M35+1)) -> 3 | S35: =IF(R35=0,0,Q35-R35) -> -2
A36: 32 | B36: SALES | E36: Testing Segregated Finance module in my local and issue solving in manage creditor | F36: ISSUE FIX | G36: COMPLETE | K36: 45374 | L36: 45376 | M36: 45379 | N36: 45384 | O36: =IF(M36="",IF(N35="",P35+1,N35+1),M36) -> 45379 | P36: =IF(O36="","",O36+Q36-1) -> 45381 | Q36: =IF(IF(K36="",0,IF(L36="",0,L36-K36))="",0,L36-K36+1) -> 3 | R36: =IF(M36="",0,IF(N36="",TODAY()-M36,N36-M36+1)) -> 6 | S36: =IF(R36=0,0,Q36-R36) -> -3
A37: 33 | B37: FINANCE | C37: All security type | D37: EMD processing | E37: EMD processing dynamic approval | F37: 2ND PHASE DESIGN | G37: DEV COMPLETE | K37: 45381 | L37: 45387 | M37: 45381 | N37: 45399 | O37: =IF(M37="",IF(N36="",P36+1,N36+1),M37) -> 45381 | P37: =IF(O37="","",O37+Q37-1) -> 45387 | Q37: =IF(IF(K37="",0,IF(L37="",0,L37-K37))="",0,L37-K37+1) -> 7 | R37: =IF(M37="",0,IF(N37="",TODAY()-M37,N37-M37+1)) -> 19 | S37: =IF(R37=0,0,Q37-R37) -> -12
